Workbook

Sheet Лист1

Sheet Дела
A1: № | B1: E-mail | C1: Телефон | D1: Сайт ответчика | E1: Ссылка на дело | F1: Номер дела | G1: Истец сокращенно | H1: ИНН Истца | I1: Ответчик сокращенно | J1: ИНН Ответчика | K1: Руководитель ответчика | L1: ИНН руководителя ответчика | M1: Сумма иска | N1: Дата подачи иска | O1: всего, судебных дел по данному ответчику | P1: Адрес ответчика | Q1: Cуд | R1: ОКВЕД Ответчика | S1: Наименование истца | T1: Ссылка на истца | U1: Наименование ответчика | V1: Ссылка на ответчика | W1: Последний акт
A2: =SUBTOTAL(103,$F$1:F2)-1 -> 1 | B2: ovchin_nn@mail.ru | C2: +7 (910) 131-18-94_x000D_ +7 (910) 143-33-00 | E2: https://kad.arbitr.ru/Card/5472b022-160c-4aab-b9b4-0d8e51681078 | F2: А40-34987/2024 | G2: ООО "Комплексная Безопасность" | H2: 5038076713 | I2: ООО "Артал Строй" | J2: 5262277538 | K2: Родионов Артем Игоревич | L2: 526211125912 | M2: 4489799 | N2: 45342 | O2: 1 | P2: 607687, Нижегородская область, Кстовский район, село Ближнее Борисово, Школьная ул, д. 18, офис 2 | Q2: АС города Москвы | R2: Производство электромонтажных, санитарно-технических и прочих строительно-монтажных работ (43.2) | S2: ОБЩЕСТВО С ОГРАНИЧЕННОЙ ОТВЕТСТВЕННОСТЬЮ "КОМПЛЕКСНАЯ БЕЗОПАСНОСТЬ" | U2: ОБЩЕСТВО С ОГРАНИЧЕННОЙ ОТВЕТСТВЕННОСТЬЮ "АРТАЛ СТРОЙ" | W2: Заявление Исковое заявление
A3: =SUBTOTAL(103,$F$1:F3)-1 -> 2 | B3: az8767@yandex.ru | E3: https://kad.arbitr.ru/Card/ad2a085e-f257-47b0-aa45-3b5f9b2ccdf9 | F3: А40-34970/2024 | G3: ИФНС России № 10 по Г. Москве | H3: 7710047253 | I3: ООО "Фортуна" | J3: 9710110269 | K3: Ооржак Олча Май Оглу | L3: 171802124419 | M3: 3174989.9 | N3: 45342 | O3: 1 | P3: 125375, город Москва, Козицкий пер, д. 1а стр. 2, помещ. 3/3 | Q3: АС города Москвы | R3: Деятельность по комплексному обслуживанию помещений (81.10) | S3: ИНСПЕКЦИЯ ФЕДЕРАЛЬНОЙ НАЛОГОВОЙ СЛУЖБЫ № 10 ПО Г. МОСКВЕ | U3: ОБЩЕСТВО С ОГРАНИЧЕННОЙ ОТВЕТСТВЕННОСТЬЮ "ФОРТУНА" | W3: Определение О принятии заявления о признании должника банкротом
A4: =SUBTOTAL(103,$F$1:F4)-1 -> 3 | B4: rzd@rzd.ru_x000D_ poddymnikovaov@wsr.ru_x000D_ DKRE-Mahalov@kbsh.rzd.ru_x000D_ dtv-3.rzd@bk.ru_x000D_ echekunova@skzd.rzd.ru_x000D_ EPBelenkaiakr@skzd.rzd.ru_x000D_ fax@css.rzd.ru_x000D_ gorkdmkadr@gmail.com_x000D_ kuzmenkovagv@center.rzd.ru_x000D_ mivc@mzd.ru_x000D_ mrzd_KostrovaSA@orw.ru_x000D_ NEKolesnikova@serw.ru_x000D_ Ngs_s@svrw.ru_x000D_ sevtcfto@yandex.ru_x000D_ TuizovaTA@mail.zabtrans.ru | C4: +7 (499) 262-99-01_x000D_ +7 (499) 262-10-02_x000D_ 8 (800) 775-00-00_x000D_ +7 (4852) 52-18-30_x000D_ +7 (3012) 28-25-04_x000D_ +7 (3022) 22-33-05_x000D_ +7 (3022) 22-46-03_x000D_ +7 (3022) 22-46-72_x000D_ +7 (3022) 22-75-05_x000D_ +7 (3022) 24-18-00_x000D_ +7 (3022) 24-22-25_x000D_ +7 (3022) 24-45-58_x000D_ +7 (30241) 2-40-54_x000D_ +7 (342) 230-22-25_x000D_ +7 (343) 358-22-25_x000D_ +7 (343) 358-22-60_x000D_ +7 (343) 358-29-32_x000D_ +7 (343) 358-40-88_x000D_ +7 (343) 358-44-00_x000D_ +7 (343) 358-48-10_x000D_ +7 (343) 358-48-48_x000D_ +7 (343) 358-48-89_x000D_ +7 (343) 358-57-27_x000D_ +7 (343) 380-14-74_x000D_ +7 (343) 380-17-54_x000D_ +7 (3435) 49-42-39_x000D_ +7 (3452) 52-31-40_x000D_ +7 (3452) 52-38-48_x000D_ +7 (3462) 39-35-33_x000D_ +7 (347) 229-63-15_x000D_ +7 (347) 253-14-52_x000D_ +7 (351) 259-29-04_x000D_ +7 (351) 263-84-82_x000D_ +7 (351) 268-21-40_x000D_ +7 (351) 268-39-12_x000D_ +7 (351) 268-65-09_x000D_ +7 (3513) 69-21-40_x000D_ +7 (3812) 44-30-79_x000D_ +7 (383) 229-20-20_x000D_ +7 (383) 229-36-02_x000D_ +7 (383) 229-48-02_x000D_ +7 (383) 229-50-27_x000D_ +7 (383) 334-02-43_x000D_ +7 (3842) 32-23-79_x000D_ +7 (3842) 32-39-50_x000D_ +7 (3852) 29-20-48_x000D_ +7 (3902) 29-45-66_x000D_ +7 (3912) 23-13-28_x000D_ +7 (3912) 48-04-35_x000D_ +7 (3912) 48-05-59_x000D_ +7 (3912) 59-52-98_x000D_ +7 (3952) 63-22-46_x000D_ +7 (3952) 63-42-66_x000D_ +7 (3952) 63-84-79_x000D_ +7 (3952) 64-42-46_x000D_ +7 (3952) 64-48-48_x000D_ +7 (3952) 64-51-55_x000D_ +7 (3953) 49-79-79_x000D_ +7 (4012) 58-61-01_x000D_ +7 (4012) 58-72-02_x000D_ +7 (41656) 7-20-00_x000D_ +7 (4212) 38-12-27_x000D_ +7 (4212) 38-37-18_x000D_ +7 (4212) 38-38-80_x000D_ +7 (4212) 38-41-36_x000D_ +7 (4212) 38-47-19_x000D_ +7 (4212) 38-48-43_x000D_ +7 (4212) 38-48-48_x000D_ +7 (4212) 38-53-57_x000D_ +7 (4212) 38-81-91_x000D_ +7 (4212) 38-88-34_x000D_ +7 (4712) 55-23-00_x000D_ +7 (4712) 55-57-54_x000D_ +7 (4722) 76-03-04_x000D_ +7 (4722) 76-05-25_x000D_ +7 (4732) 48-83-14_x000D_ +7 (4732) 65-08-10_x000D_ +7 (4732) 65-08-28_x000D_ +7 (4732) 65-22-64_x000D_ +7 (4732) 65-23-51_x000D_ +7 (4732) 65-28-32_x000D_ +7 (4732) 65-38-34_x000D_ +7 (4732) 65-44-50_x000D_ +7 (4732) 65-66-22_x000D_ +7 (4732) 65-72-81_x000D_ +7 (47391) 4-17-26_x000D_ +7 (47391) 7-59-64_x000D_ +7 (47545) 3-21-40_x000D_ +7 (47545) 3-22-76_x000D_ +7 (4812) 39-52-25_x000D_ +7 (4842) 78-52-95_x000D_ +7 (4852) 49-50-02_x000D_ +7 (4852) 52-40-86_x000D_ +7 (4852) 52-52-43_x000D_ +7 (4852) 79-22-41_x000D_ +7 (4852) 79-35-60_x000D_ +7 (4852) 79-43-14_x000D_ +7 (4852) 79-44-00_x000D_ +7 (4872) 20-20-80_x000D_ +7 (4872) 20-20-93 | D4: http://www.e-disclosure.ru/portal/company.aspx?id=4543_x000D_ http://www.rzd.ru/_x000D_ http://altaitursib.ru/_x000D_ http://dss-sverdl.ru/_x000D_ http://dzvr.ru/about/structure/_x000D_ http://krw.ru/_x000D_ http://kzd.web.rzd/_x000D_ http://rzd.ru/_x000D_ http://www.cm.rzd.ru/_x000D_ http://www.css-rzd.ru/_x000D_ http://www.kras.rzd.ru/_x000D_ http://www.nrr.cm.rzd.ru/_x000D_ http://www.pkbct.ru/_x000D_ http://www.rmzhoper.ru/_x000D_ http://www.rzd.ru/ent/public/ru?STRUCTURE_ID=5185&amp;layer_id=5554&amp;refererLayerId=5553&amp;id=1015_x000D_ http://www.rzd.ru/ent/public/ru?STRUCTURE_ID=5185&amp;layer_id=5554&amp;refererLayerId=5553&amp;id=4347_x000D_ http://www.trudvsem.ru/_x000D_ http://www.uvzd.rzd.ru/_x000D_ http://www.web.rzd/_x000D_ https://www.list-org.com/go?site=804719 | E4: https://kad.arbitr.ru/Card/6eac2fac-753c-4acd-8fe0-fbcbcbd534ba | F4: А40-34838/2024 | G4: АО "Нефтетранссервис" | H4: 7731537410 | I4: ОАО "РЖД" | J4: 7708503727 | K4: Белозёров Олег Валентинович | L4: 781306504007 | M4: 1118159 | N4: 45342 | O4: 220412 | P4: 107174, город Москва, Новая Басманная ул, д. 2/1 стр. 1 | Q4: АС города Москвы | R4: Деятельность железнодорожного транспорта: грузовые перевозки (49.20) | S4: АКЦИОНЕРНОЕ ОБЩЕСТВО "НЕФТЕТРАНССЕРВИС" | U4: ОТКРЫТОЕ АКЦИОНЕРНОЕ ОБЩЕСТВО "РОССИЙСКИЕ ЖЕЛЕЗНЫЕ ДОРОГИ" | W4: Заявление Исковое заявление
A5: =SUBTOTAL(103,$F$1:F5)-1 -> 4 | C5: +7 (916) 428-25-05 | E5: https://kad.arbitr.ru/Card/e429a3d5-ded7-42bd-a388-6a75c4919dee | F5: А40-34726/2024 | G5: ООО "Акрополь Инжиниринг" | H5: 7706682252 | I5: ООО "НЖС" | J5: 7728420282 | K5: Шевацуков Константин Юрьевич | L5: 010517174225 | M5: 4306490.7 | N5: 45342 | O5: 74 | P5: 115184, город Москва, Большая Татарская ул., д. 35 стр. 3, э 5 п II к 2-4,9 ч/к 1,5,10 | Q5: АС города Москвы | R5: Торговля оптовая лесоматериалами, строительными материалами и санитарно-техническим оборудованием (46.73) | S5: ОБЩЕСТВО С ОГРАНИЧЕННОЙ ОТВЕТСТВЕННОСТЬЮ "АКРОПОЛЬ ИНЖИНИРИНГ" | U5: ОБЩЕСТВО С ОГРАНИЧЕННОЙ ОТВЕТСТВЕННОСТЬЮ "НЖСТРОЙ" | W5: Заявление Исковое заявление
A6: =SUBTOTAL(103,$F$1:F6)-1 -> 5 | E6: https://kad.arbitr.ru/Card/af4fa098-eda4-470d-9bab-7ced56ed221a | F6: А40-34801/2024 | G6: ООО "Екс-Групп" | H6: 7723435782 | I6: ИП Гасангусейнов Вазир Султанович | J6: 052600742828 | K6: Гасангусейнов Вазир Султанович | L6: 052600742828 | M6: 611481 | N6: 45342 | O6: 1 | P6: Калужская область, Жуковский район, город Белоусово | Q6: АС города Москвы | R6: Деятельность легкового такси и арендованных легковых автомобилей с водителем (49.32) | S6: ОБЩЕСТВО С ОГРАНИЧЕННОЙ ОТВЕТСТВЕННОСТЬЮ "ЕКС-ГРУПП" | U6: ИП Гасангусейнов Вазир Султанович | W6: Заявление Исковое заявление
A7: =SUBTOTAL(103,$F$1:F7)-1 -> 6 | C7: +7 (495) 120-28-80 | D7: http://hotsto.ru/ | E7: https://kad.arbitr.ru/Card/be5bb01c-cf29-4565-8732-313c24509676 | F7: А40-34707/2024 | G7: Департамент городского Имущества Города Москвы | H7: 7705031674 | I7: ООО "Горячий Ключ" | J7: 7725457502 | K7: Асгарли Алигулу Ильгар Оглы | L7: 972905922903 | M7: 663120.56 | N7: 45342 | O7: 9 | P7: 125480, город Москва, Туристская ул, д. 20 к. 1, помещ. XVI ком. 3 | Q7: АС города Москвы | R7: Аренда и управление собственным или арендованным недвижимым имуществом (68.20) | S7: ДЕПАРТАМЕНТ ГОРОДСКОГО ИМУЩЕСТВА ГОРОДА МОСКВЫ | U7: ОБЩЕСТВО С ОГРАНИЧЕННОЙ ОТВЕТСТВЕННОСТЬЮ "ГОРЯЧИЙ КЛЮЧ" | W7: Заявление Исковое заявление
A8: =SUBTOTAL(103,$F$1:F8)-1 -> 7 | B8: info@1vrk.ru_x000D_ ovalenkorv@center.rzd.ru_x000D_ alsm_reception@1vrk.ru_x000D_ alzm_reception@1vrk.ru_x000D_ alzm_sokolovaes@1vrk.ru_x000D_ aovrk@mail.ru_x000D_ filatovanb@1vrk.ru_x000D_ grishakovaes@1vrk.ru_x000D_ it@1vrk.ru_x000D_ lydmilka4832@yandex.ru_x000D_ makovaea@irk.esr.ru_x000D_ makovaea@irk.esrr.ru_x000D_ makovaev@irk.esrr.ru_x000D_ makovaeva@irk.esrr.ru_x000D_ martynovaaa@1vrk.ru_x000D_ pl2@mail.ru_x000D_ pl_2@mail.ru_x000D_ posiseevann@1vrk.rzd_x000D_ pl_2bryansk@mail.ru_x000D_ ulan_krivolapovaaa@1vrk.rzd_x000D_ vchd12_komarovaOO@psk.orw.rzd | C8: +7 (499) 260-40-00_x000D_ +7 (4832) 60-55-48_x000D_ +7 (4832) 63-02-26_x000D_ +7 (4832) 60-22-22_x000D_ +7 (3955) 75-57-30_x000D_ +7 (3955) 75-57-33_x000D_ +7 (3955) 76-14-06_x000D_ +7 (499) 262-28-46_x000D_ +7 (950) 089-92-94_x000D_ +7 (3012) 28-21-71_x000D_ +7 (499) 260-40-50_x000D_ +7 (812) 436-61-53_x000D_ +7 (81837) 6-26-43_x000D_ +7 (84663) 2-19-75_x000D_ +7 (863) 259-08-48_x000D_ +7 (914) 176-98-95_x000D_ +7 (3955) 75-57-36_x000D_ +7 (950) 075-17-94_x000D_ +7 (812) 436-61-44_x000D_ +7 (383) 337-94-01_x000D_ +7 (3519) 44-72-22_x000D_ +7 (499) 260-71-22_x000D_ +7 (3012) 28-22-22_x000D_ +7 (3012) 28-22-58_x000D_ +7 (34256) 9-22-22_x000D_ +7 (343) 310-90-69_x000D_ +7 (343) 310-91-65_x000D_ +7 (34551) 5-22-22_x000D_ +7 (34551) 5-26-87_x000D_ +7 (3812) 44-20-61_x000D_ +7 (3812) 44-21-65_x000D_ +7 (3812) 44-99-33_x000D_ +7 (383) 229-92-87_x000D_ +7 (38448) 2-24-39_x000D_ +7 (38456) 7-37-64_x000D_ +7 (39563) 5-32-20_x000D_ +7 (39563) 5-38-40_x000D_ +7 (4212) 38-82-58_x000D_ +7 (4234) 25-30-35_x000D_ +7 (4234) 38-15-35_x000D_ +7 (42355) 4-24-21_x000D_ +7 (4725) 41-17-52_x000D_ +7 (47376) 2-27-34_x000D_ +7 (491) 375-16-26_x000D_ +7 (49644) 2-47-55_x000D_ +7 (49644) 2-55-55_x000D_ +7 (499) 623-51-40_x000D_ +7 (499) 623-51-62_x000D_ +7 (8112) 70-71-11_x000D_ +7 (8112) 70-79-08_x000D_ +7 (81361) 2-01-06_x000D_ +7 (81361) 2-80-04_x000D_ +7 (8142) 79-36-04_x000D_ +7 (8142) 79-36-75_x000D_ +7 (81533) 3-36-04_x000D_ +7 (81533) 4-33-02_x000D_ +7 (8172) 79-69-61_x000D_ +7 (81837) 6-22-22_x000D_ +7 (831) 248-52-22_x000D_ +7 (833) 260-52-22_x000D_ +7 (833) 260-61-00_x000D_ +7 (8412) 58-72-22_x000D_ +7 (8412) 58-72-64_x000D_ +7 (8452) 41-38-69_x000D_ +7 (8452) 41-75-09_x000D_ +7 (846) 303-95-00_x000D_ +7 (846) 303-95-39_x000D_ +7 (8464) 33-32-80, доб 6_x000D_ +7 (8464) 33-38-40, доб 6_x000D_ +7 (84663) 2-19-74_x000D_ +7 (8512) 32-52-55_x000D_ +7 (8612) 14-79-14_x000D_ +7 (863) 259-08-50_x000D_ +7 (863) 259-48-91_x000D_ +7 (86354) 4-54-37_x000D_ +7 (911) 957-27-96_x000D_ +7 (915) 607-33-06_x000D_ +7 (918) 508-91-11_x000D_ +7 (960) 993-79-10_x000D_ +7 (984) 277-02-89_x000D_ +7 (499) 260-00-00_x000D_ +7 (3955) 77-26-10_x000D_ +7 (4832) 60-32-33, доб 7070_x000D_ +7 (4832) 60-39-49_x000D_ +7 (4832) 60-22-56_x000D_ +7 (499) 260-49-09_x000D_ +7 (499) 260-49-66_x000D_ +7 (86354) 4-23-61_x000D_ +7 (499) 262-66-66_x000D_ +7 (846) 303-95-02, доб 303_x000D_ +7 (950) 630-39-53, доб 9_x000D_ +7 (495) 260-40-00_x000D_ +7 (499) 262-00-58_x000D_ +7 (4212) 31-58-56_x000D_ +7 (39173) 9-31-97_x000D_ +7 (846) 303-95-02_x000D_ +7 (812) 457-53-88_x000D_ +7 (812) 436-20-36_x000D_ +7 (911) 848-78-23_x000D_ +7 (499) 260-40-68 | D8: http://1vrk.ru/_x000D_ http://www.1vrk.ru/ | E8: https://kad.arbitr.ru/Card/bcb1cce1-9a5e-4605-a4c7-7b5a5c91dee7 | F8: А40-34588/2024 | G8: АО "Уголь-Транс" | H8: 5047210316 | I8: АО "ВРК-1" | J8: 7708737490 | K8: Белюгин Владимир Николаевич | L8: 614100627878 | M8: 744855.11 | N8: 45342 | O8: 15023 | P8: 129090, город Москва, Каланчевская ул., д.35 | Q8: АС города Москвы | R8: Деятельность вспомогательная, связанная с железнодорожным транспортом (52.21.1) | S8: АКЦИОНЕРНОЕ ОБЩЕСТВО "УГОЛЬ-ТРАНС" | U8: АКЦИОНЕРНОЕ ОБЩЕСТВО "ВАГОННАЯ РЕМОНТНАЯ КОМПАНИЯ - 1" | W8: Заявление Исковое заявление
A9: =SUBTOTAL(103,$F$1:F9)-1 -> 8 | E9: https://kad.arbitr.ru/Card/59ecda4f-b0e5-4a13-98a2-8c43e20e9bfc | F9: А40-34679/2024 | G9: Ассоциация СРО "Центррегион" | H9: 7722309947 | I9: ООО "Бизнес-Капитал" | J9: 7751001635 | K9: Холоднюк Дмитрий Александрович | L9: 730696467315 | M9: 506700 | N9: 45342 | O9: 4 | P9: 142134, город Москва, поселение Рязановское, поселок Знамя Октября, мкр Родники, д. 1, кв. 69 | Q9: АС города Москвы | R9: Производство прочих строительно-монтажных работ (43.29) | S9: АССОЦИАЦИЯ ПО ЗАЩИТЕ ПРАВ И ЗАКОННЫХ ИНТЕРЕСОВ ЛИЦ, ОСУЩЕСТВЛЯЮЩИХ СТРОИТЕЛЬСТВО, САМОРЕГУЛИРУЕМАЯ ОРГАНИЗАЦИЯ "ЦЕНТРРЕГИОН" | U9: ОБЩЕСТВО С ОГРАНИЧЕННОЙ ОТВЕТСТВЕННОСТЬЮ "БИЗНЕС-КАПИТАЛ" | W9: Заявление Исковое заявление
A10: =SUBTOTAL(103,$F$1:F10)-1 -> 9 | B10: gsorokina@moskomzem.ru_x000D_ ageevais@mos.ru_x000D_ barashkovaev@mos.ru_x000D_ dgi@mail.ru_x000D_ dgi@mos.ru_x000D_ dgi_news@mosa.ru_x000D_ kadyrovnn@mos.ru_x000D_ kiti0506@mail.ru_x000D_ mirskovaen@mos.ru_x000D_ polprchuv@cap.ru_x000D_ prusakovayv@mos.ru_x000D_ saraevaei@mos.ru_x000D_ zelao@mail.ru_x000D_ digm@mos.ru | C10: +7 (495) 699-72-50_x000D_ +7 (495) 959-18-02_x000D_ +7 (495) 331-02-22_x000D_ +7 (495) 587-70-87_x000D_ +7 (495) 625-45-13_x000D_ +7 (495) 634-01-27_x000D_ +7 (495) 675-46-24_x000D_ +7 (495) 953-21-56_x000D_ +7 (495) 957-75-00_x000D_ +7 (495) 959-09-75_x000D_ +7 (495) 959-19-03_x000D_ +7 (495) 959-19-13_x000D_ +7 (495) 959-19-59_x000D_ +7 (495) 959-53-39_x000D_ +7 (499) 268-56-70_x000D_ +7 (499) 380-80-84_x000D_ +7 (495) 625-45-15_x000D_ +7 (495) 777-77-77_x000D_ +7 (495) 699-20-48_x000D_ +7 (495) 362-14-63_x000D_ +7 (495) 959-19-82_x000D_ +7 (495) 957-98-53_x000D_ +7 (499) 648-05-64_x000D_ +7 (495) 959-18-88_x000D_ +7 (499) 233-97-39_x000D_ +7 (495) 959-19-55_x000D_ +7 (495) 955-53-08_x000D_ +7 (495) 122-19-27, доб 1302_x000D_ +7 (495) 955-53-79_x000D_ +7 (495) 955-51-96_x000D_ +7 (495) 955-53-68_x000D_ +7 (495) 142-12-32_x000D_ +7 (499) 649-39-23_x000D_ +7 (499) 959-18-02_x000D_ +7 (495) 959-18-22_x000D_ +7 (495) 777-77-77, доб 7_x000D_ +7 (499) 000-00-00_x000D_ +7 (495) 957-99-77 | D10: http://dgi.mos.ru/_x000D_ http://dzr.mos.ru/ | E10: https://kad.arbitr.ru/Card/ab94cc3a-d04c-413f-ac81-57b123fbe265 | F10: А40-34515/2024 | G10: АО "Специализированный Застройщик ТПУ "Рассказовка" | H10: 7701387398 | I10: Департамент городского Имущества Города Москвы | J10: 7705031674 | K10: Гаман Максим Федорович | L10: 691408455881 | M10: 330346000 | N10: 45342 | O10: 72536 | P10: 123112, город Москва, 1-й Красногвардейский пр-д, д. 21 стр. 1 | Q10: АС города Москвы | R10: Деятельность органов государственной власти субъектов Российской Федерации (республик, краев, областей), кроме судебной власти, представительств исполнительных органов государственной власти субъектов Российской Федерации при Президенте Российской Федерации (84.11.21) | S10: АКЦИОНЕРНОЕ ОБЩЕСТВО "СПЕЦИАЛИЗИРОВАННЫЙ ЗАСТРОЙЩИК ТРАНСПОРТНО-ПЕРЕСАДОЧНЫЙ УЗЕЛ "РАССКАЗОВКА" | U10: ДЕПАРТАМЕНТ ГОРОДСКОГО ИМУЩЕСТВА ГОРОДА МОСКВЫ | W10: Заявление Исковое заявление
A11: =SUBTOTAL(103,$F$1:F11)-1 -> 10 | B11: rzd@rzd.ru_x000D_ poddymnikovaov@wsr.ru_x000D_ DKRE-Mahalov@kbsh.rzd.ru_x000D_ dtv-3.rzd@bk.ru_x000D_ echekunova@skzd.rzd.ru_x000D_ EPBelenkaiakr@skzd.rzd.ru_x000D_ fax@css.rzd.ru_x000D_ gorkdmkadr@gmail.com_x000D_ kuzmenkovagv@center.rzd.ru_x000D_ mivc@mzd.ru_x000D_ mrzd_KostrovaSA@orw.ru_x000D_ NEKolesnikova@serw.ru_x000D_ Ngs_s@svrw.ru_x000D_ sevtcfto@yandex.ru_x000D_ TuizovaTA@mail.zabtrans.ru | C11: +7 (499) 262-99-01_x000D_ +7 (499) 262-10-02_x000D_ 8 (800) 775-00-00_x000D_ +7 (4852) 52-18-30_x000D_ +7 (3012) 28-25-04_x000D_ +7 (3022) 22-33-05_x000D_ +7 (3022) 22-46-03_x000D_ +7 (3022) 22-46-72_x000D_ +7 (3022) 22-75-05_x000D_ +7 (3022) 24-18-00_x000D_ +7 (3022) 24-22-25_x000D_ +7 (3022) 24-45-58_x000D_ +7 (30241) 2-40-54_x000D_ +7 (342) 230-22-25_x000D_ +7 (343) 358-22-25_x000D_ +7 (343) 358-22-60_x000D_ +7 (343) 358-29-32_x000D_ +7 (343) 358-40-88_x000D_ +7 (343) 358-44-00_x000D_ +7 (343) 358-48-10_x000D_ +7 (343) 358-48-48_x000D_ +7 (343) 358-48-89_x000D_ +7 (343) 358-57-27_x000D_ +7 (343) 380-14-74_x000D_ +7 (343) 380-17-54_x000D_ +7 (3435) 49-42-39_x000D_ +7 (3452) 52-31-40_x000D_ +7 (3452) 52-38-48_x000D_ +7 (3462) 39-35-33_x000D_ +7 (347) 229-63-15_x000D_ +7 (347) 253-14-52_x000D_ +7 (351) 259-29-04_x000D_ +7 (351) 263-84-82_x000D_ +7 (351) 268-21-40_x000D_ +7 (351) 268-39-12_x000D_ +7 (351) 268-65-09_x000D_ +7 (3513) 69-21-40_x000D_ +7 (3812) 44-30-79_x000D_ +7 (383) 229-20-20_x000D_ +7 (383) 229-36-02_x000D_ +7 (383) 229-48-02_x000D_ +7 (383) 229-50-27_x000D_ +7 (383) 334-02-43_x000D_ +7 (3842) 32-23-79_x000D_ +7 (3842) 32-39-50_x000D_ +7 (3852) 29-20-48_x000D_ +7 (3902) 29-45-66_x000D_ +7 (3912) 23-13-28_x000D_ +7 (3912) 48-04-35_x000D_ +7 (3912) 48-05-59_x000D_ +7 (3912) 59-52-98_x000D_ +7 (3952) 63-22-46_x000D_ +7 (3952) 63-42-66_x000D_ +7 (3952) 63-84-79_x000D_ +7 (3952) 64-42-46_x000D_ +7 (3952) 64-48-48_x000D_ +7 (3952) 64-51-55_x000D_ +7 (3953) 49-79-79_x000D_ +7 (4012) 58-61-01_x000D_ +7 (4012) 58-72-02_x000D_ +7 (41656) 7-20-00_x000D_ +7 (4212) 38-12-27_x000D_ +7 (4212) 38-37-18_x000D_ +7 (4212) 38-38-80_x000D_ +7 (4212) 38-41-36_x000D_ +7 (4212) 38-47-19_x000D_ +7 (4212) 38-48-43_x000D_ +7 (4212) 38-48-48_x000D_ +7 (4212) 38-53-57_x000D_ +7 (4212) 38-81-91_x000D_ +7 (4212) 38-88-34_x000D_ +7 (4712) 55-23-00_x000D_ +7 (4712) 55-57-54_x000D_ +7 (4722) 76-03-04_x000D_ +7 (4722) 76-05-25_x000D_ +7 (4732) 48-83-14_x000D_ +7 (4732) 65-08-10_x000D_ +7 (4732) 65-08-28_x000D_ +7 (4732) 65-22-64_x000D_ +7 (4732) 65-23-51_x000D_ +7 (4732) 65-28-32_x000D_ +7 (4732) 65-38-34_x000D_ +7 (4732) 65-44-50_x000D_ +7 (4732) 65-66-22_x000D_ +7 (4732) 65-72-81_x000D_ +7 (47391) 4-17-26_x000D_ +7 (47391) 7-59-64_x000D_ +7 (47545) 3-21-40_x000D_ +7 (47545) 3-22-76_x000D_ +7 (4812) 39-52-25_x000D_ +7 (4842) 78-52-95_x000D_ +7 (4852) 49-50-02_x000D_ +7 (4852) 52-40-86_x000D_ +7 (4852) 52-52-43_x000D_ +7 (4852) 79-22-41_x000D_ +7 (4852) 79-35-60_x000D_ +7 (4852) 79-43-14_x000D_ +7 (4852) 79-44-00_x000D_ +7 (4872) 20-20-80_x000D_ +7 (4872) 20-20-93 | D11: http://www.e-disclosure.ru/portal/company.aspx?id=4543_x000D_ http://www.rzd.ru/_x000D_ http://altaitursib.ru/_x000D_ http://dss-sverdl.ru/_x000D_ http://dzvr.ru/about/structure/_x000D_ http://krw.ru/_x000D_ http://kzd.web.rzd/_x000D_ http://rzd.ru/_x000D_ http://www.cm.rzd.ru/_x000D_ http://www.css-rzd.ru/_x000D_ http://www.kras.rzd.ru/_x000D_ http://www.nrr.cm.rzd.ru/_x000D_ http://www.pkbct.ru/_x000D_ http://www.rmzhoper.ru/_x000D_ http://www.rzd.ru/ent/public/ru?STRUCTURE_ID=5185&amp;layer_id=5554&amp;refererLayerId=5553&amp;id=1015_x000D_ http://www.rzd.ru/ent/public/ru?STRUCTURE_ID=5185&amp;layer_id=5554&amp;refererLayerId=5553&amp;id=4347_x000D_ http://www.trudvsem.ru/_x000D_ http://www.uvzd.rzd.ru/_x000D_ http://www.web.rzd/_x000D_ https://www.list-org.com/go?site=804719 | E11: https://kad.arbitr.ru/Card/3a21f6db-26af-410c-9ecc-a36f81016b42 | F11: А40-34376/2024 | G11: ООО "Сапфир-Агро" | H11: 4626006302 | I11: ОАО "РЖД" | J11: 7708503727 | K11: Белозёров Олег Валентинович | L11: 781306504007 | M11: 731393 | N11: 45342 | O11: 220412 | P11: 107174, город Москва, Новая Басманная ул, д. 2/1 стр. 1 | Q11: АС города Москвы | R11: Деятельность железнодорожного транспорта: грузовые перевозки (49.20) | S11: ОБЩЕСТВО С ОГРАНИЧЕННОЙ ОТВЕТСТВЕННОСТЬЮ "САПФИР-АГРО" | U11: ОТКРЫТОЕ АКЦИОНЕРНОЕ ОБЩЕСТВО "РОССИЙСКИЕ ЖЕЛЕЗНЫЕ ДОРОГИ" | W11: Заявление Исковое заявление
A12: =SUBTOTAL(103,$F$1:F12)-1 -> 11 | E12: https://kad.arbitr.ru/Card/41a9bb3f-b000-4ac2-ba55-628ca0d6c767 | F12: А40-34438/2024 | G12: АО "Трест КХМ" | H12: 7705098679 | I12: ООО "Аэрогаз" | J12: 7725715055 | K12: Имаев Салават Зайнетдинович | L12: 501301400181 | M12: 3706461.5 | N12: 45342 | O12: 2 | P12: 121205, город Москва, тер Инновационного Центра Сколково, Большой б-р, д. 42 стр. 1, помещ. 376 раб. место 11 | Q12: АС города Москвы | R12: Научные исследования и разработки в области естественных и технических наук прочие (72.19) | S12: АКЦИОНЕРНОЕ ОБЩЕСТВО "ТРЕСТ КОКСОХИММОНТАЖ" | U12: ОБЩЕСТВО С ОГРАНИЧЕННОЙ ОТВЕТСТВЕННОСТЬЮ "АЭРОГАЗ" | W12: Заявление Исковое заявление
A13: =SUBTOTAL(103,$F$1:F13)-1 -> 12 | B13: info@rst26.ru_x000D_ mup-zarya@mail.ru_x000D_ mup-zarya@yandex.ru_x000D_ shu-nn@rst26.ru_x000D_ z61380@yandex.ru_x000D_ zarya@mail.ru_x000D_ zem_ye@rst26.ru_x000D_ zarya@yandex.ru | C13: +7 (49679) 6-13-80_x000D_ +7 (49679) 6-13-79 | D13: http://www.zarya-zhilservis.ru/ | E13: https://kad.arbitr.ru/Card/f33298f7-5d05-454a-9542-f42696be9829 | F13: А40-34333/2024 | G13: АО "Мосэнергосбыт" | H13: 7736520080 | I13: ОАО "Заря-Жилсервис" | J13: 5009070386 | K13: Руднев Александр Борисович | L13: 500906686417 | M13: 1360795.4 | N13: 45342 | O13: 193 | P13: 142062, Московская область, город Домодедово, село Растуново, ул. Заря, стр. 26 | Q13: АС города Москвы | R13: Управление эксплуатацией жилого фонда за вознаграждение или на договорной основе (68.32.1) | S13: АКЦИОНЕРНОЕ ОБЩЕСТВО "МОСЭНЕРГОСБЫТ" | U13: ОТКРЫТОЕ АКЦИОНЕРНОЕ ОБЩЕСТВО "ЗАРЯ-ЖИЛСЕРВИС" | W13: Заявление Исковое заявление
A14: =SUBTOTAL(103,$F$1:F14)-1 -> 13 | B14: alexander.melnikov@foodcards.ru | E14: https://kad.arbitr.ru/Card/27165634-8e77-4687-a1b5-95427b9dab84 | F14: А40-34362/2024 | G14: ООО "Отель "Рига Ленд" | H14: 5024134531 | I14: ООО "Фуд Сервис Восток" | J14: 7725799866 | K14: Росол Артем Владимирович | L14: 324105716992 | M14: 620607.5 | N14: 45342 | O14: 36 | P14: 127287, город Москва, ул Хуторская 2-Я, д. 38а стр. 15, помещ. IX, кабинет № 64 | Q14: АС города Москвы | R14: Деятельность по предоставлению прочих вспомогательных услуг для бизнеса, не включенная в другие группировки (82.99) | S14: ОБЩЕСТВО С ОГРАНИЧЕННОЙ ОТВЕТСТВЕННОСТЬЮ "ОТЕЛЬ "РИГА ЛЕНД" | U14: ОБЩЕСТВО С ОГРАНИЧЕННОЙ ОТВЕТСТВЕННОСТЬЮ "ФУД СЕРВИС ВОСТОК" | W14: Заявление Исковое заявление
A15: =SUBTOTAL(103,$F$1:F15)-1 -> 14 | C15: +7 (383) 213-08-73 | E15: https://kad.arbitr.ru/Card/a115eafb-218f-4eed-a30b-166cfb1b3e60 | F15: А40-34332/2024 | G15: ООО "Яндекс.Такси" | H15: 7704340310 | I15: ООО "Стар" | J15: 5408017070 | K15: Головкова Евгения Александровна | L15: 540817868153 | M15: 778186.33 | N15: 45342 | O15: 11 | P15: 630117, Новосибирская область, город Новосибирск, ул. Иванова, д. 27, кв. 323 | Q15: АС города Москвы | R15: Деятельность ресторанов и услуги по доставке продуктов питания (56.10) | S15: ОБЩЕСТВО С ОГРАНИЧЕННОЙ ОТВЕТСТВЕННОСТЬЮ "ЯНДЕКС.ТАКСИ" | U15: ОБЩЕСТВО С ОГРАНИЧЕННОЙ ОТВЕТСТВЕННОСТЬЮ "СТАР" | W15: Заявление Исковое заявление
A16: =SUBTOTAL(103,$F$1:F16)-1 -> 15 | C16: +7 (926) 584-55-56 | E16: https://kad.arbitr.ru/Card/daf10b0d-4ccd-4967-82db-3753b302302f | F16: А40-34274/2024 | G16: ООО "Интегрум" | H16: 7724947688 | I16: ООО "Инком СБ" | J16: 5050100320 | K16: Кюрпя Иван Николаевич | L16: 670501775401 | M16: 671100 | N16: 45342 | O16: 18 | P16: 141103, Московская область, город Щёлково, ул. Бахчиванджи, д. 7, помещ. №4, цокольный этаж | Q16: АС города Москвы | R16: Производство электромонтажных, санитарно-технических и прочих строительно-монтажных работ (43.2) | S16: ОБЩЕСТВО С ОГРАНИЧЕННОЙ ОТВЕТСТВЕННОСТЬЮ "ИНТЕГРУМ" | U16: ОБЩЕСТВО С ОГРАНИЧЕННОЙ ОТВЕТСТВЕННОСТЬЮ "ИНТЕГРИРОВАННЫЕ КОМПЛЕКСНЫЕ СИСТЕМЫ БЕЗОПАСНОСТИ" | W16: Заявление Исковое заявление
A17: =SUBTOTAL(103,$F$1:F17)-1 -> 16 | E17: https://kad.arbitr.ru/Card/8bc3dd64-8b32-4c95-8d07-b2d14b69e4ee | F17: А40-34270/2024 | G17: ООО "Стар Строй" | H17: 7728471985 | I17: ООО "Энергопроект" | J17: 7751141921 | K17: Меджидов Шалбуз Энверович | L17: 054205291007 | M17: 3167055.1 | N17: 45342 | O17: 26 | P17: 115114, город Москва, 2-Й Павелецкий проезд, д. 5 стр. 1, подв. № 0 оф. 7 | Q17: АС города Москвы | R17: Строительство жилых и нежилых зданий (41.20) | S17: ОБЩЕСТВО С ОГРАНИЧЕННОЙ ОТВЕТСТВЕННОСТЬЮ "СТАР СТРОЙ" | U17: ОБЩЕСТВО С ОГРАНИЧЕННОЙ ОТВЕТСТВЕННОСТЬЮ "ЭНЕРГОПРОЕКТ" | W17: Заявление Исковое заявление
A18: =SUBTOTAL(103,$F$1:F18)-1 -> 17 | B18: ap@ipzavod.ru_x000D_ v.bugaeva@ipzavod.ru_x000D_ e.isaeva@ipzavod.ru_x000D_ ik@ipzavod.ru_x000D_ ns@ipzavod.ru | C18: +7 (4876) 27-04-40_x000D_ +7 (4876) 27-06-08_x000D_ +7 (910) 702-40-80_x000D_ +7 (495) 369-02-36 | E18: https://kad.arbitr.ru/Card/5d4d1879-fe27-477c-a7b0-616424d837e9 | F18: А40-33874/2024 | G18: ООО "Союз Св. Иоанна Воина" | H18: 7729705354 | I18: ООО "Тульский Винокуренный Завод 1911" | J18: 7751507541 | K18: Щербенев Сергей Николаевич | L18: 231104996872 | M18: 1907403 | N18: 45342 | O18: 29 | P18: 301733, Тульская область, Кимовский район, поселок Пронь, Заводская ул., зд. 10 стр. 23, помещ. 9 | Q18: АС города Москвы | R18: Производство дистиллированных питьевых алкогольных напитков: водки, виски, бренди, джина, ликеров и т. п. (11.01.1) | S18: ОБЩЕСТВО С ОГРАНИЧЕННОЙ ОТВЕТСТВЕННОСТЬЮ "СОЮЗ СВЯТОГО ИОАННА ВОИНА" | U18: ОБЩЕСТВО С ОГРАНИЧЕННОЙ ОТВЕТСТВЕННОСТЬЮ "ТУЛЬСКИЙ ВИНОКУРЕННЫЙ ЗАВОД 1911" | W18: Заявление Исковое заявление
A19: =SUBTOTAL(103,$F$1:F19)-1 -> 18 | B19: KLEN@vfmgei.ru_x000D_ tmacyuk@inbox.ru | C19: +7 (4842) 57-74-72_x000D_ +7 (495) 237-56-60_x000D_ +7 (8352) 34-90-38_x000D_ +7 (8617) 64-41-13_x000D_ +7 (4842) 59-75-73_x000D_ +7 (495) 237-55-40_x000D_ +7 (8352) 34-90-32_x000D_ +7 (8152) 24-62-01_x000D_ +7 (8352) 34-90-35_x000D_ +7 (8152) 24-62-04_x000D_ +7 (833) 262-13-00 | D19: http://mgei.ru/_x000D_ http://mgeitver.ru/_x000D_ http://nvr-mgei.ru/_x000D_ http://skf-mgei.ru/ | E19: https://kad.arbitr.ru/Card/b56292f7-e486-4c88-88af-826cf082c641 | F19: А40-33722/2024 | G19: Департамент городского Имущества Города Москвы | H19: 7705031674 | I19: АНО ВО МГЭУ | J19: 7737040022 | K19: Демидова Любовь Анисимовна | L19: 500601092377 | M19: 952992.01 | N19: 45342 | O19: 26 | P19: 119049, город Москва, Ленинский пр-кт, д.8 стр. 16 | Q19: АС города Москвы | R19: Образование высшее (85.22) | S19: ДЕПАРТАМЕНТ ГОРОДСКОГО ИМУЩЕСТВА ГОРОДА МОСКВЫ | U19: АВТОНОМНАЯ НЕКОММЕРЧЕСКАЯ ОРГАНИЗАЦИЯ ВЫСШЕГО ОБРАЗОВАНИЯ МОСКОВСКИЙ ГУМАНИТАРНО-ЭКОНОМИЧЕСКИЙ УНИВЕРСИТЕТ | W19: Заявление Исковое заявление
A20: =SUBTOTAL(103,$F$1:F20)-1 -> 19 | B20: rzd@rzd.ru_x000D_ poddymnikovaov@wsr.ru_x000D_ DKRE-Mahalov@kbsh.rzd.ru_x000D_ dtv-3.rzd@bk.ru_x000D_ echekunova@skzd.rzd.ru_x000D_ EPBelenkaiakr@skzd.rzd.ru_x000D_ fax@css.rzd.ru_x000D_ gorkdmkadr@gmail.com_x000D_ kuzmenkovagv@center.rzd.ru_x000D_ mivc@mzd.ru_x000D_ mrzd_KostrovaSA@orw.ru_x000D_ NEKolesnikova@serw.ru_x000D_ Ngs_s@svrw.ru_x000D_ sevtcfto@yandex.ru_x000D_ TuizovaTA@mail.zabtrans.ru | C20: +7 (499) 262-99-01_x000D_ +7 (499) 262-10-02_x000D_ 8 (800) 775-00-00_x000D_ +7 (4852) 52-18-30_x000D_ +7 (3012) 28-25-04_x000D_ +7 (3022) 22-33-05_x000D_ +7 (3022) 22-46-03_x000D_ +7 (3022) 22-46-72_x000D_ +7 (3022) 22-75-05_x000D_ +7 (3022) 24-18-00_x000D_ +7 (3022) 24-22-25_x000D_ +7 (3022) 24-45-58_x000D_ +7 (30241) 2-40-54_x000D_ +7 (342) 230-22-25_x000D_ +7 (343) 358-22-25_x000D_ +7 (343) 358-22-60_x000D_ +7 (343) 358-29-32_x000D_ +7 (343) 358-40-88_x000D_ +7 (343) 358-44-00_x000D_ +7 (343) 358-48-10_x000D_ +7 (343) 358-48-48_x000D_ +7 (343) 358-48-89_x000D_ +7 (343) 358-57-27_x000D_ +7 (343) 380-14-74_x000D_ +7 (343) 380-17-54_x000D_ +7 (3435) 49-42-39_x000D_ +7 (3452) 52-31-40_x000D_ +7 (3452) 52-38-48_x000D_ +7 (3462) 39-35-33_x000D_ +7 (347) 229-63-15_x000D_ +7 (347) 253-14-52_x000D_ +7 (351) 259-29-04_x000D_ +7 (351) 263-84-82_x000D_ +7 (351) 268-21-40_x000D_ +7 (351) 268-39-12_x000D_ +7 (351) 268-65-09_x000D_ +7 (3513) 69-21-40_x000D_ +7 (3812) 44-30-79_x000D_ +7 (383) 229-20-20_x000D_ +7 (383) 229-36-02_x000D_ +7 (383) 229-48-02_x000D_ +7 (383) 229-50-27_x000D_ +7 (383) 334-02-43_x000D_ +7 (3842) 32-23-79_x000D_ +7 (3842) 32-39-50_x000D_ +7 (3852) 29-20-48_x000D_ +7 (3902) 29-45-66_x000D_ +7 (3912) 23-13-28_x000D_ +7 (3912) 48-04-35_x000D_ +7 (3912) 48-05-59_x000D_ +7 (3912) 59-52-98_x000D_ +7 (3952) 63-22-46_x000D_ +7 (3952) 63-42-66_x000D_ +7 (3952) 63-84-79_x000D_ +7 (3952) 64-42-46_x000D_ +7 (3952) 64-48-48_x000D_ +7 (3952) 64-51-55_x000D_ +7 (3953) 49-79-79_x000D_ +7 (4012) 58-61-01_x000D_ +7 (4012) 58-72-02_x000D_ +7 (41656) 7-20-00_x000D_ +7 (4212) 38-12-27_x000D_ +7 (4212) 38-37-18_x000D_ +7 (4212) 38-38-80_x000D_ +7 (4212) 38-41-36_x000D_ +7 (4212) 38-47-19_x000D_ +7 (4212) 38-48-43_x000D_ +7 (4212) 38-48-48_x000D_ +7 (4212) 38-53-57_x000D_ +7 (4212) 38-81-91_x000D_ +7 (4212) 38-88-34_x000D_ +7 (4712) 55-23-00_x000D_ +7 (4712) 55-57-54_x000D_ +7 (4722) 76-03-04_x000D_ +7 (4722) 76-05-25_x000D_ +7 (4732) 48-83-14_x000D_ +7 (4732) 65-08-10_x000D_ +7 (4732) 65-08-28_x000D_ +7 (4732) 65-22-64_x000D_ +7 (4732) 65-23-51_x000D_ +7 (4732) 65-28-32_x000D_ +7 (4732) 65-38-34_x000D_ +7 (4732) 65-44-50_x000D_ +7 (4732) 65-66-22_x000D_ +7 (4732) 65-72-81_x000D_ +7 (47391) 4-17-26_x000D_ +7 (47391) 7-59-64_x000D_ +7 (47545) 3-21-40_x000D_ +7 (47545) 3-22-76_x000D_ +7 (4812) 39-52-25_x000D_ +7 (4842) 78-52-95_x000D_ +7 (4852) 49-50-02_x000D_ +7 (4852) 52-40-86_x000D_ +7 (4852) 52-52-43_x000D_ +7 (4852) 79-22-41_x000D_ +7 (4852) 79-35-60_x000D_ +7 (4852) 79-43-14_x000D_ +7 (4852) 79-44-00_x000D_ +7 (4872) 20-20-80_x000D_ +7 (4872) 20-20-93 | D20: http://www.e-disclosure.ru/portal/company.aspx?id=4543_x000D_ http://www.rzd.ru/_x000D_ http://altaitursib.ru/_x000D_ http://dss-sverdl.ru/_x000D_ http://dzvr.ru/about/structure/_x000D_ http://krw.ru/_x000D_ http://kzd.web.rzd/_x000D_ http://rzd.ru/_x000D_ http://www.cm.rzd.ru/_x000D_ http://www.css-rzd.ru/_x000D_ http://www.kras.rzd.ru/_x000D_ http://www.nrr.cm.rzd.ru/_x000D_ http://www.pkbct.ru/_x000D_ http://www.rmzhoper.ru/_x000D_ http://www.rzd.ru/ent/public/ru?STRUCTURE_ID=5185&amp;layer_id=5554&amp;refererLayerId=5553&amp;id=1015_x000D_ http://www.rzd.ru/ent/public/ru?STRUCTURE_ID=5185&amp;layer_id=5554&amp;refererLayerId=5553&amp;id=4347_x000D_ http://www.trudvsem.ru/_x000D_ http://www.uvzd.rzd.ru/_x000D_ http://www.web.rzd/_x000D_ https://www.list-org.com/go?site=804719 | E20: https://kad.arbitr.ru/Card/557c72d2-6273-4cac-8bd9-afeb68a00391 | F20: А40-34777/2024 | G20: ООО "Транспортные Технологии" | H20: 7726326069 | I20: ОАО "РЖД" | J20: 7708503727 | K20: Белозёров Олег Валентинович | L20: 781306504007 | M20: 1178136.2 | N20: 45342 | O20: 220413 | P20: 107174, город Москва, Новая Басманная ул, д. 2/1 стр. 1 | Q20: АС города Москвы | R20: Деятельность железнодорожного транспорта: грузовые перевозки (49.20) | S20: ОБЩЕСТВО С ОГРАНИЧЕННОЙ ОТВЕТСТВЕННОСТЬЮ "ТРАНСПОРТНЫЕ ТЕХНОЛОГИИ" | U20: ОТКРЫТОЕ АКЦИОНЕРНОЕ ОБЩЕСТВО "РОССИЙСКИЕ ЖЕЛЕЗНЫЕ ДОРОГИ" | W20: Заявление Исковое заявление
A21: =SUBTOTAL(103,$F$1:F21)-1 -> 20 | E21: https://kad.arbitr.ru/Card/e1dcb263-6cd8-4e69-ba94-1bac3fcde2dd | F21: А40-34716/2024 | G21: ООО "Сервис" | H21: 7703773208 | I21: ООО "Йота" | J21: 7705743537 | K21: Черноморченко Елена Ивановна | L21: 772973522707 | M21: 559266.08 | N21: 45342 | O21: 17 | P21: 119285, город Москва, Минская ул., д. 1г к. 1, помещ. XX | Q21: АС города Москвы | R21: Покупка и продажа собственного недвижимого имущества (68.1) | S21: ОБЩЕСТВО С ОГРАНИЧЕННОЙ ОТВЕТСТВЕННОСТЬЮ "СЕРВИС" | U21: ОБЩЕСТВО С ОГРАНИЧЕННОЙ ОТВЕТСТВЕННОСТЬЮ "ЙОТА" | W21: Заявление Заявление о выдаче судебного приказа
A22: =SUBTOTAL(103,$F$1:F22)-1 -> 21 | B22: taser.m@mail.ru_x000D_ kott036@rambler.ru | C22: 79266339592 | E22: https://kad.arbitr.ru/Card/b690bef0-0ead-4dab-a690-fc09a96f2c19 | F22: А40-34603/2024 | G22: ООО УК "РЭЦ" | H22: 9710031296 | I22: ООО "Тасера" | J22: 9731106440 | K22: Государев Константин Сергеевич | L22: 772904759494 | M22: 2628672 | N22: 45342 | O22: 2 | P22: 111677, город Москва, Рождественская ул, д. 4, помещ. 7/1 | Q22: АС города Москвы | R22: Управление эксплуатацией жилого фонда за вознаграждение или на договорной основе (68.32.1) | S22: ОБЩЕСТВО С ОГРАНИЧЕННОЙ ОТВЕТСТВЕННОСТЬЮ УПРАВЛЯЮЩАЯ КОМПАНИЯ "РЭЦ" | U22: ОБЩЕСТВО С ОГРАНИЧЕННОЙ ОТВЕТСТВЕННОСТЬЮ "ТАСЕРА" | W22: Заявление Исковое заявление
A23: =SUBTOTAL(103,$F$1:F23)-1 -> 22 | E23: https://kad.arbitr.ru/Card/f1bfe3fa-27de-42f6-9583-6dadf45bacfd | F23: А40-34562/2024 | G23: ООО "Пик-Комфорт" | H23: 7701208190 | I23: ООО "Московская Международная Школа" | J23: 7734447758 | K23: Сяфуков Марат Рафикович | L23: 524909899251 | M23: 3093717.4 | N23: 45342 | O23: 1 | P23: 121087, город Москва, Большая Филёвская ул, д. 3 стр. 5 | Q23: АС города Москвы | R23: Предоставление услуг по дневному уходу за детьми (88.91) | S23: ОБЩЕСТВО С ОГРАНИЧЕННОЙ ОТВЕТСТВЕННОСТЬЮ "ПИК-КОМФОРТ" | U23: ОБЩЕСТВО С ОГРАНИЧЕННОЙ ОТВЕТСТВЕННОСТЬЮ "МОСКОВСКАЯ МЕЖДУНАРОДНАЯ ШКОЛА" | W23: Заявление Исковое заявление
A24: =SUBTOTAL(103,$F$1:F24)-1 -> 23 | E24: https://kad.arbitr.ru/Card/39cba366-a73f-4c67-a4c7-95cbb1f6b842 | F24: А40-34464/2024 | G24: АО "Мосэнергосбыт" | H24: 7736520080 | I24: ООО "УК "Меркурий-Покровское" | J24: 9723113147 | K24: Кривоносов Никита Борисович | L24: 781300677677 | M24: 1921285.7 | N24: 45342 | O24: 22 | P24: 125424, город Москва, Волоколамское ш, д. 71 к. 8, помещ. 6 | Q24: АС города Москвы | R24: Управление недвижимым имуществом за вознаграждение или на договорной основе (68.32) | S24: АКЦИОНЕРНОЕ ОБЩЕСТВО "МОСЭНЕРГОСБЫТ" | U24: ОБЩЕСТВО С ОГРАНИЧЕННОЙ ОТВЕТСТВЕННОСТЬЮ "УПРАВЛЯЮЩАЯ КОМПАНИЯ "МЕРКУРИЙ-ПОКРОВСКОЕ" | W24: Заявление Исковое заявление
A25: =SUBTOTAL(103,$F$1:F25)-1 -> 24 | C25: +7 (495) 651-95-99 | E25: https://kad.arbitr.ru/Card/214c2795-f84c-4aff-a13e-6b41fd6b1e14 | F25: А40-34436/2024 | G25: АО "ФМП Групп" | H25: 7717744461 | I25: ООО "Форс Медиа" | J25: 7722551627 | K25: Алпацкая Алена Дмитриевна | L25: 344505935977 | M25: 25743568 | N25: 45342 | O25: 16 | P25: 107078, город Москва, Новорязанская ул., д. 18 стр. 17 | Q25: АС города Москвы | R25: Производство кинофильмов, видеофильмов и телевизионных программ (59.11) | S25: АКЦИОНЕРНОЕ ОБЩЕСТВО "ФМП ГРУПП" | U25: ОБЩЕСТВО С ОГРАНИЧЕННОЙ ОТВЕТСТВЕННОСТЬЮ "ФОРС МЕДИА" | W25: Заявление Исковое заявление
A26: =SUBTOTAL(103,$F$1:F26)-1 -> 25 | E26: https://kad.arbitr.ru/Card/1808edcd-160c-454b-85fe-4872fc45a59d | F26: А40-34311/2024 | G26: ООО "Яндекс.Такси" | H26: 7704340310 | I26: ООО "Премьерспорт" | J26: 7704467612 | K26: Абрамова Елена Викторовна | L26: 773202675936 | M26: 758931.9 | N26: 45342 | O26: 4 | P26: 125167, город Москва, Ленинградский пр-кт, д. 36 к. 33, эт/пом/ком 4/I/48 | Q26: АС города Москвы | R26: Деятельность фитнес-центров (93.13) | S26: ОБЩЕСТВО С ОГРАНИЧЕННОЙ ОТВЕТСТВЕННОСТЬЮ "ЯНДЕКС.ТАКСИ" | U26: ОБЩЕСТВО С ОГРАНИЧЕННОЙ ОТВЕТСТВЕННОСТЬЮ "ПРЕМЬЕРСПОРТ" | W26: Заявление Исковое заявление
A27: =SUBTOTAL(103,$F$1:F27)-1 -> 26 | C27: +7 (3412) 43-24-44_x000D_ +7 (3412) 94-39-38 | D27: http://ohranacentr.ru/ | E27: https://kad.arbitr.ru/Card/cea3d6b7-29ea-4e18-a905-9cabf0b4a8e9 | F27: А40-33963/2024 | G27: ООО "РМ-Плюс" | H27: 7715599770 | I27: ООО "Центр" | J27: 1832006126 | K27: Ощепков Константин Сергеевич | L27: 183512023747 | M27: 7162072 | N27: 45342 | O27: 31 | P27: 426053, Удмуртская Республика, город Ижевск, ул. Ворошилова, д.53 | Q27: АС города Москвы | R27: Торговля оптовая бытовыми электротоварами (46.43) | S27: ОБЩЕСТВО С ОГРАНИЧЕННОЙ ОТВЕТСТВЕННОСТЬЮ "РМ-ПЛЮС" | U27: ОБЩЕСТВО С ОГРАНИЧЕННОЙ ОТВЕТСТВЕННОСТЬЮ "ЦЕНТР" | W27: Заявление Исковое заявление
A28: =SUBTOTAL(103,$F$1:F28)-1 -> 27 | B28: dsk1.rostokino@dsk1.ru_x000D_ dsk1@dsk1.ru_x000D_ rostokino@dsk1.ru | E28: https://kad.arbitr.ru/Card/b77f47bf-5aa9-40af-bfb9-15510b6c86ba | F28: А40-33988/2024 | G28: АО "Первый Автокомбинат" имени Г.Л. Краузе | H28: 7734032873 | I28: ООО "Дск1-Ростокино" | J28: 7716917390 | M28: 1893833.2 | N28: 45342 | O28: 38 | P28: 129343, город Москва, ул. Амундсена, д. 2 стр. 18, эт 1 пом I ком 2 | Q28: АС города Москвы | R28: Производство готовых строительных изделий из бетона, цемента и искусственного камня (23.61.1) | S28: ОРДЕНА ТРУДОВОГО КРАСНОГО ЗНАМЕНИ АКЦИОНЕРНОЕ ОБЩЕСТВО "ПЕРВЫЙ АВТОКОМБИНАТ" ИМЕНИ Г.Л. КРАУЗЕ | U28: ОБЩЕСТВО С ОГРАНИЧЕННОЙ ОТВЕТСТВЕННОСТЬЮ "ДСК1-РОСТОКИНО" | W28: Заявление Исковое заявление
A29: =SUBTOTAL(103,$F$1:F29)-1 -> 28 | B29: soyuzsnabgroup@mail.ru | C29: +7 (8452) 25-99-20_x000D_ +7 (8452) 49-73-95_x000D_ +7 (8453) 53-64-28 | E29: https://kad.arbitr.ru/Card/d49cad1e-305a-486e-b3d2-21d32f7d3b09 | F29: А40-33916/2024 | G29: ООО "ЗНГС-Прометей" | H29: 7706214286 | I29: ООО "ССГ" | J29: 6450083544 | K29: Жуков Андрей Леонидович | L29: 645302844668 | M29: 70983587 | N29: 45342 | O29: 23 | P29: 125481, город Москва, Фомичёвой ул, д. 16 к. 3, кв. 197 | Q29: АС города Москвы | R29: Строительство жилых и нежилых зданий (41.20) | S29: ОБЩЕСТВО С ОГРАНИЧЕННОЙ ОТВЕТСТВЕННОСТЬЮ "ЗАКНЕФТЕГАЗСТРОЙ-ПРОМЕТЕЙ" | U29: ОБЩЕСТВО С ОГРАНИЧЕННОЙ ОТВЕТСТВЕННОСТЬЮ "СОЮЗСТРОЙГРУПП" | W29: Заявление Исковое заявление
A30: =SUBTOTAL(103,$F$1:F30)-1 -> 29 | B30: andrey79_777@mail.ru | E30: https://kad.arbitr.ru/Card/69bde3c4-c1d0-4d8d-9eaf-557edcad0105 | F30: А40-33857/2024 | G30: ООО "Веста" | H30: 7726454159 | I30: ООО "Альянс-Строй" | J30: 5614084072 | K30: Ляшко Анатолий Иванович | L30: 561600203503 | M30: 564253.97 | N30: 45342 | O30: 5 | P30: 462422, Оренбургская область, город Орск, ул. К.Маркса, д. 76 | Q30: АС города Москвы | R30: Разработка гравийных и песчаных карьеров, добыча глины и каолина (08.12) | S30: ОБЩЕСТВО С ОГРАНИЧЕННОЙ ОТВЕТСТВЕННОСТЬЮ "ВЕСТА" | U30: ОБЩЕСТВО С ОГРАНИЧЕННОЙ ОТВЕТСТВЕННОСТЬЮ "АЛЬЯНС-СТРОЙ" | W30: Заявление Исковое заявление
A31: =SUBTOTAL(103,$F$1:F31)-1 -> 30 | B31: dsu68@bk.ru | C31: +7 (915) 879-88-34 | E31: https://kad.arbitr.ru/Card/95c56ee2-36ab-4968-8ffd-27649babb069 | F31: А40-33816/2024 | G31: ООО "ТДМ" | H31: 9717102115 | I31: ООО "Дсу-68" | J31: 6829156219 | K31: Хабоян Армен Гасанович | L31: 682968058219 | M31: 992375.71 | N31: 45342 | O31: 2 | P31: 392526, Тамбовская область, п Строитель, Дорожно-Строительная ул, стр. 46а, офис 1 | Q31: АС города Москвы | R31: Строительство автомобильных дорог и автомагистралей (42.11) | S31: ОБЩЕСТВО С ОГРАНИЧЕННОЙ ОТВЕТСТВЕННОСТЬЮ "ТОРГОВЫЙ ДОМ МАГИСТРАЛЬ" | U31: ОБЩЕСТВО С ОГРАНИЧЕННОЙ ОТВЕТСТВЕННОСТЬЮ "ДСУ-68" | W31: Определение О принятии заявления к производству с рассмотрением в порядке упрощенного производства
A32: =SUBTOTAL(103,$F$1:F32)-1 -> 31 | B32: 1574104@mail.ru | C32: +7 (985) 776-86-74 | E32: https://kad.arbitr.ru/Card/9d51caec-6033-4d4a-bb06-06885a5c48c2 | F32: А40-33867/2024 | G32: АО "СТВ" | H32: 7725810365 | I32: ООО "Е ТВ" | J32: 7714353928 | K32: Кирсанова Виктория Викторовна | L32: 773102302803 | M32: 3186869.7 | N32: 45342 | O32: 7 | P32: 125493, город Москва, Смольная ул, д. 12, этаж 1 помещ. 189з | Q32: АС города Москвы | R32: Деятельность в области телевизионного вещания (60.20) | S32: АКЦИОНЕРНОЕ ОБЩЕСТВО "СПУТНИКОВОЕ ТЕЛЕВИДЕНИЕ" | U32: ОБЩЕСТВО С ОГРАНИЧЕННОЙ ОТВЕТСТВЕННОСТЬЮ "ЕТЕРРА ТВ" | W32: Заявление Исковое заявление
A33: =SUBTOTAL(103,$F$1:F33)-1 -> 32 | C33: +7 (499) 126-66-08_x000D_ +7 (495) 942-71-71_x000D_ +7 (495) 236-13-15_x000D_ +7 (499) 550-00-55_x000D_ +7 (495) 223-40-25, доб 607_x000D_ +7 (495) 987-31-66_x000D_ +7 (495) 727-25-82_x000D_ +7 (495) 727-24-24, доб 5834_x000D_ +7 (495) 223-40-20, доб 5662_x000D_ +7 (495) 727-24-75_x000D_ +7 (495) 983-06-78_x000D_ +7 (495) 758-68-69_x000D_ +7 (495) 727-25-37_x000D_ +7 (495) 223-40-20, доб 5607_x000D_ +7 (495) 942-95-95_x000D_ +7 (495) 942-80-80_x000D_ +7 (495) 948-62-80_x000D_ +7 (495) 983-06-71_x000D_ +7 (495) 222-22-22, доб 2_x000D_ +7 (495) 727-25-24_x000D_ +7 (495) 727-25-23_x000D_ +7 (495) 727-26-26_x000D_ +7 (495) 987-42-33, доб 4177_x000D_ +7 (495) 223-40-20_x000D_ +7 (495) 727-24-24_x000D_ +7 (495) 727-26-25_x000D_ +7 (495) 727-25-98_x000D_ +7 (495) 000-00-00_x000D_ +7 (495) 727-80-80_x000D_ +7 (495) 223-40-20, доб 5657_x000D_ +7 (495) 228-12-23_x000D_ +7 (495) 126-26-35 | E33: https://kad.arbitr.ru/Card/1d623689-4729-45ad-8ecd-a0302e2dec48 | F33: А40-33905/2024 | G33: ООО "Элфокс" | H33: 5012055483 | I33: ООО "Крокус" | J33: 7728115183 | K33: Мросвирина Марина Николаевна | L33: 772503697297 | M33: 3207953.9 | N33: 45342 | O33: 2487 | P33: 107120, город Москва, ул. Земляной Вал, д.41, кв.2 | Q33: АС города Москвы | R33: Сведения о видах деятельности отсутствуют. | S33: ОБЩЕСТВО С ОГРАНИЧЕННОЙ ОТВЕТСТВЕННОСТЬЮ "ЭЛФОКС" | U33: ОБЩЕСТВО С ОГРАНИЧЕННОЙ ОТВЕТСТВЕННОСТЬЮ "КРОКУС 02" | W33: Определение О принятии искового заявления (заявления) к производству
A34: =SUBTOTAL(103,$F$1:F34)-1 -> 33 | B34: bfm@btsrvs.ru | C34: +7 (495) 230-55-87 | E34: https://kad.arbitr.ru/Card/a472e31e-f9ad-4985-8a37-94a17820d117 | F34: А40-34623/2024 | G34: ПАО "Промсвязьбанк" | H34: 7744000912 | I34: ООО "БТС" | J34: 5040165689 | K34: Мухтаров Мирзотуйчи Мирзоазизович | L34: 742007514797 | M34: 2537142 | N34: 45342 | O34: 5 | P34: 142322, Московская область, с Новый Быт, тер. Коммунальная, ком. 1. азс | Q34: АС города Москвы | R34: Техническое обслуживание и ремонт автотранспортных средств (45.20) | S34: ПУБЛИЧНОЕ АКЦИОНЕРНОЕ ОБЩЕСТВО "ПРОМСВЯЗЬБАНК" | U34: ОБЩЕСТВО С ОГРАНИЧЕННОЙ ОТВЕТСТВЕННОСТЬЮ "БОСС ТРАК СЕРВИС" | W34: Заявление Исковое заявление
A35: =SUBTOTAL(103,$F$1:F35)-1 -> 34 | B35: info@pfvis.ru_x000D_ bulavinova3@yandex.ru_x000D_ a.dubrovskih@vis-group.ru_x000D_ timofeeva_sl@pfvis.ru_x000D_ info@pfvis-msk.ru_x000D_ nk@pfvis.ru | C35: +7 (495) 789-85-55_x000D_ +7 (495) 789-85-56_x000D_ +7 (3496) 39-81-12, доб 55_x000D_ +7 (495) 789-85-55, доб 55_x000D_ +7 (495) 789-85-55, доб 7_x000D_ +7 (921) 321-63-10_x000D_ +7 (495) 789-85-55, доб 1858_x000D_ +7 (495) 789-85-55, доб 1875_x000D_ +7 (495) 778-85-55_x000D_ +7 (495) 779-85-56_x000D_ +7 (812) 336-69-90_x000D_ +7 (812) 336-69-91_x000D_ +7 (81371) 3-03-17_x000D_ +7 (495) 781-08-55 | E35: https://kad.arbitr.ru/Card/9a38845c-276c-4df2-af71-4f068723b31e | F35: А40-33896/2024 | G35: ООО "СЗТК" | H35: 7841372708 | I35: ООО "ПФ "ВИС" | J35: 7816158919 | K35: Юдин Сергей Сергеевич | L35: 773127081176 | M35: 1169834.1 | N35: 45342 | O35: 333 | P35: 188300, Ленинградская область, Гатчинский район, город Гатчина, ул. 7 Армии, д. 22а, помещ. 10 | Q35: АС города Москвы | R35: Строительство жилых и нежилых зданий (41.20) | S35: ОБЩЕСТВО С ОГРАНИЧЕННОЙ ОТВЕТСТВЕННОСТЬЮ "СЕВЕРО-ЗАПАДНАЯ ТРУБНАЯ КОМПАНИЯ" | U35: ОБЩЕСТВО С ОГРАНИЧЕННОЙ ОТВЕТСТВЕННОСТЬЮ "ПРОИЗВОДСТВЕННАЯ ФИРМА "ВИС" | W35: Заявление Исковое заявление
A36: =SUBTOTAL(103,$F$1:F36)-1 -> 35 | C36: +7 (922) 639-44-44 | E36: https://kad.arbitr.ru/Card/e587eb78-9515-4587-b99b-0bea7f445a27 | F36: А40-33981/2024 | G36: АО "НЛТ" | H36: 7708334941 | I36: ООО "Промстрой" | J36: 7447240439 | K36: Оганян Гайк Сергеевич | L36: 745312418887 | M36: 4099713.4 | N36: 45342 | O36: 11 | P36: 350010, Краснодарский край, г Краснодар, Зиповская ул, д. 5б, офис 61 | Q36: АС города Москвы | R36: Строительство жилых и нежилых зданий (41.20) | S36: АКЦИОНЕРНОЕ ОБЩЕСТВО "НАЦИОНАЛЬНЫЕ ЛОГИСТИЧЕСКИЕ ТЕХНОЛОГИИ" | U36: ОБЩЕСТВО С ОГРАНИЧЕННОЙ ОТВЕТСТВЕННОСТЬЮ "ПРОМСТРОЙ" | W36: Заявление Исковое заявление
A37: =SUBTOTAL(103,$F$1:F37)-1 -> 36 | B37: avgkh.podolsk@gmail.com_x000D_ nikituk.notarius@yandex.ru_x000D_ buh@avgkh.ru | C37: +7 (495) 214-97-55_x000D_ +7 (498) 505-95-47_x000D_ 8 (800) 250-43-88_x000D_ +7 (495) 741-93-10 | E37: https://kad.arbitr.ru/Card/cf94e8b4-8a27-4853-80c2-c3fc1da7bfbb | F37: А40-34342/2024 | G37: АО "Мосэнергосбыт" | H37: 7736520080 | I37: ООО "УК Август ЖКХ" | J37: 5045055143 | K37: Киляков Игорь Владимирович | L37: 500109604283 | M37: 516806.26 | N37: 45342 | O37: 1236 | P37: 142118, Московская область, город Подольск, ул. 43-й Армии, д. 17, помещ. 4 | Q37: АС города Москвы | R37: Управление недвижимым имуществом за вознаграждение или на договорной основе (68.32) | S37: АКЦИОНЕРНОЕ ОБЩЕСТВО "МОСЭНЕРГОСБЫТ" | U37: ОБЩЕСТВО С ОГРАНИЧЕННОЙ ОТВЕТСТВЕННОСТЬЮ "УПРАВЛЯЮЩАЯ КОМПАНИЯ АВГУСТ ЖКХ" | W37: Заявление Исковое заявление
A38: =SUBTOTAL(103,$F$1:F38)-1 -> 37 | B38: rzd@rzd.ru_x000D_ poddymnikovaov@wsr.ru_x000D_ DKRE-Mahalov@kbsh.rzd.ru_x000D_ dtv-3.rzd@bk.ru_x000D_ echekunova@skzd.rzd.ru_x000D_ EPBelenkaiakr@skzd.rzd.ru_x000D_ fax@css.rzd.ru_x000D_ gorkdmkadr@gmail.com_x000D_ kuzmenkovagv@center.rzd.ru_x000D_ mivc@mzd.ru_x000D_ mrzd_KostrovaSA@orw.ru_x000D_ NEKolesnikova@serw.ru_x000D_ Ngs_s@svrw.ru_x000D_ sevtcfto@yandex.ru_x000D_ TuizovaTA@mail.zabtrans.ru | C38: +7 (499) 262-99-01_x000D_ +7 (499) 262-10-02_x000D_ 8 (800) 775-00-00_x000D_ +7 (4852) 52-18-30_x000D_ +7 (3012) 28-25-04_x000D_ +7 (3022) 22-33-05_x000D_ +7 (3022) 22-46-03_x000D_ +7 (3022) 22-46-72_x000D_ +7 (3022) 22-75-05_x000D_ +7 (3022) 24-18-00_x000D_ +7 (3022) 24-22-25_x000D_ +7 (3022) 24-45-58_x000D_ +7 (30241) 2-40-54_x000D_ +7 (342) 230-22-25_x000D_ +7 (343) 358-22-25_x000D_ +7 (343) 358-22-60_x000D_ +7 (343) 358-29-32_x000D_ +7 (343) 358-40-88_x000D_ +7 (343) 358-44-00_x000D_ +7 (343) 358-48-10_x000D_ +7 (343) 358-48-48_x000D_ +7 (343) 358-48-89_x000D_ +7 (343) 358-57-27_x000D_ +7 (343) 380-14-74_x000D_ +7 (343) 380-17-54_x000D_ +7 (3435) 49-42-39_x000D_ +7 (3452) 52-31-40_x000D_ +7 (3452) 52-38-48_x000D_ +7 (3462) 39-35-33_x000D_ +7 (347) 229-63-15_x000D_ +7 (347) 253-14-52_x000D_ +7 (351) 259-29-04_x000D_ +7 (351) 263-84-82_x000D_ +7 (351) 268-21-40_x000D_ +7 (351) 268-39-12_x000D_ +7 (351) 268-65-09_x000D_ +7 (3513) 69-21-40_x000D_ +7 (3812) 44-30-79_x000D_ +7 (383) 229-20-20_x000D_ +7 (383) 229-36-02_x000D_ +7 (383) 229-48-02_x000D_ +7 (383) 229-50-27_x000D_ +7 (383) 334-02-43_x000D_ +7 (3842) 32-23-79_x000D_ +7 (3842) 32-39-50_x000D_ +7 (3852) 29-20-48_x000D_ +7 (3902) 29-45-66_x000D_ +7 (3912) 23-13-28_x000D_ +7 (3912) 48-04-35_x000D_ +7 (3912) 48-05-59_x000D_ +7 (3912) 59-52-98_x000D_ +7 (3952) 63-22-46_x000D_ +7 (3952) 63-42-66_x000D_ +7 (3952) 63-84-79_x000D_ +7 (3952) 64-42-46_x000D_ +7 (3952) 64-48-48_x000D_ +7 (3952) 64-51-55_x000D_ +7 (3953) 49-79-79_x000D_ +7 (4012) 58-61-01_x000D_ +7 (4012) 58-72-02_x000D_ +7 (41656) 7-20-00_x000D_ +7 (4212) 38-12-27_x000D_ +7 (4212) 38-37-18_x000D_ +7 (4212) 38-38-80_x000D_ +7 (4212) 38-41-36_x000D_ +7 (4212) 38-47-19_x000D_ +7 (4212) 38-48-43_x000D_ +7 (4212) 38-48-48_x000D_ +7 (4212) 38-53-57_x000D_ +7 (4212) 38-81-91_x000D_ +7 (4212) 38-88-34_x000D_ +7 (4712) 55-23-00_x000D_ +7 (4712) 55-57-54_x000D_ +7 (4722) 76-03-04_x000D_ +7 (4722) 76-05-25_x000D_ +7 (4732) 48-83-14_x000D_ +7 (4732) 65-08-10_x000D_ +7 (4732) 65-08-28_x000D_ +7 (4732) 65-22-64_x000D_ +7 (4732) 65-23-51_x000D_ +7 (4732) 65-28-32_x000D_ +7 (4732) 65-38-34_x000D_ +7 (4732) 65-44-50_x000D_ +7 (4732) 65-66-22_x000D_ +7 (4732) 65-72-81_x000D_ +7 (47391) 4-17-26_x000D_ +7 (47391) 7-59-64_x000D_ +7 (47545) 3-21-40_x000D_ +7 (47545) 3-22-76_x000D_ +7 (4812) 39-52-25_x000D_ +7 (4842) 78-52-95_x000D_ +7 (4852) 49-50-02_x000D_ +7 (4852) 52-40-86_x000D_ +7 (4852) 52-52-43_x000D_ +7 (4852) 79-22-41_x000D_ +7 (4852) 79-35-60_x000D_ +7 (4852) 79-43-14_x000D_ +7 (4852) 79-44-00_x000D_ +7 (4872) 20-20-80_x000D_ +7 (4872) 20-20-93 | D38: http://www.e-disclosure.ru/portal/company.aspx?id=4543_x000D_ http://www.rzd.ru/_x000D_ http://altaitursib.ru/_x000D_ http://dss-sverdl.ru/_x000D_ http://dzvr.ru/about/structure/_x000D_ http://krw.ru/_x000D_ http://kzd.web.rzd/_x000D_ http://rzd.ru/_x000D_ http://www.cm.rzd.ru/_x000D_ http://www.css-rzd.ru/_x000D_ http://www.kras.rzd.ru/_x000D_ http://www.nrr.cm.rzd.ru/_x000D_ http://www.pkbct.ru/_x000D_ http://www.rmzhoper.ru/_x000D_ http://www.rzd.ru/ent/public/ru?STRUCTURE_ID=5185&amp;layer_id=5554&amp;refererLayerId=5553&amp;id=1015_x000D_ http://www.rzd.ru/ent/public/ru?STRUCTURE_ID=5185&amp;layer_id=5554&amp;refererLayerId=5553&amp;id=4347_x000D_ http://www.trudvsem.ru/_x000D_ http://www.uvzd.rzd.ru/_x000D_ http://www.web.rzd/_x000D_ https://www.list-org.com/go?site=804719 | E38: https://kad.arbitr.ru/Card/f7ee1dba-d0ea-400a-a63f-f227653196e9 | F38: А40-34432/2024 | G38: ООО "ЧНК" | H38: 2337044305 | I38: ОАО "РЖД" | J38: 7708503727 | K38: Белозёров Олег Валентинович | L38: 781306504007 | M38: 619878.84 | N38: 45342 | O38: 220414 | P38: 107174, город Москва, Новая Басманная ул, д. 2/1 стр. 1 | Q38: АС города Москвы | R38: Деятельность железнодорожного транспорта: грузовые перевозки (49.20) | S38: ОБЩЕСТВО С ОГРАНИЧЕННОЙ ОТВЕТСТВЕННОСТЬЮ "ЧЕРНОМОРСКАЯ НЕФТЯНАЯ КОМПАНИЯ" | U38: ОТКРЫТОЕ АКЦИОНЕРНОЕ ОБЩЕСТВО "РОССИЙСКИЕ ЖЕЛЕЗНЫЕ ДОРОГИ" | W38: Заявление Исковое заявление
A39: =SUBTOTAL(103,$F$1:F39)-1 -> 38 | B39: andnik@fastmail.com_x000D_ ao@fortex-group.ru_x000D_ 311416@mail.ru_x000D_ nfo@glavms.ru | C39: +7 (495) 708-31-35_x000D_ +7 (495) 137-56-25_x000D_ +7 (985) 163-53-43_x000D_ +7 (495) 921-31-21 | E39: https://kad.arbitr.ru/Card/282f0533-6141-4bee-b3b8-1b92e89db46c | F39: А40-34287/2024 | G39: ООО "СМ-Групп" | H39: 7724325253 | I39: ООО "Главмонтажстрой" | J39: 7730699401 | K39: Еремичев Сергей Викторович | L39: 772800624206 | M39: 7142160 | N39: 45342 | O39: 40 | P39: 121059, город Москва, Брянская ул., д. 2, эт антресоль1 пом III каб 8 | Q39: АС города Москвы | R39: Строительство жилых и нежилых зданий (41.20) | S39: ОБЩЕСТВО С ОГРАНИЧЕННОЙ ОТВЕТСТВЕННОСТЬЮ "СТРОИТЕЛЬНЫЕ МАШИНЫ" | U39: ОБЩЕСТВО С ОГРАНИЧЕННОЙ ОТВЕТСТВЕННОСТЬЮ "ГЛАВМОНТАЖСТРОЙ" | W39: Заявление Исковое заявление
A40: =SUBTOTAL(103,$F$1:F40)-1 -> 39 | B40: info@ksum.ru_x000D_ oks2902@yandex.ru | C40: +7 (48336) 4-02-66_x000D_ +7 (48336) 4-24-85_x000D_ +7 (48336) 4-69-37_x000D_ +7 (916) 684-81-94_x000D_ +7 (910) 734-44-86 | E40: https://kad.arbitr.ru/Card/7e8e1181-57c2-4374-9493-60d73b448183 | F40: А40-34248/2024 | G40: ФГУП "Эндофарм" | H40: 7722059711 | I40: ООО "Клинцовское Сум" | J40: 3241006974 | K40: Лысаков Александр Васильевич | L40: 320301337305 | M40: 754139.65 | N40: 45342 | O40: 42 | P40: 107014, город Москва, 1-Я Боевская ул, д. 2/12 стр. 4, помещ. 1/1 | Q40: АС города Москвы | R40: Строительство жилых и нежилых зданий (41.2) | S40: ФЕДЕРАЛЬНОЕ ГОСУДАРСТВЕННОЕ УНИТАРНОЕ ПРЕДПРИЯТИЕ "МОСКОВСКИЙ ЭНДОКРИННЫЙ ЗАВОД" | U40: ОБЩЕСТВО С ОГРАНИЧЕННОЙ ОТВЕТСТВЕННОСТЬЮ "КЛИНЦОВСКОЕ СПЕЦУПРАВЛЕНИЕ МЕХАНИЗАЦИИ" | W40: Заявление Исковое заявление
A41: =SUBTOTAL(103,$F$1:F41)-1 -> 40 | E41: https://kad.arbitr.ru/Card/e0d8c155-df37-417b-be05-fe09f687ee6b | F41: А40-34101/2024 | I41: ООО "Сити-Планнинг" | J41: 7718757103 | K41: Глебов Александр Александрович | L41: 672304106123 | M41: 2136000 | N41: 45342 | O41: 6 | P41: 125040, город Москва, Ленинградский пр-кт, д. 7 стр. 1, помещ. 1/2 | Q41: АС города Москвы | R41: Производство прочих строительно-монтажных работ (43.29) | S41: Кривцов Евгений Евгеньевич | U41: ОБЩЕСТВО С ОГРАНИЧЕННОЙ ОТВЕТСТВЕННОСТЬЮ "АРХИТЕКТУРНО-ИНЖИНИРИНГОВАЯ КОМПАНИЯ "СИТИ-ПЛАННИНГ" | W41: Заявление Исковое заявление
A42: =SUBTOTAL(103,$F$1:F42)-1 -> 41 | B42: rzd@rzd.ru_x000D_ poddymnikovaov@wsr.ru_x000D_ DKRE-Mahalov@kbsh.rzd.ru_x000D_ dtv-3.rzd@bk.ru_x000D_ echekunova@skzd.rzd.ru_x000D_ EPBelenkaiakr@skzd.rzd.ru_x000D_ fax@css.rzd.ru_x000D_ gorkdmkadr@gmail.com_x000D_ kuzmenkovagv@center.rzd.ru_x000D_ mivc@mzd.ru_x000D_ mrzd_KostrovaSA@orw.ru_x000D_ NEKolesnikova@serw.ru_x000D_ Ngs_s@svrw.ru_x000D_ sevtcfto@yandex.ru_x000D_ TuizovaTA@mail.zabtrans.ru | C42: +7 (499) 262-99-01_x000D_ +7 (499) 262-10-02_x000D_ 8 (800) 775-00-00_x000D_ +7 (4852) 52-18-30_x000D_ +7 (3012) 28-25-04_x000D_ +7 (3022) 22-33-05_x000D_ +7 (3022) 22-46-03_x000D_ +7 (3022) 22-46-72_x000D_ +7 (3022) 22-75-05_x000D_ +7 (3022) 24-18-00_x000D_ +7 (3022) 24-22-25_x000D_ +7 (3022) 24-45-58_x000D_ +7 (30241) 2-40-54_x000D_ +7 (342) 230-22-25_x000D_ +7 (343) 358-22-25_x000D_ +7 (343) 358-22-60_x000D_ +7 (343) 358-29-32_x000D_ +7 (343) 358-40-88_x000D_ +7 (343) 358-44-00_x000D_ +7 (343) 358-48-10_x000D_ +7 (343) 358-48-48_x000D_ +7 (343) 358-48-89_x000D_ +7 (343) 358-57-27_x000D_ +7 (343) 380-14-74_x000D_ +7 (343) 380-17-54_x000D_ +7 (3435) 49-42-39_x000D_ +7 (3452) 52-31-40_x000D_ +7 (3452) 52-38-48_x000D_ +7 (3462) 39-35-33_x000D_ +7 (347) 229-63-15_x000D_ +7 (347) 253-14-52_x000D_ +7 (351) 259-29-04_x000D_ +7 (351) 263-84-82_x000D_ +7 (351) 268-21-40_x000D_ +7 (351) 268-39-12_x000D_ +7 (351) 268-65-09_x000D_ +7 (3513) 69-21-40_x000D_ +7 (3812) 44-30-79_x000D_ +7 (383) 229-20-20_x000D_ +7 (383) 229-36-02_x000D_ +7 (383) 229-48-02_x000D_ +7 (383) 229-50-27_x000D_ +7 (383) 334-02-43_x000D_ +7 (3842) 32-23-79_x000D_ +7 (3842) 32-39-50_x000D_ +7 (3852) 29-20-48_x000D_ +7 (3902) 29-45-66_x000D_ +7 (3912) 23-13-28_x000D_ +7 (3912) 48-04-35_x000D_ +7 (3912) 48-05-59_x000D_ +7 (3912) 59-52-98_x000D_ +7 (3952) 63-22-46_x000D_ +7 (3952) 63-42-66_x000D_ +7 (3952) 63-84-79_x000D_ +7 (3952) 64-42-46_x000D_ +7 (3952) 64-48-48_x000D_ +7 (3952) 64-51-55_x000D_ +7 (3953) 49-79-79_x000D_ +7 (4012) 58-61-01_x000D_ +7 (4012) 58-72-02_x000D_ +7 (41656) 7-20-00_x000D_ +7 (4212) 38-12-27_x000D_ +7 (4212) 38-37-18_x000D_ +7 (4212) 38-38-80_x000D_ +7 (4212) 38-41-36_x000D_ +7 (4212) 38-47-19_x000D_ +7 (4212) 38-48-43_x000D_ +7 (4212) 38-48-48_x000D_ +7 (4212) 38-53-57_x000D_ +7 (4212) 38-81-91_x000D_ +7 (4212) 38-88-34_x000D_ +7 (4712) 55-23-00_x000D_ +7 (4712) 55-57-54_x000D_ +7 (4722) 76-03-04_x000D_ +7 (4722) 76-05-25_x000D_ +7 (4732) 48-83-14_x000D_ +7 (4732) 65-08-10_x000D_ +7 (4732) 65-08-28_x000D_ +7 (4732) 65-22-64_x000D_ +7 (4732) 65-23-51_x000D_ +7 (4732) 65-28-32_x000D_ +7 (4732) 65-38-34_x000D_ +7 (4732) 65-44-50_x000D_ +7 (4732) 65-66-22_x000D_ +7 (4732) 65-72-81_x000D_ +7 (47391) 4-17-26_x000D_ +7 (47391) 7-59-64_x000D_ +7 (47545) 3-21-40_x000D_ +7 (47545) 3-22-76_x000D_ +7 (4812) 39-52-25_x000D_ +7 (4842) 78-52-95_x000D_ +7 (4852) 49-50-02_x000D_ +7 (4852) 52-40-86_x000D_ +7 (4852) 52-52-43_x000D_ +7 (4852) 79-22-41_x000D_ +7 (4852) 79-35-60_x000D_ +7 (4852) 79-43-14_x000D_ +7 (4852) 79-44-00_x000D_ +7 (4872) 20-20-80_x000D_ +7 (4872) 20-20-93 | D42: http://www.e-disclosure.ru/portal/company.aspx?id=4543_x000D_ http://www.rzd.ru/_x000D_ http://altaitursib.ru/_x000D_ http://dss-sverdl.ru/_x000D_ http://dzvr.ru/about/structure/_x000D_ http://krw.ru/_x000D_ http://kzd.web.rzd/_x000D_ http://rzd.ru/_x000D_ http://www.cm.rzd.ru/_x000D_ http://www.css-rzd.ru/_x000D_ http://www.kras.rzd.ru/_x000D_ http://www.nrr.cm.rzd.ru/_x000D_ http://www.pkbct.ru/_x000D_ http://www.rmzhoper.ru/_x000D_ http://www.rzd.ru/ent/public/ru?STRUCTURE_ID=5185&amp;layer_id=5554&amp;refererLayerId=5553&amp;id=1015_x000D_ http://www.rzd.ru/ent/public/ru?STRUCTURE_ID=5185&amp;layer_id=5554&amp;refererLayerId=5553&amp;id=4347_x000D_ http://www.trudvsem.ru/_x000D_ http://www.uvzd.rzd.ru/_x000D_ http://www.web.rzd/_x000D_ https://www.list-org.com/go?site=804719 | E42: https://kad.arbitr.ru/Card/02af8c1a-0cad-4f8a-b65f-831e5ff00830 | F42: А40-34148/2024 | G42: ООО "Евразия" | H42: 6685088780 | I42: ОАО "РЖД" | J42: 7708503727 | K42: Белозёров Олег Валентинович | L42: 781306504007 | M42: 3083200 | N42: 45342 | O42: 220414 | P42: 107174, город Москва, Новая Басманная ул, д. 2/1 стр. 1 | Q42: АС города Москвы | R42: Деятельность железнодорожного транспорта: грузовые перевозки (49.20) | S42: ОБЩЕСТВО С ОГРАНИЧЕННОЙ ОТВЕТСТВЕННОСТЬЮ "ЕВРАЗИЯ" | U42: ОТКРЫТОЕ АКЦИОНЕРНОЕ ОБЩЕСТВО "РОССИЙСКИЕ ЖЕЛЕЗНЫЕ ДОРОГИ" | W42: Заявление Исковое заявление
A43: =SUBTOTAL(103,$F$1:F43)-1 -> 42 | E43: https://kad.arbitr.ru/Card/600b0274-4a8e-4d4d-a2c6-b6b1ac60dc6a | F43: А40-34811/2024 | G43: ООО "Опцион-ТМ" | H43: 7727524240 | I43: ИП Кулалаева Зухра Исагаджиевна | J43: 611901148857 | K43: Кулалаева Зухра Исагаджиевна | L43: 611901148857 | M43: 35229665 | N43: 45342 | O43: 2 | P43: Ростовская область, город Ростов-на-Дону | Q43: АС города Москвы | R43: Консультирование по вопросам коммерческой деятельности и управления (70.22) | S43: ОБЩЕСТВО С ОГРАНИЧЕННОЙ ОТВЕТСТВЕННОСТЬЮ "ОПЦИОН-ТМ" | U43: ИП Кулалаева Зухра Исагаджиевна | W43: Заявление Исковое заявление
A44: =SUBTOTAL(103,$F$1:F44)-1 -> 43 | B44: irinaselezneva.v@gmail.com_x000D_ dgz1@mail.ru_x000D_ erc_33@mil.ru_x000D_ guk_corruption@mil.ru_x000D_ info@morf.ru_x000D_ minob@mail.ru_x000D_ press@mil.ru_x000D_ uvpminob@mail.ru | C44: +7 (495) 696-60-26_x000D_ +7 (495) 696-89-00_x000D_ +7 (495) 696-60-42_x000D_ +7 (495) 293-89-79_x000D_ +7 (495) 496-17-33_x000D_ +7 (495) 526-69-11_x000D_ +7 (495) 693-01-77_x000D_ +7 (495) 693-30-17_x000D_ +7 (495) 696-06-88_x000D_ +7 (495) 696-11-87_x000D_ +7 (495) 696-17-33_x000D_ +7 (495) 696-64-84_x000D_ +7 (495) 696-88-00_x000D_ +7 (495) 696-91-84_x000D_ +7 (963) 447-93-21_x000D_ +7 (495) 693-85-41_x000D_ +7 (495) 696-19-40_x000D_ +7 (495) 696-66-26_x000D_ +7 (3412) 41-41-37_x000D_ +7 (495) 696-11-05_x000D_ +7 (3452) 43-44-30_x000D_ +7 (3452) 69-11-05_x000D_ +7 (35168) 9-36-84_x000D_ +7 (3522) 29-52-94_x000D_ +7 (4212) 21-27-91_x000D_ +7 (4212) 27-07-41_x000D_ +7 (4212) 39-52-58_x000D_ +7 (4212) 39-55-83_x000D_ +7 (4212) 39-71-37_x000D_ +7 (4212) 39-73-28_x000D_ +7 (4212) 39-78-67_x000D_ +7 (49672) 6-35-12_x000D_ +7 (909) 958-61-20_x000D_ +7 (983) 536-65-91_x000D_ +7 (495) 577-84-87_x000D_ +7 (812) 494-02-62_x000D_ +7 (495) 498-01-82_x000D_ +7 (499) 263-86-35_x000D_ 8 (800) 200-22-94_x000D_ +7 (499) 244-52-31_x000D_ +7 (48439) 9-65-98_x000D_ +7 (495) 498-32-34_x000D_ +7 (495) 111-11-11 | D44: http://mil.ru/ | E44: https://kad.arbitr.ru/Card/13ffca83-19d3-4761-9d8e-d33d4e783a70 | F44: А40-34717/2024 | G44: АО "НПК "Ниидар" | H44: 7718016698 | I44: Минобороны России | J44: 7704252261 | K44: Шойгу Сергей Кужугетович | L44: 503201733649 | M44: 142571450 | N44: 45342 | O44: 34770 | P44: 119160, город Москва, ул. Знаменка, д. 19 | Q44: АС города Москвы | R44: Деятельность, связанная с обеспечением военной безопасности (84.22) | S44: АКЦИОНЕРНОЕ ОБЩЕСТВО "НАУЧНО-ПРОИЗВОДСТВЕННЫЙ КОМПЛЕКС "НАУЧНО-ИССЛЕДОВАТЕЛЬСКИЙ ИНСТИТУТ ДАЛЬНЕЙ РАДИОСВЯЗИ" | U44: МИНИСТЕРСТВО ОБОРОНЫ РОССИЙСКОЙ ФЕДЕРАЦИИ | W44: Заявление Исковое заявление
A45: =SUBTOTAL(103,$F$1:F45)-1 -> 44 | B45: buh@allstarmedia.ru | C45: +7 (903) 748-89-01_x000D_ +7 (926) 109-71-67 | E45: https://kad.arbitr.ru/Card/28178559-c63d-4cad-9879-b93e4d66441d | F45: А40-34954/2024 | G45: ООО "Топхит" | H45: 7743270377 | I45: ООО "Ол Стар Мьюзик" | J45: 9701124900 | K45: Павлов Дмитрий Олегович | L45: 770170882018 | M45: 974431.73 | N45: 45342 | O45: 9 | P45: 105082, город Москва, Спартаковская пл, д. 14 стр. 2, ком. 8-9 | Q45: АС города Москвы | R45: Деятельность в области звукозаписи и издания музыкальных произведений (59.20) | S45: ОБЩЕСТВО С ОГРАНИЧЕННОЙ ОТВЕТСТВЕННОСТЬЮ "ТОПХИТ" | U45: ОБЩЕСТВО С ОГРАНИЧЕННОЙ ОТВЕТСТВЕННОСТЬЮ "ОЛ СТАР МЬЮЗИК" | W45: Заявление Исковое заявление
A46: =SUBTOTAL(103,$F$1:F46)-1 -> 45 | B46: notarius_rudenko@mail.ru | C46: +7 (965) 133-61-83 | E46: https://kad.arbitr.ru/Card/cd9d3689-4ebb-40e9-a5fe-6e25ed5f067c | F46: А40-34678/2024 | G46: ООО "Инвест Менеджмент" | H46: 9701009897 | I46: ООО "Айтишеринг" | J46: 7723382354 | K46: Чуприна Павел Николаевич | L46: 772854890300 | M46: 543000 | N46: 45342 | O46: 7 | P46: 117186, город Москва, Нагорная ул, д. 24 к. 9, этаж 1 помещ. II, ком. 1ж | Q46: АС города Москвы | R46: Деятельность консультативная и работы в области компьютерных технологий (62.02) | S46: ОБЩЕСТВО С ОГРАНИЧЕННОЙ ОТВЕТСТВЕННОСТЬЮ "ИНВЕСТ МЕНЕДЖМЕНТ" | U46: ОБЩЕСТВО С ОГРАНИЧЕННОЙ ОТВЕТСТВЕННОСТЬЮ "АЙТИШЕРИНГ" | W46: Заявление Исковое заявление
A47: =SUBTOTAL(103,$F$1:F47)-1 -> 46 | C47: +7 (499) 330-97-55 | D47: http://cpkmagistr.ru/ | E47: https://kad.arbitr.ru/Card/ebdabeb3-6419-4a56-9981-6707e6b65a21 | F47: А40-34115/2024 | G47: ИП Поливеев Алексей Анатольевич | H47: 772481030161 | I47: ООО "ЦПК Магистр" | J47: 7729404607 | K47: Козлов Владимир Григорьевич | L47: 772443501660 | M47: 635879.2 | N47: 45342 | O47: 15 | P47: 119192, город Москва, Винницкая ул., д.11, кв.197 | Q47: АС города Москвы | R47: Обработка металлов и нанесение покрытий на металлы (25.61) | S47: ИП Поливеев Алексей Анатольевич | U47: ОБЩЕСТВО С ОГРАНИЧЕННОЙ ОТВЕТСТВЕННОСТЬЮ "ЦПК МАГИСТР" | W47: Определение О принятии заявления к производству с рассмотрением в порядке упрощенного производства
A48: =SUBTOTAL(103,$F$1:F48)-1 -> 47 | E48: https://kad.arbitr.ru/Card/80f285cb-a87c-4a57-836f-0b4f7c5ef79a | F48: А40-34495/2024 | G48: ООО "Алькор" | H48: 9701223749 | M48: 7.4751718e+08 | N48: 45342 | P48: 105066, Россия, г Москва, г вн тер Муниципальный Округ Басманный, г. Москва, ул. Спартаковская, д. 19 строение 3а, кв. Помещ 1/1 | Q48: АС города Москвы | S48: ОБЩЕСТВО С ОГРАНИЧЕННОЙ ОТВЕТСТВЕННОСТЬЮ "АЛЬКОР" | U48: Юфура Холдинг Лимитед (YOFOURA HOLDING LIMITED) | W48: Заявление Исковое заявление
A49: =SUBTOTAL(103,$F$1:F49)-1 -> 48 | C49: +7 (495) 691-83-07 | D49: http://mp3dv.ru/_x000D_ http://4904900.ru/_x000D_ http://ermistage.ru/_x000D_ http://ermitagehotel.ru/_x000D_ http://mosgorsad.ru/ | E49: https://kad.arbitr.ru/Card/e275e20c-ecee-4701-ae63-ef68c2829f61 | F49: А40-34320/2024 | G49: ООО "Яндекс.Такси" | H49: 7704340310 | I49: ООО "Эрмитаж" | J49: 7704665999 | K49: Далгатов Башир Шейхмагомедович | L49: 056204058499 | M49: 693847.38 | N49: 45342 | O49: 6 | P49: 119270, город Москва, ул Хамовнический Вал, д. 4 | Q49: АС города Москвы | R49: Деятельность в области звукозаписи и издания музыкальных произведений (59.20) | S49: ОБЩЕСТВО С ОГРАНИЧЕННОЙ ОТВЕТСТВЕННОСТЬЮ "ЯНДЕКС.ТАКСИ" | U49: ОБЩЕСТВО С ОГРАНИЧЕННОЙ ОТВЕТСТВЕННОСТЬЮ "ЭРМИТАЖ" | W49: Заявление Исковое заявление
A50: =SUBTOTAL(103,$F$1:F50)-1 -> 49 | B50: vektor999@yandex.ru_x000D_ notariusalmazova@mail.ru_x000D_ 4991688975@mail.ru_x000D_ asdf@td.ru_x000D_ guppreo@mail.ru_x000D_ sok-jul@mail.ru | C50: +7 (964) 711-10-57_x000D_ +7 (499) 168-93-62_x000D_ +7 (499) 161-53-97_x000D_ +7 (499) 168-62-93_x000D_ +7 (964) 771-10-57 | E50: https://kad.arbitr.ru/Card/7d47470d-f030-4c4a-a163-20d3a9016d55 | F50: А40-34308/2024 | G50: АО "Мосводоканал" | H50: 7701984274 | I50: ООО "УК "Преображенское" | J50: 7718866769 | K50: Посохов Роман Владимирович | L50: 503110456701 | M50: 1807856.2 | N50: 45342 | O50: 121 | P50: 123007, город Москва, 5-Я Магистральная ул, д. 10а, помещ. I ком. 8 | Q50: АС города Москвы | R50: Управление недвижимым имуществом за вознаграждение или на договорной основе (68.32) | S50: АКЦИОНЕРНОЕ ОБЩЕСТВО "МОСВОДОКАНАЛ" | U50: ОБЩЕСТВО С ОГРАНИЧЕННОЙ ОТВЕТСТВЕННОСТЬЮ "УПРАВЛЯЮЩАЯ КОМПАНИЯ "ПРЕОБРАЖЕНСКОЕ" | W50: Заявление Исковое заявление
A51: =SUBTOTAL(103,$F$1:F51)-1 -> 50 | B51: kravchenko@kuzina.ru | C51: +7 (383) 222-09-04_x000D_ +7 (923) 104-91-19 | E51: https://kad.arbitr.ru/Card/16f37fac-1548-4fe2-b7de-b7481be8071b | F51: А40-34334/2024 | G51: ООО "Яндекс.Такси" | H51: 7704340310 | I51: ООО "Кузина" | J51: 5404373487 | K51: Головкова Евгения Александровна | L51: 540817868153 | M51: 3736263 | N51: 45342 | O51: 29 | P51: 630049, Новосибирская область, город Новосибирск, Красный пр-кт, д. 157, этаж 1 помещение 32 | Q51: АС города Москвы | R51: Деятельность ресторанов и услуги по доставке продуктов питания (56.10) | S51: ОБЩЕСТВО С ОГРАНИЧЕННОЙ ОТВЕТСТВЕННОСТЬЮ "ЯНДЕКС.ТАКСИ" | U51: ОБЩЕСТВО С ОГРАНИЧЕННОЙ ОТВЕТСТВЕННОСТЬЮ "КУЗИНА" | W51: Заявление Исковое заявление
A52: =SUBTOTAL(103,$F$1:F52)-1 -> 51 | C52: +7 (495) 481-11-46 | E52: https://kad.arbitr.ru/Card/76016ecb-a8c2-42ed-b8e3-a0ffbcee7f87 | F52: А40-34231/2024 | G52: АО "Мосводоканал" | H52: 7701984274 | I52: ЖСК "Дегунино-6" | J52: 7713035802 | K52: Осипов Геннадий Михайлович | L52: 771311990733 | M52: 1156876 | N52: 45342 | O52: 6 | P52: 127540, город Москва, Керамический пр-д, д.49 | Q52: АС города Москвы | R52: Сведения о видах деятельности отсутствуют. | S52: АКЦИОНЕРНОЕ ОБЩЕСТВО "МОСВОДОКАНАЛ" | U52: ЖИЛИЩНО - СТРОИТЕЛЬНЫЙ КООПЕРАТИВ "ДЕГУНИНО-6" | W52: Заявление Исковое заявление
A53: =SUBTOTAL(103,$F$1:F53)-1 -> 52 | B53: hr-crccrus@mail.ru_x000D_ 13671011233@163.com_x000D_ 18145124396@163.com_x000D_ chirkina.marina@crccrus.ru_x000D_ chirkinamarina@gmail.com | C53: +7 (985) 111-52-77_x000D_ +7 (985) 111-73-55 | E53: https://kad.arbitr.ru/Card/dae42885-2a64-4f88-9c11-66905cba310a | F53: А40-34736/2024 | G53: ООО "Нефтьсервис" | H53: 5250060530 | I53: ООО "Сиарсиси Рус" | J53: 7730212723 | K53: Чжао Цзяшу | L53: 772876064152 | M53: 11572329 | N53: 45342 | O53: 351 | P53: 117485, город Москва, ул Обручева, д. 30/1 стр. 1, этаж 5 помещ.VIII ком. 1-31 | Q53: АС города Москвы | R53: Деятельность заказчика-застройщика, генерального подрядчика (71.12.2) | S53: ОБЩЕСТВО С ОГРАНИЧЕННОЙ ОТВЕТСТВЕННОСТЬЮ "НЕФТЬСЕРВИС" | U53: ОБЩЕСТВО С ОГРАНИЧЕННОЙ ОТВЕТСТВЕННОСТЬЮ "СИАРСИСИ РУС" | W53: Заявление Исковое заявление
A54: =SUBTOTAL(103,$F$1:F54)-1 -> 53 | E54: https://kad.arbitr.ru/Card/73c8f25d-31ca-43b8-bdb1-f821742f8a64 | F54: А40-36144/2024 | G54: ООО "Орион" | H54: 9723183169 | I54: ООО "Гемолайф" | J54: 7730316384 | K54: Смирнова Марианна Сергеевна | M54: 1087141.1 | N54: 45343 | O54: 1 | P54: 121096, город Москва, Василисы Кожиной ул, д. 1, помещ. 15/7 | Q54: АС города Москвы | R54: Торговля оптовая техникой, оборудованием и инструментами, применяемыми в медицинских целях (46.69.8) | S54: ОБЩЕСТВО С ОГРАНИЧЕННОЙ ОТВЕТСТВЕННОСТЬЮ "ОРИОН" | U54: ОБЩЕСТВО С ОГРАНИЧЕННОЙ ОТВЕТСТВЕННОСТЬЮ "ГЕМОЛАЙФ" | W54: Определение О принятии заявления к производству с рассмотрением в порядке упрощенного производства
A55: =SUBTOTAL(103,$F$1:F55)-1 -> 54 | B55: nvs.sk@mail.ru | E55: https://kad.arbitr.ru/Card/38b3ef0e-55fa-4053-b1cd-4353ce74ed9b | F55: А40-36122/2024 | G55: ООО "ТДМ-Комплект" | H55: 7727770943 | I55: ООО "Новая Высота" | J55: 7730294564 | K55: Каландия Леван Зурабович | L55: 773202531740 | M55: 925813.08 | N55: 45343 | O55: 7 | P55: 121151, город Москва, ул Можайский Вал, д. 8, этаж/помещ. 8/5 офис 856 | Q55: АС города Москвы | R55: Строительство жилых и нежилых зданий (41.20) | S55: ОБЩЕСТВО С ОГРАНИЧЕННОЙ ОТВЕТСТВЕННОСТЬЮ "ТДМ-КОМПЛЕКТ" | U55: ОБЩЕСТВО С ОГРАНИЧЕННОЙ ОТВЕТСТВЕННОСТЬЮ "НОВАЯ ВЫСОТА" | W55: Заявление Исковое заявление
A56: =SUBTOTAL(103,$F$1:F56)-1 -> 55 | B56: pansionagagarina@mail.ru_x000D_ pansionatgagarina@mail.ru_x000D_ surnina63@mail.ru | C56: +7 (365) 696-12-05_x000D_ +7 (365) 696-13-04_x000D_ +7 (978) 731-94-70_x000D_ +7 (978) 855-54-76_x000D_ +7 (978) 755-02-42_x000D_ +7 (365) 696-01-69_x000D_ +7 (365) 699-30-35_x000D_ +7 (978) 793-48-74_x000D_ +7 (919) 875-81-01_x000D_ +7 (978) 687-77-51_x000D_ 8 (800) 550-54-76 | E56: https://kad.arbitr.ru/Card/41eeded3-71d8-49ad-8565-26cfe5a0abf8 | F56: А40-36093/2024 | G56: ГКУ "Дирекция ОДОТСЗН Г. Москвы" | H56: 7701827320 | I56: МУП "Евпатория-Крым-Курорт" | J56: 9110014884 | K56: Павицкая Светлана Викторовна | L56: 911004068073 | M56: 657603 | N56: 45343 | O56: 10 | P56: 297407, Республика Крым, город Евпатория, ул. Полупанова, д. 10 | Q56: АС города Москвы | R56: Деятельность по предоставлению мест для краткосрочного проживания (55.20) | S56: ГОСУДАРСТВЕННОЕ КАЗЕННОЕ УЧРЕЖДЕНИЕ ГОРОДА МОСКВЫ "ДИРЕКЦИЯ ПО ОБЕСПЕЧЕНИЮ ДЕЯТЕЛЬНОСТИ ОРГАНИЗАЦИЙ ТРУДА И СОЦИАЛЬНОЙ ЗАЩИТЫ НАСЕЛЕНИЯ ГОРОДА МОСКВЫ" | U56: МУНИЦИПАЛЬНОЕ УНИТАРНОЕ ПРЕДПРИЯТИЕ "ЕВПАТОРИЯ-КРЫМ-КУРОРТ" ГОРОДСКОГО ОКРУГА ЕВПАТОРИЯ РЕСПУБЛИКИ КРЫМ | W56: Заявление Исковое заявление
A57: =SUBTOTAL(103,$F$1:F57)-1 -> 56 | C57: +7 (905) 506-16-92 | E57: https://kad.arbitr.ru/Card/4bee33dd-8885-40d7-9113-ca7fdb0fa229 | F57: А40-36082/2024 | G57: ООО "Верус" | H57: 1323000514 | I57: ООО "СВ Логистика" | J57: 1323000426 | K57: Демьяненко Алексей Владимирович | L57: 552801496439 | M57: 2756391.2 | N57: 45343 | O57: 157 | P57: 117461, город Москва, ул. Каховка, д. 20 стр. 2, эт 2 каб 8а | Q57: АС города Москвы | R57: Деятельность автомобильного грузового транспорта (49.41) | S57: ОБЩЕСТВО С ОГРАНИЧЕННОЙ ОТВЕТСТВЕННОСТЬЮ "ВЕРУС" | U57: ОБЩЕСТВО С ОГРАНИЧЕННОЙ ОТВЕТСТВЕННОСТЬЮ "СВ ЛОГИСТИКА" | W57: Заявление Исковое заявление
A58: =SUBTOTAL(103,$F$1:F58)-1 -> 57 | B58: info@faber-electro.ru_x000D_ reseption@faber-electro.ru | C58: +7 (84862) 4-70-44, доб 9_x000D_ +7 (84862) 4-99-90, доб 9_x000D_ +7 (4862) 47-04-49_x000D_ +7 (4862) 49-99-09 | D58: http://faber-electro.ru/ | E58: https://kad.arbitr.ru/Card/7162eea7-2c37-4475-ace4-d516924d8bd7 | F58: А40-36037/2024 | G58: ООО "А Групп" | H58: 7717625418 | I58: ООО "Фабер" | J58: 5754004013 | K58: Медведев Алексей Николаевич | L58: 575201322870 | M58: 1977846.9 | N58: 45343 | O58: 64 | P58: 302006, Орловская область, город Орёл, Семинарская ул., д.3 | Q58: АС города Москвы | R58: Производство приборов и аппаратуры для автоматического регулирования или управления (26.51.7) | S58: ОБЩЕСТВО С ОГРАНИЧЕННОЙ ОТВЕТСТВЕННОСТЬЮ "А ГРУПП" | U58: ОБЩЕСТВО С ОГРАНИЧЕННОЙ ОТВЕТСТВЕННОСТЬЮ "ФАБЕР" | W58: Заявление Исковое заявление
A59: =SUBTOTAL(103,$F$1:F59)-1 -> 58 | B59: 9110219@list.ru | C59: +7 (495) 911-02-19_x000D_ +7 (925) 507-45-07_x000D_ +7 (495) 911-02-10 | E59: https://kad.arbitr.ru/Card/ede40b67-efb4-4681-a2b0-feb91521394b | F59: А40-36009/2024 | G59: Департамент городского Имущества Города Москвы | H59: 7705031674 | I59: ЗАО Фирма "Гарни" | J59: 7709000162 | K59: Кветный Дмитрий Семенович | L59: 771914299660 | M59: 3763175.7 | N59: 45343 | O59: 9 | P59: город Москва, ул. Александра Солженицына, 19-2 | Q59: АС города Москвы | R59: Производство обуви (15.20) | S59: ДЕПАРТАМЕНТ ГОРОДСКОГО ИМУЩЕСТВА ГОРОДА МОСКВЫ | U59: ЗАКРЫТОЕ АКЦИОНЕРНОЕ ОБЩЕСТВО ФИРМА "ГАРНИ" | W59: Заявление Исковое заявление
A60: =SUBTOTAL(103,$F$1:F60)-1 -> 59 | E60: https://kad.arbitr.ru/Card/930e316b-f13b-43d2-aa40-73e05d38c3f4 | F60: А40-35864/2024 | G60: ООО "Всеинструменты.Ру" | H60: 7722753969 | I60: ООО "Озгюн-Строй" | J60: 9703017357 | K60: Каракуллукчу Сонер | L60: 770379136854 | M60: 2105308.7 | N60: 45343 | O60: 13 | P60: 125375, город Москва, Тверская ул, д. 16 стр. 3, эт. 1 помещ. 13/12 | Q60: АС города Москвы | R60: Разработка строительных проектов (41.10) | S60: ОБЩЕСТВО С ОГРАНИЧЕННОЙ ОТВЕТСТВЕННОСТЬЮ "ВСЕИНСТРУМЕНТЫ.РУ" | U60: ОБЩЕСТВО С ОГРАНИЧЕННОЙ ОТВЕТСТВЕННОСТЬЮ "ОЗГЮН-СТРОЙ" | W60: Заявление Исковое заявление
A61: =SUBTOTAL(103,$F$1:F61)-1 -> 60 | B61: hotline@pik-comfort.ru_x000D_ arina_lemekhova@mail.ru_x000D_ 7012179@mail.ru_x000D_ akaevaea@pik-comfort.ru_x000D_ antonovann@pik-comfort.ru_x000D_ chumakovani@pik-comfort.ru_x000D_ kaznakovayv@pik-comfort.ru_x000D_ pepelinavn@pik-comfort.ru | C61: +7 (495) 505-97-33_x000D_ +7 (495) 361-84-14_x000D_ +7 (495) 505-89-89_x000D_ +7 (495) 510-39-70_x000D_ +7 (495) 677-06-12_x000D_ +7 (495) 817-62-38_x000D_ +7 (499) 505-89-89_x000D_ +7 (499) 510-39-70_x000D_ 8 (800) 505-89-89_x000D_ +7 (495) 608-00-59_x000D_ +7 (495) 933-42-84_x000D_ 8 (800) 234-22-22_x000D_ +7 (916) 192-69-80_x000D_ +7 (495) 716-39-18_x000D_ +7 (495) 716-39-72 | E61: https://kad.arbitr.ru/Card/b1ff58ee-8ef8-4f5b-a254-fc45c93b2918 | F61: А40-35805/2024 | G61: ООО "Хартия" | H61: 7703770101 | I61: ООО "Пик-Комфорт" | J61: 7701208190 | K61: Розанов Илья Владимирович | L61: 505201952387 | M61: 11599205 | N61: 45343 | O61: 5670 | P61: 123060, город Москва, ул Маршала Соколовского, д. 3, этаж 5 помещ. II ком. 2,4 | Q61: АС города Москвы | R61: Управление недвижимым имуществом за вознаграждение или на договорной основе (68.32) | S61: ОБЩЕСТВО С ОГРАНИЧЕННОЙ ОТВЕТСТВЕННОСТЬЮ "ХАРТИЯ" | U61: ОБЩЕСТВО С ОГРАНИЧЕННОЙ ОТВЕТСТВЕННОСТЬЮ "ПИК-КОМФОРТ" | W61: Заявление Исковое заявление
A62: =SUBTOTAL(103,$F$1:F62)-1 -> 61 | E62: https://kad.arbitr.ru/Card/01e13eec-48f1-4029-8f26-88de2673e6df | F62: А40-35708/2024 | G62: АО "Альфа-Банк" | H62: 7728168971 | I62: ИП Качанов Сергей Геннадьевич | J62: 212710565307 | K62: Качанов Сергей Геннадьевич | M62: 2880954.3 | N62: 45343 | O62: 2 | P62: Чувашская Республика - Чувашия, город Чебоксары | Q62: АС города Москвы | R62: Разборка и снос зданий (43.11) | S62: АКЦИОНЕРНОЕ ОБЩЕСТВО "АЛЬФА-БАНК" | U62: ИП Качанов Сергей Геннадьевич | W62: Заявление Исковое заявление
A63: =SUBTOTAL(103,$F$1:F63)-1 -> 62 | E63: https://kad.arbitr.ru/Card/b95df6c7-af2a-4c14-b6da-1a81f9cfae9d | F63: А40-35723/2024 | G63: АО "Альфа-Банк" | H63: 7728168971 | I63: ИП Баклагин Дмитрий Александрович | J63: 461302824407 | K63: Баклагин Дмитрий Александрович | L63: 461302824407 | M63: 1934970.3 | N63: 45343 | O63: 3 | P63: Курская область, город Курск | Q63: АС города Москвы | R63: Производство кирпича, черепицы и прочих строительных изделий из обожженной глины (23.32) | S63: АКЦИОНЕРНОЕ ОБЩЕСТВО "АЛЬФА-БАНК" | U63: ИП Баклагин Дмитрий Александрович | W63: Заявление Исковое заявление
A64: =SUBTOTAL(103,$F$1:F64)-1 -> 63 | C64: +7 (499) 126-66-08_x000D_ +7 (495) 942-71-71_x000D_ +7 (495) 236-13-15_x000D_ +7 (499) 550-00-55_x000D_ +7 (495) 223-40-25, доб 607_x000D_ +7 (495) 987-31-66_x000D_ +7 (495) 727-25-82_x000D_ +7 (495) 727-24-24, доб 5834_x000D_ +7 (495) 223-40-20, доб 5662_x000D_ +7 (495) 727-24-75_x000D_ +7 (495) 983-06-78_x000D_ +7 (495) 758-68-69_x000D_ +7 (495) 727-25-37_x000D_ +7 (495) 223-40-20, доб 5607_x000D_ +7 (495) 942-95-95_x000D_ +7 (495) 942-80-80_x000D_ +7 (495) 948-62-80_x000D_ +7 (495) 983-06-71_x000D_ +7 (495) 222-22-22, доб 2_x000D_ +7 (495) 727-25-24_x000D_ +7 (495) 727-25-23_x000D_ +7 (495) 727-26-26_x000D_ +7 (495) 987-42-33, доб 4177_x000D_ +7 (495) 223-40-20_x000D_ +7 (495) 727-24-24_x000D_ +7 (495) 727-26-25_x000D_ +7 (495) 727-25-98_x000D_ +7 (495) 000-00-00_x000D_ +7 (495) 727-80-80_x000D_ +7 (495) 223-40-20, доб 5657_x000D_ +7 (495) 228-12-23_x000D_ +7 (495) 126-26-35 | E64: https://kad.arbitr.ru/Card/75d3fb47-44d4-45fb-9849-40d377a1c658 | F64: А40-35750/2024 | G64: ООО "Экомир" | H64: 2315994374 | I64: ООО "Крокус" | J64: 7728115183 | K64: Мросвирина Марина Николаевна | L64: 772503697297 | M64: 1783007.4 | N64: 45343 | O64: 2488 | P64: 107120, город Москва, ул. Земляной Вал, д.41, кв.2 | Q64: АС города Москвы | R64: Сведения о видах деятельности отсутствуют. | S64: ОБЩЕСТВО С ОГРАНИЧЕННОЙ ОТВЕТСТВЕННОСТЬЮ "ЭКОМИР" | U64: ОБЩЕСТВО С ОГРАНИЧЕННОЙ ОТВЕТСТВЕННОСТЬЮ "КРОКУС 02" | W64: Заявление Исковое заявление
A65: =SUBTOTAL(103,$F$1:F65)-1 -> 64 | B65: info@bsoinsur.ru_x000D_ c0007-1@bsoincur.ru | C65: +7 (495) 540-51-10 | E65: https://kad.arbitr.ru/Card/91204912-0842-48a8-82d0-544222f8f9f7 | F65: А40-35703/2024 | G65: ООО "Новая Энергетика" | H65: 6671311012 | I65: АО "Боровицкое Страховое Общество" | J65: 7714034590 | K65: Шамшев Константин Валерьевич | L65: 773002453446 | M65: 54063904 | N65: 45343 | O65: 268 | P65: 119049, город Москва, Мытная ул, д. 1 стр. 1 | Q65: АС города Москвы | R65: Страхование, кроме страхования жизни (65.12) | S65: ОБЩЕСТВО С ОГРАНИЧЕННОЙ ОТВЕТСТВЕННОСТЬЮ "НОВАЯ ЭНЕРГЕТИКА" | U65: АКЦИОНЕРНОЕ ОБЩЕСТВО "БОРОВИЦКОЕ СТРАХОВОЕ ОБЩЕСТВО" | W65: Заявление Исковое заявление
A66: =SUBTOTAL(103,$F$1:F66)-1 -> 65 | B66: tendercds@mail.ru_x000D_ cds.duh@mail.ru_x000D_ cds@ncport.ru_x000D_ info@oaocds.ru_x000D_ oaocdsbuh@list.ru_x000D_ cds@oaocds.ru | C66: +7 (495) 628-47-48_x000D_ +7 (495) 628-62-45_x000D_ +7 (495) 625-55-49_x000D_ +7 (495) 628-57-93_x000D_ +7 (495) 928-47-48_x000D_ +7 (495) 279-56-38_x000D_ +7 (495) 528-06-54_x000D_ +7 (495) 626-62-45 | E66: https://kad.arbitr.ru/Card/b81df256-feb3-4a30-be05-be0719187bb9 | F66: А40-35566/2024 | G66: ООО "Макси Строй" | H66: 3907061089 | I66: АО "ЦДС" | J66: 7702059544 | K66: Теплинский Дмитрий Сергеевич | L66: 780528101649 | M66: 16869973 | N66: 45343 | O66: 636 | P66: 107031, город Москва, ул. Кузнецкий Мост, д.19 к.2 | Q66: АС города Москвы | R66: Строительство автомобильных дорог и автомагистралей (42.11) | S66: ОБЩЕСТВО С ОГРАНИЧЕННОЙ ОТВЕТСТВЕННОСТЬЮ "МАКСИ СТРОЙ" | U66: АКЦИОНЕРНОЕ ОБЩЕСТВО "ЦЕНТРОДОРСТРОЙ" | W66: Заявление Исковое заявление
A67: =SUBTOTAL(103,$F$1:F67)-1 -> 66 | B67: ct-ctc2017@yandex.ru | E67: https://kad.arbitr.ru/Card/f30a4aa7-5455-4314-b23e-6cf62c2ac6cc | F67: А40-35488/2024 | G67: ООО "Развитие" | H67: 1832156837 | I67: ООО "СК "Пантеон" | J67: 7713772362 | K67: Кайтуков Андрей Казбекович | L67: 502239769515 | M67: 4265108 | N67: 45343 | O67: 12 | P67: 117218, город Москва, Большая Черёмушкинская ул, д. 34, этаж 3 помещ. 324,323/ком 323.1, 323.2, 323.3 | Q67: АС города Москвы | R67: Строительство жилых и нежилых зданий (41.2) | S67: ОБЩЕСТВО С ОГРАНИЧЕННОЙ ОТВЕТСТВЕННОСТЬЮ "РАЗВИТИЕ" | U67: ОБЩЕСТВО С ОГРАНИЧЕННОЙ ОТВЕТСТВЕННОСТЬЮ "СК "ПАНТЕОН" | W67: Заявление Исковое заявление
A68: =SUBTOTAL(103,$F$1:F68)-1 -> 67 | E68: https://kad.arbitr.ru/Card/d8868639-d0ed-44a1-8a46-4d46cfc0f7ed | F68: А40-35395/2024 | G68: ИП Епихин Дмитрий Андреевич | H68: 772426726014 | I68: ООО "Всеновостройки.Ру" | J68: 7724415683 | K68: Лузанова Анастасия Николаевна | L68: 502100175499 | M68: 800000 | N68: 45343 | O68: 3 | P68: 117405, город Москва, Дорожная ул, д. 60б, офис 249 | Q68: АС города Москвы | R68: Деятельность рекламных агентств (73.11) | S68: ИП Епихин Дмитрий Андреевич | U68: ОБЩЕСТВО С ОГРАНИЧЕННОЙ ОТВЕТСТВЕННОСТЬЮ "ВСЕНОВОСТРОЙКИ.РУ" | W68: Заявление Исковое заявление
A69: =SUBTOTAL(103,$F$1:F69)-1 -> 68 | B69: rzd@rzd.ru_x000D_ poddymnikovaov@wsr.ru_x000D_ DKRE-Mahalov@kbsh.rzd.ru_x000D_ dtv-3.rzd@bk.ru_x000D_ echekunova@skzd.rzd.ru_x000D_ EPBelenkaiakr@skzd.rzd.ru_x000D_ fax@css.rzd.ru_x000D_ gorkdmkadr@gmail.com_x000D_ kuzmenkovagv@center.rzd.ru_x000D_ mivc@mzd.ru_x000D_ mrzd_KostrovaSA@orw.ru_x000D_ NEKolesnikova@serw.ru_x000D_ Ngs_s@svrw.ru_x000D_ sevtcfto@yandex.ru_x000D_ TuizovaTA@mail.zabtrans.ru | C69: +7 (499) 262-99-01_x000D_ +7 (499) 262-10-02_x000D_ 8 (800) 775-00-00_x000D_ +7 (4852) 52-18-30_x000D_ +7 (3012) 28-25-04_x000D_ +7 (3022) 22-33-05_x000D_ +7 (3022) 22-46-03_x000D_ +7 (3022) 22-46-72_x000D_ +7 (3022) 22-75-05_x000D_ +7 (3022) 24-18-00_x000D_ +7 (3022) 24-22-25_x000D_ +7 (3022) 24-45-58_x000D_ +7 (30241) 2-40-54_x000D_ +7 (342) 230-22-25_x000D_ +7 (343) 358-22-25_x000D_ +7 (343) 358-22-60_x000D_ +7 (343) 358-29-32_x000D_ +7 (343) 358-40-88_x000D_ +7 (343) 358-44-00_x000D_ +7 (343) 358-48-10_x000D_ +7 (343) 358-48-48_x000D_ +7 (343) 358-48-89_x000D_ +7 (343) 358-57-27_x000D_ +7 (343) 380-14-74_x000D_ +7 (343) 380-17-54_x000D_ +7 (3435) 49-42-39_x000D_ +7 (3452) 52-31-40_x000D_ +7 (3452) 52-38-48_x000D_ +7 (3462) 39-35-33_x000D_ +7 (347) 229-63-15_x000D_ +7 (347) 253-14-52_x000D_ +7 (351) 259-29-04_x000D_ +7 (351) 263-84-82_x000D_ +7 (351) 268-21-40_x000D_ +7 (351) 268-39-12_x000D_ +7 (351) 268-65-09_x000D_ +7 (3513) 69-21-40_x000D_ +7 (3812) 44-30-79_x000D_ +7 (383) 229-20-20_x000D_ +7 (383) 229-36-02_x000D_ +7 (383) 229-48-02_x000D_ +7 (383) 229-50-27_x000D_ +7 (383) 334-02-43_x000D_ +7 (3842) 32-23-79_x000D_ +7 (3842) 32-39-50_x000D_ +7 (3852) 29-20-48_x000D_ +7 (3902) 29-45-66_x000D_ +7 (3912) 23-13-28_x000D_ +7 (3912) 48-04-35_x000D_ +7 (3912) 48-05-59_x000D_ +7 (3912) 59-52-98_x000D_ +7 (3952) 63-22-46_x000D_ +7 (3952) 63-42-66_x000D_ +7 (3952) 63-84-79_x000D_ +7 (3952) 64-42-46_x000D_ +7 (3952) 64-48-48_x000D_ +7 (3952) 64-51-55_x000D_ +7 (3953) 49-79-79_x000D_ +7 (4012) 58-61-01_x000D_ +7 (4012) 58-72-02_x000D_ +7 (41656) 7-20-00_x000D_ +7 (4212) 38-12-27_x000D_ +7 (4212) 38-37-18_x000D_ +7 (4212) 38-38-80_x000D_ +7 (4212) 38-41-36_x000D_ +7 (4212) 38-47-19_x000D_ +7 (4212) 38-48-43_x000D_ +7 (4212) 38-48-48_x000D_ +7 (4212) 38-53-57_x000D_ +7 (4212) 38-81-91_x000D_ +7 (4212) 38-88-34_x000D_ +7 (4712) 55-23-00_x000D_ +7 (4712) 55-57-54_x000D_ +7 (4722) 76-03-04_x000D_ +7 (4722) 76-05-25_x000D_ +7 (4732) 48-83-14_x000D_ +7 (4732) 65-08-10_x000D_ +7 (4732) 65-08-28_x000D_ +7 (4732) 65-22-64_x000D_ +7 (4732) 65-23-51_x000D_ +7 (4732) 65-28-32_x000D_ +7 (4732) 65-38-34_x000D_ +7 (4732) 65-44-50_x000D_ +7 (4732) 65-66-22_x000D_ +7 (4732) 65-72-81_x000D_ +7 (47391) 4-17-26_x000D_ +7 (47391) 7-59-64_x000D_ +7 (47545) 3-21-40_x000D_ +7 (47545) 3-22-76_x000D_ +7 (4812) 39-52-25_x000D_ +7 (4842) 78-52-95_x000D_ +7 (4852) 49-50-02_x000D_ +7 (4852) 52-40-86_x000D_ +7 (4852) 52-52-43_x000D_ +7 (4852) 79-22-41_x000D_ +7 (4852) 79-35-60_x000D_ +7 (4852) 79-43-14_x000D_ +7 (4852) 79-44-00_x000D_ +7 (4872) 20-20-80_x000D_ +7 (4872) 20-20-93 | D69: http://www.e-disclosure.ru/portal/company.aspx?id=4543_x000D_ http://www.rzd.ru/_x000D_ http://altaitursib.ru/_x000D_ http://dss-sverdl.ru/_x000D_ http://dzvr.ru/about/structure/_x000D_ http://krw.ru/_x000D_ http://kzd.web.rzd/_x000D_ http://rzd.ru/_x000D_ http://www.cm.rzd.ru/_x000D_ http://www.css-rzd.ru/_x000D_ http://www.kras.rzd.ru/_x000D_ http://www.nrr.cm.rzd.ru/_x000D_ http://www.pkbct.ru/_x000D_ http://www.rmzhoper.ru/_x000D_ http://www.rzd.ru/ent/public/ru?STRUCTURE_ID=5185&amp;layer_id=5554&amp;refererLayerId=5553&amp;id=1015_x000D_ http://www.rzd.ru/ent/public/ru?STRUCTURE_ID=5185&amp;layer_id=5554&amp;refererLayerId=5553&amp;id=4347_x000D_ http://www.trudvsem.ru/_x000D_ http://www.uvzd.rzd.ru/_x000D_ http://www.web.rzd/_x000D_ https://www.list-org.com/go?site=804719 | E69: https://kad.arbitr.ru/Card/01c38e36-36b4-44d6-9c50-5947fcd80401 | F69: А40-35346/2024 | G69: ООО "Эколайн" | H69: 7719843549 | I69: ОАО "РЖД" | J69: 7708503727 | K69: Белозёров Олег Валентинович | L69: 781306504007 | M69: 731515.08 | N69: 45343 | O69: 220462 | P69: 107174, город Москва, Новая Басманная ул, д. 2/1 стр. 1 | Q69: АС города Москвы | R69: Деятельность железнодорожного транспорта: грузовые перевозки (49.20) | S69: ОБЩЕСТВО С ОГРАНИЧЕННОЙ ОТВЕТСТВЕННОСТЬЮ "ЭКОЛАЙН" | U69: ОТКРЫТОЕ АКЦИОНЕРНОЕ ОБЩЕСТВО "РОССИЙСКИЕ ЖЕЛЕЗНЫЕ ДОРОГИ" | W69: Заявление Исковое заявление
A70: =SUBTOTAL(103,$F$1:F70)-1 -> 69 | C70: +7 (937) 154-99-77 | E70: https://kad.arbitr.ru/Card/dc11366b-0a11-4721-a0e9-7adb6f4411d4 | F70: А40-35292/2024 | G70: ООО "Всеинструменты.Ру" | H70: 7722753969 | I70: ООО "Дип-Строй" | J70: 0267022157 | K70: Лысюк Дмитрий Юрьевич | L70: 026705057874 | M70: 711829.22 | N70: 45343 | O70: 36 | P70: 453838, Республика Башкортостан, город Сибай, Индустриальное ш, д. 1, помещ. 24 | Q70: АС города Москвы | R70: Строительство жилых и нежилых зданий (41.20) | S70: ОБЩЕСТВО С ОГРАНИЧЕННОЙ ОТВЕТСТВЕННОСТЬЮ "ВСЕИНСТРУМЕНТЫ.РУ" | U70: ОБЩЕСТВО С ОГРАНИЧЕННОЙ ОТВЕТСТВЕННОСТЬЮ "ДИП-СТРОЙ" | W70: Заявление Исковое заявление
A71: =SUBTOTAL(103,$F$1:F71)-1 -> 70 | B71: terekhov6969@mail.ru | E71: https://kad.arbitr.ru/Card/0de2c44c-ed75-4072-b769-f7a8a7ddf823 | F71: А40-35257/2024 | G71: ООО "Биджи Инжиниринг" | H71: 5047194537 | I71: ООО "СК Паритет" | J71: 5032333890 | K71: Терехов Олег Евгеньевич | L71: 402702232046 | M71: 2181198 | N71: 45343 | O71: 3 | P71: 143002, Московская область, г Одинцово, Акуловская ул, д. 1, офис 34/2 | Q71: АС города Москвы | R71: Производство санитарно-технических работ, монтаж отопительных систем и систем кондиционирования воздуха (43.22) | S71: ОБЩЕСТВО С ОГРАНИЧЕННОЙ ОТВЕТСТВЕННОСТЬЮ "БИДЖИ ИНЖИНИРИНГ" | U71: ОБЩЕСТВО С ОГРАНИЧЕННОЙ ОТВЕТСТВЕННОСТЬЮ "СК ПАРИТЕТ" | W71: Заявление Исковое заявление
A72: =SUBTOTAL(103,$F$1:F72)-1 -> 71 | B72: assistant_spb@rosinter.ru_x000D_ nlibkina@rosinter.ru_x000D_ ikirushina@rosinter.ru_x000D_ mrumyantseva@rosinter.ru_x000D_ nbodrova@rosinter.ru_x000D_ oeliseeva@rosinter.ru_x000D_ mushakova@rosinter.ru | C72: +7 (495) 788-44-88_x000D_ +7 (960) 244-09-33_x000D_ +7 (495) 424-61-20_x000D_ +7 (495) 788-44-88, доб 2586_x000D_ +7 (812) 331-88-47_x000D_ +7 (903) 735-24-27_x000D_ +7 (967) 174-54-29_x000D_ +7 (495) 956-47-05_x000D_ +7 (4967) 52-54-85_x000D_ +7 (952) 459-92-98 | D72: http://www.rosinter.ru/ | E72: https://kad.arbitr.ru/Card/ea0d2527-e458-48f2-9190-6e174aa43ad7 | F72: А40-35222/2024 | G72: ООО "Торговый Дом "Таганка М" | H72: 7709217912 | I72: ООО "РОСИНТЕР Ресторантс" | J72: 7737115648 | K72: Костеева Маргарита Валерьевна | L72: 774304331301 | M72: 5747741.1 | N72: 45343 | O72: 362 | P72: 111024, город Москва, Душинская ул., д. 7 стр 1 | Q72: АС города Москвы | R72: Деятельность ресторанов и услуги по доставке продуктов питания (56.10) | S72: ОБЩЕСТВО С ОГРАНИЧЕННОЙ ОТВЕТСТВЕННОСТЬЮ "ТОРГОВЫЙ ДОМ "ТАГАНКА М" | U72: ОБЩЕСТВО С ОГРАНИЧЕННОЙ ОТВЕТСТВЕННОСТЬЮ "РЕСТОРАННАЯ ОБЪЕДИНЕННАЯ СЕТЬ И НОВЕЙШИЕ ТЕХНОЛОГИИ ЕВРОАМЕРИКАНСКОГО РАЗВИТИЯ РЕСТОРАНТС" | W72: Заявление Исковое заявление
A73: =SUBTOTAL(103,$F$1:F73)-1 -> 72 | B73: buh@prostor.ru | C73: +7 (495) 502-81-71 | E73: https://kad.arbitr.ru/Card/129d2de5-7329-4db7-aca8-38c46f0782cb | F73: А40-35247/2024 | G73: ООО "Академия Льда" | H73: 9715321714 | I73: ООО "Простор-Л" | J73: 5018183386 | K73: Солдатов Василий Григорьевич | L73: 501800963408 | M73: 633500 | N73: 45343 | O73: 6 | P73: 141070, Московская область, город Королёв, ул. Циолковского, д. 2а, помещ. VIII | Q73: АС города Москвы | R73: Производство промышленного холодильного и вентиляционного оборудования (28.25) | S73: ОБЩЕСТВО С ОГРАНИЧЕННОЙ ОТВЕТСТВЕННОСТЬЮ "АКАДЕМИЯ ЛЬДА" | U73: ОБЩЕСТВО С ОГРАНИЧЕННОЙ ОТВЕТСТВЕННОСТЬЮ "ПРОСТОР-Л" | W73: Заявление Исковое заявление
A74: =SUBTOTAL(103,$F$1:F74)-1 -> 73 | B74: trcont@trcont.ru_x000D_ chita.trcont@mail.ru_x000D_ kulkovrs@trcont.ru_x000D_ deynegaon@trcont.ru_x000D_ golovinda@trcont.ru_x000D_ gurianovaius@trcont.ru_x000D_ komisarovdg@trcont.ru_x000D_ kraszd@trcont.ru_x000D_ lin.vitebsk@yandex.ru_x000D_ lukaninav@trcont.ru_x000D_ lupandinov@trcont.ru_x000D_ skzd@trcont.ru_x000D_ tr@m.ru_x000D_ vszd@trcont.ru_x000D_ zszd@trcont.ru_x000D_ AlbitovaTN@trcont.ru | C74: +7 (3022) 22-54-69_x000D_ +7 (3022) 32-52-11_x000D_ +7 (383) 222-21-00_x000D_ +7 (3912) 48-00-45_x000D_ +7 (495) 262-85-06_x000D_ +7 (495) 788-17-17_x000D_ +7 (499) 262-75-78_x000D_ +7 (831) 248-42-53_x000D_ +7 (3022) 22-00-39_x000D_ +7 (3022) 22-00-58_x000D_ +7 (343) 380-12-00_x000D_ +7 (343) 380-12-46_x000D_ +7 (383) 229-42-27_x000D_ +7 (383) 248-03-19_x000D_ +7 (3912) 48-00-36_x000D_ +7 (3912) 48-13-22_x000D_ +7 (3952) 64-20-24_x000D_ +7 (4212) 45-12-10_x000D_ +7 (4852) 79-88-81_x000D_ +7 (812) 458-67-99_x000D_ +7 (831) 224-84-25, доб 3_x000D_ +7 (831) 248-27-47_x000D_ +7 (831) 275-69-84_x000D_ +7 (8793) 39-85-22_x000D_ +7 (4732) 65-35-08_x000D_ +7 (8452) 39-00-54_x000D_ +7 (863) 259-46-76_x000D_ +7 (863) 282-95-03_x000D_ +7 (3912) 48-00-31_x000D_ +7 (383) 227-18-52_x000D_ +7 (3952) 64-20-20_x000D_ +7 (831) 248-37-29_x000D_ +7 (812) 458-68-00_x000D_ +7 (499) 262-51-71_x000D_ +7 (4212) 38-55-08_x000D_ +7 (4852) 23-02-77_x000D_ +7 (3022) 22-71-18_x000D_ +7 (383) 229-47-57_x000D_ +7 (3912) 24-80-04, доб 5_x000D_ +7 (3952) 64-59-48_x000D_ +7 (3952) 64-59-50_x000D_ +7 (4212) 38-47-52_x000D_ +7 (4212) 38-54-72_x000D_ +7 (4732) 55-83-23_x000D_ +7 (4852) 23-01-20_x000D_ +7 (495) 262-75-78_x000D_ +7 (495) 495-26-23, доб 300_x000D_ +7 (495) 495-26-26, доб 135_x000D_ +7 (499) 154-82-02_x000D_ +7 (812) 458-68-04_x000D_ +7 (812) 458-91-18_x000D_ +7 (8452) 39-00-48_x000D_ +7 (846) 303-24-68_x000D_ +7 (863) 259-08-98_x000D_ +7 (863) 269-92-28_x000D_ +7 (499) 262-33-00_x000D_ +7 (495) 222-21-00_x000D_ +7 (3022) 22-00-29_x000D_ +7 (3466) 46-75-06_x000D_ +7 (495) 788-17-17, доб 4812_x000D_ +7 (3022) 22-59-25_x000D_ +7 (351) 259-22-61_x000D_ +7 (4212) 45-12-10, доб 8_x000D_ +7 (499) 788-17-17_x000D_ +7 (351) 259-24-79_x000D_ +7 (831) 248-80-02_x000D_ +7 (812) 495-41-76_x000D_ +7 (343) 262-85-06_x000D_ +7 (499) 262-85-06_x000D_ +7 (343) 380-12-00, доб 5007_x000D_ +7 (343) 380-12-00, доб 5008_x000D_ +7 (863) 259-08-74_x000D_ +7 (4212) 45-12-19_x000D_ +7 (495) 266-11-86 | D74: http://www.e-disclosure.ru/portal/company.aspx?id=11194_x000D_ http://www.trcont.com/_x000D_ http://www.trcont.ru/_x000D_ https://trcont.com/ | E74: https://kad.arbitr.ru/Card/50d6b501-6538-43d7-a845-607545872969 | F74: А40-35177/2024 | G74: ООО "Восточный Экспресс" | H74: 9705096153 | I74: ПАО "Трансконтейнер" | J74: 7708591995 | K74: Концерев Михаил Рудольфович | L74: 781400896256 | M74: 2207842 | N74: 45343 | O74: 2669 | P74: 141402, Московская область, г Химки, Ленинградская ул, влд. 39 стр. 6, офис 3 (этаж 6) | Q74: АС города Москвы | R74: Деятельность вспомогательная прочая, связанная с перевозками (52.29) | S74: ОБЩЕСТВО С ОГРАНИЧЕННОЙ ОТВЕТСТВЕННОСТЬЮ "ВОСТОЧНЫЙ ЭКСПРЕСС" | U74: ПУБЛИЧНОЕ АКЦИОНЕРНОЕ ОБЩЕСТВО "ТРАНСКОНТЕЙНЕР" | W74: Заявление Исковое заявление
A75: =SUBTOTAL(103,$F$1:F75)-1 -> 74 | E75: https://kad.arbitr.ru/Card/8e334aac-c0c9-4381-ac3a-096e42662c7f | F75: А40-35186/2024 | G75: ООО "РАР" | H75: 1655294280 | I75: ООО "Газ-Автоматика" | J75: 1660199881 | K75: Зайцева Александра Сергеевна | L75: 161601918260 | M75: 7500000 | N75: 45343 | O75: 46 | P75: 420081, Республика Татарстан, г Казань, ул Седова, зд. 27 к. 3, этаж 2 помещ. 11 | Q75: АС города Москвы | R75: Строительство инженерных коммуникаций для водоснабжения и водоотведения, газоснабжения (42.21) | S75: ОБЩЕСТВО С ОГРАНИЧЕННОЙ ОТВЕТСТВЕННОСТЬЮ "РАР" | U75: ОБЩЕСТВО С ОГРАНИЧЕННОЙ ОТВЕТСТВЕННОСТЬЮ "ГАЗ-АВТОМАТИКА" | W75: Заявление Исковое заявление
A76: =SUBTOTAL(103,$F$1:F76)-1 -> 75 | B76: welcome@turandot-palace.ru_x000D_ razumova@maison-dellos.com | C76: +7 (495) 739-00-11_x000D_ +7 (495) 252-21-24_x000D_ +7 (919) 993-00-72_x000D_ +7 (495) 641-19-27_x000D_ +7 (495) 739-00-11, доб 3503_x000D_ +7 (495) 739-00-11, доб 3537_x000D_ +7 (495) 739-00-11, доб 3403_x000D_ +7 (495) 982-43-19 | D76: http://www.maison-dellos.com/ | E76: https://kad.arbitr.ru/Card/51363cb0-1894-43d5-8518-09ebcc4247c9 | F76: А40-35076/2024 | G76: ООО "Авентура" | H76: 7453190835 | I76: ООО "Юста Лайн" | J76: 7703286155 | K76: Сибиряков Артем Сергеевич | L76: 500122187014 | M76: 939708 | N76: 45343 | O76: 9 | P76: 125375, город Москва, Тверской б-р, д. 26а | Q76: АС города Москвы | R76: Деятельность ресторанов и услуги по доставке продуктов питания (56.10) | S76: ОБЩЕСТВО С ОГРАНИЧЕННОЙ ОТВЕТСТВЕННОСТЬЮ "АВЕНТУРА" | U76: ОБЩЕСТВО С ОГРАНИЧЕННОЙ ОТВЕТСТВЕННОСТЬЮ "ЮСТА ЛАЙН" | W76: Заявление Исковое заявление
A77: =SUBTOTAL(103,$F$1:F77)-1 -> 76 | B77: info@dolomant.ru | C77: +7 (495) 234-06-36_x000D_ +7 (495) 232-20-33_x000D_ +7 (495) 234-06-39_x000D_ +7 (495) 739-07-76_x000D_ +7 (495) 739-07-73_x000D_ +7 (499) 781-69-18_x000D_ +7 (495) 739-07-75_x000D_ +7 (8612) 24-95-13_x000D_ +7 (495) 232-16-54_x000D_ +7 (495) 232-20-22_x000D_ +7 (495) 232-39-93 | D77: http://www.dolomant.ru/_x000D_ http://www.fasteko.ru/ | E77: https://kad.arbitr.ru/Card/d59d286b-20f6-423c-a571-e60e8827d614 | F77: А40-35101/2024 | G77: ООО "Легат" | H77: 7728552360 | I77: ЗАО "НПФ "Доломант" | J77: 7728512529 | K77: Федякин Николай Викторович | L77: 772801332703 | M77: 2449484.2 | N77: 45343 | O77: 55 | P77: 117342, город Москва, ул. Введенского, д.3 | Q77: АС города Москвы | R77: Производство частей приборов и инструментов для навигации, управления, измерения, контроля, испытаний и прочих целей (26.51.8) | S77: ОБЩЕСТВО С ОГРАНИЧЕННОЙ ОТВЕТСТВЕННОСТЬЮ "ЛЕГАТ" | U77: ЗАКРЫТОЕ АКЦИОНЕРНОЕ ОБЩЕСТВО "НАУЧНО-ПРОИЗВОДСТВЕННАЯ ФИРМА "ДОЛОМАНТ" | W77: Заявление Исковое заявление
A78: =SUBTOTAL(103,$F$1:F78)-1 -> 77 | B78: stspsila@mail.ru_x000D_ notarius001@mail.ru_x000D_ stroispetssila@mail.ru_x000D_ stroispetssilf@mail.ru_x000D_ stroy@mail.ru_x000D_ stroiSpetsSikf@mail.ru | C78: +7 (495) 733-57-28_x000D_ +7 (495) 773-41-58_x000D_ +7 (926) 000-23-65_x000D_ +7 (962) 951-20-01_x000D_ +7 (495) 733-57-31 | E78: https://kad.arbitr.ru/Card/d59d5475-fd9d-40f7-95ff-607d548daab0 | F78: А40-35070/2024 | G78: ООО "Инженерные Системы" | H78: 7724488650 | I78: ООО "Стройспецсила" | J78: 7715724438 | K78: Сухорученков Максим Сергеевич | L78: 673000764034 | M78: 1690892.3 | N78: 45343 | O78: 45 | P78: 119633, город Москва, Новоорловская ул., д. 7а, этаж 2 офис 217 | Q78: АС города Москвы | R78: Строительство жилых и нежилых зданий (41.20) | S78: ОБЩЕСТВО С ОГРАНИЧЕННОЙ ОТВЕТСТВЕННОСТЬЮ "ИНЖЕНЕРНЫЕ СИСТЕМЫ" | U78: ОБЩЕСТВО С ОГРАНИЧЕННОЙ ОТВЕТСТВЕННОСТЬЮ "СТРОЙСПЕЦСИЛА" | W78: Заявление Исковое заявление
A79: =SUBTOTAL(103,$F$1:F79)-1 -> 78 | B79: lyudino@bk.ru | E79: https://kad.arbitr.ru/Card/5b58b1ba-e2e4-4c84-8a31-ec9ab9851fc5 | F79: А40-35071/2024 | G79: ИП Сильченко Кристина Викторовна | H79: 231296792100 | I79: ООО "Людин" | J79: 9704084902 | K79: Паршина Татьяна Александровна | L79: 772607886235 | M79: 4847539 | N79: 45343 | O79: 1 | P79: 119121, город Москва, Ружейный пер, д. 3, этаж/помещ 1/XIV ком/офис 13/13-2 | Q79: АС города Москвы | R79: Торговля оптовая прочими машинами, приборами, аппаратурой и оборудованием общепромышленного и специального назначения (46.69.9) | S79: ИП Сильченко Кристина Викторовна | U79: ОБЩЕСТВО С ОГРАНИЧЕННОЙ ОТВЕТСТВЕННОСТЬЮ "ЛЮДИН" | W79: Заявление Исковое заявление
A80: =SUBTOTAL(103,$F$1:F80)-1 -> 79 | E80: https://kad.arbitr.ru/Card/7eacead3-ed26-4ebd-a619-8b8429b34957 | F80: А40-35009/2024 | G80: ООО "Строй Инвест" | H80: 9705083115 | I80: ООО "Диалог" | J80: 7721569999 | K80: Дмитриченкова Татьяна Владимировна | L80: 503111111925 | M80: 5398668.2 | N80: 45343 | O80: 2 | P80: 109377, город Москва, 1-Я Новокузьминская ул, д. 13/8, помещ. III,этаж п ком. 5 | Q80: АС города Москвы | R80: Деятельность ресторанов и услуги по доставке продуктов питания (56.10) | S80: ОБЩЕСТВО С ОГРАНИЧЕННОЙ ОТВЕТСТВЕННОСТЬЮ "СТРОЙ ИНВЕСТ" | U80: ОБЩЕСТВО С ОГРАНИЧЕННОЙ ОТВЕТСТВЕННОСТЬЮ "ДИАЛОГ" | W80: Заявление Исковое заявление
A81: =SUBTOTAL(103,$F$1:F81)-1 -> 80 | C81: +7 (926) 736-30-83 | E81: https://kad.arbitr.ru/Card/122b18ab-72f8-4bf1-b7c0-a80027a1035f | F81: А40-35007/2024 | G81: ООО "Ситистройтандем" | H81: 7725684512 | I81: ООО "Новация" | J81: 7721813020 | K81: Столярова Александра Валерьевна | L81: 772208775004 | M81: 768000 | N81: 45343 | O81: 2 | P81: 123317, город Москва, Звенигородское ш, д. 28 стр. 39 | Q81: АС города Москвы | R81: Строительство жилых и нежилых зданий (41.20) | S81: ОБЩЕСТВО С ОГРАНИЧЕННОЙ ОТВЕТСТВЕННОСТЬЮ "СИТИСТРОЙТАНДЕМ" | U81: ОБЩЕСТВО С ОГРАНИЧЕННОЙ ОТВЕТСТВЕННОСТЬЮ "НОВАЦИЯ" | W81: Заявление Исковое заявление
A82: =SUBTOTAL(103,$F$1:F82)-1 -> 81 | B82: usmr4511c@eandex.ru | C82: +7 (903) 744-55-25 | E82: https://kad.arbitr.ru/Card/cdcf6ce4-a2be-48b6-8b9f-357066e4b4c5 | F82: А40-34993/2024 | G82: ИП Красильников Илья Борисович | H82: 525910700458 | I82: ООО "Усмр-45" | J82: 7720413029 | K82: Балашов Илья Сергеевич | L82: 772032689567 | M82: 1695120.7 | N82: 45343 | O82: 39 | P82: 105118, город Москва, ул. Буракова, д. 27 к. 3, э 3 пом IV к 42 | Q82: АС города Москвы | R82: Строительство жилых и нежилых зданий (41.20) | S82: ИП Красильников Илья Борисович | U82: ОБЩЕСТВО С ОГРАНИЧЕННОЙ ОТВЕТСТВЕННОСТЬЮ "УСМР-45" | W82: Заявление Исковое заявление
A83: =SUBTOTAL(103,$F$1:F83)-1 -> 82 | C83: +7 (909) 949-99-88_x000D_ +7 (499) 450-99-21 | E83: https://kad.arbitr.ru/Card/27c50a41-c5b1-4038-8033-8171aed9c76f | F83: А40-35089/2024 | G83: ООО "Инженерные Системы" | H83: 7724488650 | I83: ООО "ТМ-Групп" | J83: 7707376804 | K83: Мальсагова Лейла Ахметовна | L83: 772618155413 | M83: 967234.33 | N83: 45343 | O83: 16 | P83: 115280, город Москва, ул Ленинская Слобода, д. 19, помещ. 22/2 | Q83: АС города Москвы | R83: Строительство жилых и нежилых зданий (41.20) | S83: ОБЩЕСТВО С ОГРАНИЧЕННОЙ ОТВЕТСТВЕННОСТЬЮ "ИНЖЕНЕРНЫЕ СИСТЕМЫ" | U83: ОБЩЕСТВО С ОГРАНИЧЕННОЙ ОТВЕТСТВЕННОСТЬЮ "ТМ-ГРУПП" | W83: Заявление Исковое заявление
A84: =SUBTOTAL(103,$F$1:F84)-1 -> 83 | C84: +7 (846) 241-77-10_x000D_ +7 (846) 222-41-77 | D84: http://tr-serv.ru/ | E84: https://kad.arbitr.ru/Card/ce790b60-b42b-4ff6-95c4-191682e86979 | F84: А40-36130/2024 | G84: ОАО "РЖД" | H84: 7708503727 | I84: ООО "Транзит Сервис" | J84: 6311048824 | K84: Климантова Елена Анатольевна | L84: 631902673883 | M84: 2541155.8 | N84: 45343 | O84: 6 | P84: 443082, Самарская область, город Самара, Владимирская ул., д.41а, офис 3-21 | Q84: АС города Москвы | R84: Деятельность вспомогательная прочая, связанная с перевозками (52.29) | S84: ОТКРЫТОЕ АКЦИОНЕРНОЕ ОБЩЕСТВО "РОССИЙСКИЕ ЖЕЛЕЗНЫЕ ДОРОГИ" | U84: ОБЩЕСТВО С ОГРАНИЧЕННОЙ ОТВЕТСТВЕННОСТЬЮ "ТРАНЗИТ СЕРВИС" | W84: Определение О принятии искового заявления (заявления) к производству
A85: =SUBTOTAL(103,$F$1:F85)-1 -> 84 | E85: https://kad.arbitr.ru/Card/fa5e316b-ed27-4abe-9dcf-eb43947ed88a | F85: А40-36143/2024 | I85: ИП Кудашов Андрей Павлович | J85: 690708315964 | K85: Кудашов Андрей Павлович | L85: 690708315964 | M85: 1073877.2 | N85: 45343 | O85: 8 | P85: Тверская область, Бологовский район, поселок городского типа Куженкино | Q85: АС города Москвы | R85: Торговля розничная по почте или по информационно-коммуникационной сети Интернет (47.91) | S85: Самоделова Лидия Николаевна | U85: ИП Кудашов Андрей Павлович | W85: Определение Об оставлении искового заявления (заявления) без движения
A86: =SUBTOTAL(103,$F$1:F86)-1 -> 85 | B86: vek_stroi@mail.ru | C86: +7 (86141) 3-22-96_x000D_ +7 (86141) 5-44-47_x000D_ +7 (86141) 3-26-56_x000D_ +7 (86141) 3-22-94_x000D_ +7 (86141) 5-10-36_x000D_ +7 (86141) 7-10-10_x000D_ +7 (928) 432-99-81_x000D_ +7 (928) 881-17-77_x000D_ +7 (964) 921-20-20 | E86: https://kad.arbitr.ru/Card/b62847d6-72ad-4f9c-9326-6ab90eab6751 | F86: А40-36113/2024 | G86: АО "Банк СГБ" | H86: 3525023780 | I86: ООО "ВЕК" | J86: 2304034735 | K86: Воронцов Владимир Васильевич | L86: 230403290931 | M86: 8591978.1 | N86: 45343 | O86: 2 | P86: 353460, Краснодарский край, г Геленджик, ул Островского, д. 141, кв. 312 | Q86: АС города Москвы | R86: Строительство жилых и нежилых зданий (41.20) | S86: АКЦИОНЕРНОЕ ОБЩЕСТВО "СЕВЕРГАЗБАНК" | U86: ОБЩЕСТВО С ОГРАНИЧЕННОЙ ОТВЕТСТВЕННОСТЬЮ "ВЕК" | W86: Определение Об оставлении искового заявления (заявления) без движения
A87: =SUBTOTAL(103,$F$1:F87)-1 -> 86 | B87: avtomdorogi@mail.ru_x000D_ skveto@mail.ru_x000D_ nsi-40@yandex.ru_x000D_ ador-kanc@dom.mos.ru_x000D_ ked@mail.ru_x000D_ ad.opt@mail.ru_x000D_ avto@mail.ru_x000D_ dmo-1@mail.ru_x000D_ dmu-1@mail.ru_x000D_ pkkr-avtodor@mail.ru_x000D_ dmu-1ok@yandex.ru | C87: +7 (495) 940-09-37_x000D_ +7 (495) 940-11-82_x000D_ +7 (495) 669-30-63_x000D_ +7 (495) 689-30-63, доб 2135_x000D_ +7 (499) 722-90-00_x000D_ +7 (903) 782-96-82_x000D_ +7(495)9400937_x000D_ +7(495)9408263_x000D_ +7 (495) 940-82-63_x000D_ +7(495)6894086_x000D_ +7 (495) 689-40-86_x000D_ +7 (495) 957-99-77_x000D_ +7 (495) 940-11-74_x000D_ +7 (495) 940-06-94_x000D_ +7 (495) 302-85-26 | D87: http://gbuador.ru/_x000D_ http://stroivisota.ru/ | E87: https://kad.arbitr.ru/Card/26f0a457-bf51-42ae-a640-632a6d9c111b | F87: А40-36139/2024 | G87: ФКУ "Войсковая Часть 33877" | H87: 5048022643 | I87: ГБУ "Автомобильные Дороги" | J87: 7727656790 | K87: Орешкин Александр Станиславович | L87: 771002705058 | M87: 748425.5 | N87: 45343 | O87: 1837 | P87: 123007, город Москва, 1-Я Магистральная ул, д. 23 стр. 21 | Q87: АС города Москвы | R87: Деятельность по эксплуатации автомобильных дорог и автомагистралей (52.21.22) | S87: ФЕДЕРАЛЬНОЕ КАЗЕННОЕ УЧРЕЖДЕНИЕ "ВОЙСКОВАЯ ЧАСТЬ 33877" | U87: ГОСУДАРСТВЕННОЕ БЮДЖЕТНОЕ УЧРЕЖДЕНИЕ ГОРОДА МОСКВЫ "АВТОМОБИЛЬНЫЕ ДОРОГИ" | W87: Заявление Исковое заявление
A88: =SUBTOTAL(103,$F$1:F88)-1 -> 87 | B88: vage@mira.company_x000D_ adfn@mail.ru_x000D_ aleksandr@mira.compani_x000D_ carlos@mira.company_x000D_ carlos@mira.company.ru_x000D_ eldar@mira.company_x000D_ info@k-agent.ru_x000D_ info@mira.msk.ru_x000D_ mira@mail.ru_x000D_ net@net.ru_x000D_ ohota69@mail.ru_x000D_ romanenko@mira.company_x000D_ tender@mira.company_x000D_ timur@mira.company_x000D_ zakaz@mail.ru | C88: +7 (495) 380-36-61_x000D_ +7 (4822) 50-98-01_x000D_ +7 (495) 380-38-61_x000D_ +7 (495) 545-41-58_x000D_ +7 (495) 651-61-66_x000D_ +7 (495) 901-66-30, доб 107_x000D_ +7 (495) 902-66-30, доб 104_x000D_ +7 (495) 902-66-30, доб 107_x000D_ +7 (495) 902-66-30, доб 111_x000D_ +7 (495) 902-66-30, доб 115_x000D_ +7 (495) 902-66-39_x000D_ +7 (495) 902-66-70_x000D_ +7 (495) 906-66-30_x000D_ +7 (499) 707-14-23_x000D_ +7 (84722) 3-56-35, доб 6_x000D_ +7 (962) 939-91-39_x000D_ +7 (969) 123-93-29_x000D_ +7 (495) 902-66-30_x000D_ +7 (906) 738-14-35_x000D_ +7 (495) 903-63-30_x000D_ +7 (495) 380-38-61, доб 107_x000D_ +7 (495) 902-66-30, доб 114_x000D_ +7 (495) 902-66-30, доб 100_x000D_ +7 (926) 665-34-55 | E88: https://kad.arbitr.ru/Card/7b72dd2c-4cac-4020-9664-dbdd5c458e0b | F88: А40-36072/2024 | G88: АО "Крафтвэй Корпорэйшн ПЛС" | H88: 5018037096 | I88: ООО "Мира" | J88: 7716735094 | K88: Арутюнян Ваге Эдуардович | L88: 772465217878 | M88: 11880355 | N88: 45343 | O88: 16 | P88: 129327, город Москва, ул. Коминтерна, д.7 к.2 | Q88: АС города Москвы | R88: Торговля оптовая компьютерами, периферийными устройствами к компьютерам и программным обеспечением (46.51) | S88: АКЦИОНЕРНОЕ ОБЩЕСТВО "КРАФТВЭЙ КОРПОРЭЙШН ПЛС" | U88: ОБЩЕСТВО С ОГРАНИЧЕННОЙ ОТВЕТСТВЕННОСТЬЮ "МИРА" | W88: Заявление Исковое заявление
A89: =SUBTOTAL(103,$F$1:F89)-1 -> 88 | C89: +7 (383) 213-31-32_x000D_ 8 (800) 511-87-82 | D89: http://sibm-nsk.com/_x000D_ http://stroystil-nsk.ru/ | E89: https://kad.arbitr.ru/Card/b92d66c8-321c-4059-a4f6-f83b19e16578 | F89: А40-36046/2024 | G89: ООО "Бизнес-Сервис" | H89: 5402491728 | I89: ООО "НСК-Механизация" | J89: 5405040160 | K89: Чугуевский Павел Юрьевич | L89: 542222858466 | M89: 2987154.6 | N89: 45343 | O89: 11 | P89: 630073, Новосибирская область, г Новосибирск, Геодезическая ул, д. 2/1, подв. б/н помещ. 30 | Q89: АС города Москвы | R89: Деятельность автомобильного грузового транспорта (49.41) | S89: ОБЩЕСТВО С ОГРАНИЧЕННОЙ ОТВЕТСТВЕННОСТЬЮ "БИЗНЕС-СЕРВИС" | U89: ОБЩЕСТВО С ОГРАНИЧЕННОЙ ОТВЕТСТВЕННОСТЬЮ "НСК-МЕХАНИЗАЦИЯ" | W89: Заявление Исковое заявление
A90: =SUBTOTAL(103,$F$1:F90)-1 -> 89 | E90: https://kad.arbitr.ru/Card/b993819f-fe50-49db-95b8-04f52c505ee2 | F90: А40-35987/2024 | G90: ИП Монахов Игорь Сергеевич | H90: 771908810164 | I90: ООО "Интекс" | J90: 7725378547 | K90: Крылова Елена Михайловна | L90: 323300381890 | M90: 3891906.1 | N90: 45343 | O90: 18 | P90: 115280, город Москва, ул. Ленинская Слобода, д. 19, офис 41х1д | Q90: АС города Москвы | R90: Торговля розничная одеждой в специализированных магазинах (47.71) | S90: ИП Монахов Игорь Сергеевич | U90: ОБЩЕСТВО С ОГРАНИЧЕННОЙ ОТВЕТСТВЕННОСТЬЮ "ИНТЕКС" | W90: Заявление Исковое заявление
A91: =SUBTOTAL(103,$F$1:F91)-1 -> 90 | B91: taser.m@mail.ru_x000D_ dvor.2019@yandex.ru | C91: +79266339592_x000D_ +7 (904) 494-01-42 | E91: https://kad.arbitr.ru/Card/ac413630-15b7-4ae5-aaeb-3689743a8eca | F91: А40-36173/2024 | G91: ООО "Тинкер" | H91: 9724075906 | I91: ООО "Чистый Двор" | J91: 7203444759 | K91: Государев Константин Сергеевич | L91: 772904759494 | M91: 2246377.5 | N91: 45344 | O91: 13 | P91: 625026, Тюменская область, г Тюмень, ул 50 Лет Влксм, д. 51, офис 512 | Q91: АС города Москвы | R91: Управление эксплуатацией жилого фонда за вознаграждение или на договорной основе (68.32.1) | S91: ОБЩЕСТВО С ОГРАНИЧЕННОЙ ОТВЕТСТВЕННОСТЬЮ "ТИНКЕР" | U91: ОБЩЕСТВО С ОГРАНИЧЕННОЙ ОТВЕТСТВЕННОСТЬЮ "ЧИСТЫЙ ДВОР" | W91: Заявление Исковое заявление
A92: =SUBTOTAL(103,$F$1:F92)-1 -> 91 | B92: fgup18@yandex.ru_x000D_ c-s@v1a.ru_x000D_ 18bux@mail.ru_x000D_ 18cnif-fes@mil.ru_x000D_ 18cnii-fes@mil.ru_x000D_ bux@mail.ru_x000D_ cnii-fes@mil.ru_x000D_ knii@kursktellekom.ru_x000D_ omto46@kursktelecom.ru_x000D_ shalimovalera@mail.ru | C92: +7 (495) 302-94-40_x000D_ +7 (4712) 58-80-90_x000D_ +7 (910) 270-03-70_x000D_ +7 (4712) 58-87-59_x000D_ +7 (4712) 58-80-55_x000D_ +7 (495) 303-43-95_x000D_ +7 (495) 302-94-14 | E92: https://kad.arbitr.ru/Card/63656c6f-547a-45e3-bdb9-6b97f6d47ee9 | F92: А40-35910/2024 | G92: АО "Концерн "Созвездие" | H92: 3666127502 | I92: ФГУП "18 ЦНИИ" МО РФ | J92: 7720090314 | K92: Швыдя Олег Викторович | L92: 772033573491 | M92: 1416698.4 | N92: 45343 | O92: 286 | P92: 111558, город Москва, Свободный пр-кт, д. 4 | Q92: АС города Москвы | R92: Научные исследования и разработки в области естественных и технических наук прочие (72.19) | S92: АКЦИОНЕРНОЕ ОБЩЕСТВО "КОНЦЕРН "СОЗВЕЗДИЕ" | U92: ФЕДЕРАЛЬНОЕ ГОСУДАРСТВЕННОЕ УНИТАРНОЕ ПРЕДПРИЯТИЕ "18 ЦЕНТРАЛЬНЫЙ НАУЧНО-ИССЛЕДОВАТЕЛЬСКИЙ ИНСТИТУТ" МИНИСТЕРСТВА ОБОРОНЫ РОССИЙСКОЙ ФЕДЕРАЦИИ | W92: Заявление Исковое заявление
A93: =SUBTOTAL(103,$F$1:F93)-1 -> 92 | B93: eko-holding@mail.ru_x000D_ bukhgalter1@eko-holding.com_x000D_ ecoholding1@gmail.com_x000D_ eko-holding@mai.ru_x000D_ eko5042341@gmail.com_x000D_ ekoholding1@gmail.com_x000D_ ekoholding@gmail.com_x000D_ info@k-agent.ru | C93: +7 (495) 123-45-67_x000D_ +7 (495) 504-23-41_x000D_ +7 (903) 180-70-00_x000D_ +7 (495) 640-16-79_x000D_ +7 (916) 136-22-67 | E93: https://kad.arbitr.ru/Card/0aba6be1-1527-4cff-bee8-96b4e8b1cee5 | F93: А40-35832/2024 | G93: ООО "Ситистройтандем" | H93: 7725684512 | I93: ООО "Эко Холдинг" | J93: 5074036642 | K93: Башмаков Виталий Николаевич | L93: 775101365674 | M93: 719880 | N93: 45343 | O93: 55 | P93: 115054, город Москва, Большая Пионерская ул, д. 15 стр. 1, помещ. 1/1 | Q93: АС города Москвы | R93: Строительство жилых и нежилых зданий (41.2) | S93: ОБЩЕСТВО С ОГРАНИЧЕННОЙ ОТВЕТСТВЕННОСТЬЮ "СИТИСТРОЙТАНДЕМ" | U93: ОБЩЕСТВО С ОГРАНИЧЕННОЙ ОТВЕТСТВЕННОСТЬЮ "ЭКО ХОЛДИНГ" | W93: Определение Об оставлении искового заявления (заявления) без движения
A94: =SUBTOTAL(103,$F$1:F94)-1 -> 93 | B94: info@nsgd.ru_x000D_ irina.kuleshova@nsgd.ru | C94: +7 (495) 643-10-22_x000D_ +7 (495) 545-37-36_x000D_ +7 (495) 643-10-22, доб 5277_x000D_ +7 (495) 643-10-22, доб 5401_x000D_ +7 (922) 462-14-87_x000D_ +7 (926) 912-06-78_x000D_ +7 (495) 643-10-16, доб 5067 | E94: https://kad.arbitr.ru/Card/e0e22bc2-d3aa-4b05-bb2d-52be60810f0e | F94: А40-35918/2024 | G94: ООО "Всеинструменты.Ру" | H94: 7722753969 | I94: ООО "НСГД" | J94: 8903018853 | K94: Гафаров Руслан Рафкатович | L94: 503417787559 | M94: 1528319.4 | N94: 45343 | O94: 255 | P94: 119180, город Москва, ул. Малая Полянка, д. 2, пом II ком 36,37,38 | Q94: АС города Москвы | R94: Строительство жилых и нежилых зданий (41.20) | S94: ОБЩЕСТВО С ОГРАНИЧЕННОЙ ОТВЕТСТВЕННОСТЬЮ "ВСЕИНСТРУМЕНТЫ.РУ" | U94: ОБЩЕСТВО С ОГРАНИЧЕННОЙ ОТВЕТСТВЕННОСТЬЮ "НАДЫМСТРОЙГАЗДОБЫЧА" | W94: Заявление Исковое заявление
A95: =SUBTOTAL(103,$F$1:F95)-1 -> 94 | B95: postman@rosneft.ru_x000D_ a_dvornikov@rosneft.ru_x000D_ a_panov@rosneft.ru_x000D_ a_pashali@rosneft.ru_x000D_ a_yarimaka@rosneft.ru_x000D_ e_efimenko@rosneft.ru_x000D_ e_farafonov@rosneft.ru_x000D_ vumetrofanov@rosneft.ru_x000D_ i_kudryashova@rosneft.ru | C95: +7 (495) 777-44-22_x000D_ +7 (499) 517-88-88_x000D_ +7 (499) 517-72-35_x000D_ +7 (499) 517-88-99_x000D_ +7 (495) 777-44-00_x000D_ +7 (495) 777-44-77_x000D_ +7 (495) 777-45-64_x000D_ +7 (495) 777-77-31_x000D_ +7 (499) 517-82-21_x000D_ +7 (499) 517-88-89_x000D_ +7 (4862) 43-21-76_x000D_ +7 (3463) 31-01-50_x000D_ +7 (34936) 3-18-99_x000D_ +7 (34936) 5-12-72_x000D_ +7 (4217) 56-52-04_x000D_ +7 (495) 730-35-13_x000D_ +7 (499) 515-32-40_x000D_ +7 (818) 221-75-42_x000D_ +7 (818) 221-75-45_x000D_ +7 (8612) 01-67-81_x000D_ +7 (86558) 2-22-83_x000D_ +7 (962) 493-63-41_x000D_ +7 (495) 517-88-99_x000D_ +7 (499) 951-78-89, доб 9_x000D_ +7 (499) 514-88-99_x000D_ +7 (926) 007-17-09_x000D_ +7 (499) 517-86-53_x000D_ +7 (499) 514-40-94_x000D_ +7 (916) 713-44-00_x000D_ +7 (495) 239-88-00_x000D_ +7 (499) 517-81-09_x000D_ +7 (499) 517-82-12_x000D_ +7 (499) 518-88-88_x000D_ +7 (499) 517-88-11_x000D_ +7 (495) 748-64-24_x000D_ +7 (499) 513-31-36_x000D_ +7 (499) 517-80-80_x000D_ +7 (495) 777-45-57_x000D_ +7 (499) 513-53-54_x000D_ +7 (499) 777-44-22_x000D_ +7 (495) 230-29-45_x000D_ +7 (495) 777-46-01_x000D_ +7 (495) 980-59-00, доб 1165_x000D_ +7 (499) 517-86-34_x000D_ +7 (499) 517-88-59_x000D_ +7 (495) 411-05-04_x000D_ +7 (499) 517-88-65_x000D_ +7 (495) 987-30-60_x000D_ +7 (495) 777-44-22, доб 6_x000D_ 8 (800) 500-11-00_x000D_ +7 (495) 517-88-88_x000D_ +7 (499) 517-88-88, доб 9655_x000D_ +7 (499) 517-88-88, доб 9429_x000D_ +7 (495) 212-05-68_x000D_ +7 (499) 555-55-55 | D95: http://www.rosneft.ru/ | E95: https://kad.arbitr.ru/Card/4423303e-6c22-47b5-8b15-805ebe54f7ea | F95: А40-35781/2024 | G95: ГУП СО "Газовые Сети" | H95: 6659106560 | I95: ПАО "НК "Роснефть" | J95: 7706107510 | K95: Сечин Игорь Иванович | L95: 770370393938 | M95: 6461193.8 | N95: 45343 | O95: 4170 | P95: 115035, город Москва, Софийская наб., д.26/1 | Q95: АС города Москвы | R95: Добыча нефти (06.10.1) | S95: ГОСУДАРСТВЕННОЕ УНИТАРНОЕ ПРЕДПРИЯТИЕ СВЕРДЛОВСКОЙ ОБЛАСТИ "ГАЗОВЫЕ СЕТИ" | U95: ПУБЛИЧНОЕ АКЦИОНЕРНОЕ ОБЩЕСТВО "НЕФТЯНАЯ КОМПАНИЯ "РОСНЕФТЬ" | W95: Заявление Исковое заявление
A96: =SUBTOTAL(103,$F$1:F96)-1 -> 95 | B96: mail@tisenergo.ru_x000D_ mail@tienergo.ru | C96: +7 (495) 789-68-34_x000D_ +7 (495) 789-68-34, доб 7_x000D_ +7 (985) 767-90-75, доб 39_x000D_ +7 (495) 789-85-76 | E96: https://kad.arbitr.ru/Card/63495461-704d-4feb-a52f-71f6443202a8 | F96: А40-36179/2024 | G96: ООО "Энергоальянс" | H96: 2310122757 | I96: ООО "ТИС-Энерго" | J96: 7704774589 | K96: Лукин Александр Андреевич | L96: 502918849638 | M96: 726640.15 | N96: 45344 | O96: 9 | P96: 123112, город Москва, Пресненская наб, д. 12, помещ. 10/45 | Q96: АС города Москвы | R96: Производство электромонтажных работ (43.21) | S96: ОБЩЕСТВО С ОГРАНИЧЕННОЙ ОТВЕТСТВЕННОСТЬЮ "ЭНЕРГОАЛЬЯНС" | U96: ОБЩЕСТВО С ОГРАНИЧЕННОЙ ОТВЕТСТВЕННОСТЬЮ "ТЕЛЕМЕХАНИКА И СВЯЗЬ В ЭЛЕКТРОЭНЕРГЕТИКЕ" | W96: Заявление Заявление о выдаче судебного приказа
A97: =SUBTOTAL(103,$F$1:F97)-1 -> 96 | C97: +7 (968) 604-47-93_x000D_ +7 (495) 662-94-93 | E97: https://kad.arbitr.ru/Card/86217bc1-be9c-4545-800d-8a3a5d4b5a35 | F97: А40-36185/2024 | G97: ООО "ПИИ Лигато" | H97: 1102049889 | I97: ООО "Союз Проект" | J97: 9702016696 | K97: Демидов Николай Николаевич | L97: 504404663942 | M97: 11507948 | N97: 45344 | O97: 25 | P97: 129110, город Москва, Орлово-Давыдовский пер., д. 1, э 1 п III ком 3 оф ф89 | Q97: АС города Москвы | R97: Деятельность в области архитектуры (71.11) | S97: ОБЩЕСТВО С ОГРАНИЧЕННОЙ ОТВЕТСТВЕННОСТЬЮ "ПРОЕКТНО-ИЗЫСКАТЕЛЬСКИЙ ИНСТИТУТ ЛИНЕЙНЫХ ГАЗОТРАНСПОРТНЫХ ОБЪЕКТОВ" | U97: ОБЩЕСТВО С ОГРАНИЧЕННОЙ ОТВЕТСТВЕННОСТЬЮ "СОЮЗ ПРОЕКТ" | W97: Заявление Исковое заявление
A98: =SUBTOTAL(103,$F$1:F98)-1 -> 97 | C98: +7 (928) 625-84-95 | E98: https://kad.arbitr.ru/Card/f081325e-e2f7-489a-b3e7-404b7438d61e | F98: А40-35349/2024 | G98: ООО "Артвайн" | H98: 7704853745 | I98: ООО "Победа61" | J98: 6166119114 | K98: Холопов Сергей Николаевич | L98: 616205447308 | M98: 1281954.2 | N98: 45343 | O98: 2 | P98: 344065, Ростовская область, г Ростов-На-Дону, Орская ул, зд. 31 стр. 1 | Q98: АС города Москвы | R98: Торговля розничная прочая в неспециализированных магазинах (47.19) | S98: ОБЩЕСТВО С ОГРАНИЧЕННОЙ ОТВЕТСТВЕННОСТЬЮ "АРТВАЙН" | U98: ОБЩЕСТВО С ОГРАНИЧЕННОЙ ОТВЕТСТВЕННОСТЬЮ "ПОБЕДА61" | W98: Заявление Исковое заявление
A99: =SUBTOTAL(103,$F$1:F99)-1 -> 98 | B99: zbpo36@gmail.com | C99: +7 (499) 144-98-08_x000D_ +7 (499) 144-97-82 | E99: https://kad.arbitr.ru/Card/7c442fe1-9213-4fb7-8003-c6c00e2facf8 | F99: А40-36216/2024 | G99: Департамент городского Имущества Города Москвы | H99: 7705031674 | I99: ООО НПКК "М & к" | J99: 7730030219 | K99: Коломийцев Владимир Андреевич | L99: 500101746180 | M99: 7747254.8 | N99: 45344 | O99: 18 | P99: 121293, город Москва, пл. Победы, д.1 к.б | Q99: АС города Москвы | R99: Техническое обслуживание и ремонт автотранспортных средств (45.2) | S99: ДЕПАРТАМЕНТ ГОРОДСКОГО ИМУЩЕСТВА ГОРОДА МОСКВЫ | U99: ОБЩЕСТВО С ОГРАНИЧЕННОЙ ОТВЕТСТВЕННОСТЬЮ НАУЧНО-ПРОИЗВОДСТВЕННАЯ КОММЕРЧЕСКАЯ КОМПАНИЯ "М & К" | W99: Заявление Исковое заявление
A100: =SUBTOTAL(103,$F$1:F100)-1 -> 99 | E100: https://kad.arbitr.ru/Card/b0c9a0f2-bafb-486d-bb73-b7952f8af4e3 | F100: А40-36199/2024 | G100: ООО"Группа Полимертепло" | H100: 7706163360 | I100: ООО "Инженерные Решения" | J100: 2312293170 | K100: Семкин Александр Сергеевич | L100: 231294310721 | M100: 4546705.5 | N100: 45344 | O100: 1 | P100: 350059, Краснодарский край, город Краснодар, Уральская ул., д. 85, офис 7 | Q100: АС города Москвы | R100: Торговля оптовая прочими потребительскими товарами, не включенными в другие группировки (46.49.49) | S100: ОБЩЕСТВО С ОГРАНИЧЕННОЙ ОТВЕТСТВЕННОСТЬЮ"ГРУППА ПОЛИМЕРТЕПЛО" | U100: ОБЩЕСТВО С ОГРАНИЧЕННОЙ ОТВЕТСТВЕННОСТЬЮ "ИНЖЕНЕРНЫЕ РЕШЕНИЯ" | W100: Заявление Исковое заявление
...

Sheet Рассылка
A1: Телефон | B1: Номер дела | C1: Истец сокращенно | D1: Ответчик сокращенно | E1: ИО руководителя ответчика | F1: Сумма иска | G1: Дата подачи иска | H1: Руководитель ответчика
A2: =IF(COUNTIF(Дела!$A:$A,ROW()-1)>0,VLOOKUP(ROW()-1,Дела!$A:$C,3,0),"") -> +7 (910) 131-18-94_x000D_ +7 (910) 143-33-00 | B2: =IF(COUNTIF(Дела!$A:$A,ROW()-1)>0,VLOOKUP(ROW()-1,Дела!$A:$F,6,0),"") -> А40-34987/2024 | C2: =IF(COUNTIF(Дела!$A:$A,ROW()-1)>0,VLOOKUP(ROW()-1,Дела!$A:$G,7,0),"") -> ООО "Комплексная Безопасность" | D2: =IF(COUNTIF(Дела!$A:$A,ROW()-1)>0,VLOOKUP(ROW()-1,Дела!$A:$I,9,0),"") -> ООО "Артал Строй" | E2: =IF(H2="","",MID(H2,SEARCH(" ",H2)+1,1000)) -> Артем Игоревич | F2: =IF(COUNTIF(Дела!$A:$A,ROW()-1)>0,VLOOKUP(ROW()-1,Дела!$A:$M,13,0),"") -> 4489799 | G2: =IF(COUNTIF(Дела!$A:$A,ROW()-1)>0,VLOOKUP(ROW()-1,Дела!$A:$N,14,0),"") -> 45342 | H2: =IF(COUNTIF(Дела!$A:$A,ROW()-1)>0,VLOOKUP(ROW()-1,Дела!$A:$K,11,0),"") -> Родионов Артем Игоревич
A3: =IF(COUNTIF(Дела!$A:$A,ROW()-1)>0,VLOOKUP(ROW()-1,Дела!$A:$C,3,0),"") -> 0 | B3: =IF(COUNTIF(Дела!$A:$A,ROW()-1)>0,VLOOKUP(ROW()-1,Дела!$A:$F,6,0),"") -> А40-34970/2024 | C3: =IF(COUNTIF(Дела!$A:$A,ROW()-1)>0,VLOOKUP(ROW()-1,Дела!$A:$G,7,0),"") -> ИФНС России № 10 по Г. Москве | D3: =IF(COUNTIF(Дела!$A:$A,ROW()-1)>0,VLOOKUP(ROW()-1,Дела!$A:$I,9,0),"") -> ООО "Фортуна" | E3: =IF(H3="","",MID(H3,SEARCH(" ",H3)+1,1000)) -> Олча Май Оглу | F3: =IF(COUNTIF(Дела!$A:$A,ROW()-1)>0,VLOOKUP(ROW()-1,Дела!$A:$M,13,0),"") -> 3174989.9 | G3: =IF(COUNTIF(Дела!$A:$A,ROW()-1)>0,VLOOKUP(ROW()-1,Дела!$A:$N,14,0),"") -> 45342 | H3: =IF(COUNTIF(Дела!$A:$A,ROW()-1)>0,VLOOKUP(ROW()-1,Дела!$A:$K,11,0),"") -> Ооржак Олча Май Оглу
A4: =IF(COUNTIF(Дела!$A:$A,ROW()-1)>0,VLOOKUP(ROW()-1,Дела!$A:$C,3,0),"") -> +7 (499) 262-99-01_x000D_ +7 (499) 262-10-02_x000D_ 8 (800) 775-00-00_x000D_ +7 (4852) 52-18-30_x000D_ +7 (3012) 28-25-04_x000D_ +7 (3022) 22-33-05_x000D_ +7 (3022) 22-46-03_x000D_ +7 (3022) 22-46-72_x000D_ +7 (3022) 22-75-05_x000D_ +7 (3022) 24-18-00_x000D_ +7 (3022) 24-22-25_x000D_ +7 (3022) 24-45-58_x000D_ +7 (30241) 2-40-54_x000D_ +7 (342) 230-22-25_x000D_ +7 (343) 358-22-25_x000D_ +7 (343) 358-22-60_x000D_ +7 (343) 358-29-32_x000D_ +7 (343) 358-40-88_x000D_ +7 (343) 358-44-00_x000D_ +7 (343) 358-48-10_x000D_ +7 (343) 358-48-48_x000D_ +7 (343) 358-48-89_x000D_ +7 (343) 358-57-27_x000D_ +7 (343) 380-14-74_x000D_ +7 (343) 380-17-54_x000D_ +7 (3435) 49-42-39_x000D_ +7 (3452) 52-31-40_x000D_ +7 (3452) 52-38-48_x000D_ +7 (3462) 39-35-33_x000D_ +7 (347) 229-63-15_x000D_ +7 (347) 253-14-52_x000D_ +7 (351) 259-29-04_x000D_ +7 (351) 263-84-82_x000D_ +7 (351) 268-21-40_x000D_ +7 (351) 268-39-12_x000D_ +7 (351) 268-65-09_x000D_ +7 (3513) 69-21-40_x000D_ +7 (3812) 44-30-79_x000D_ +7 (383) 229-20-20_x000D_ +7 (383) 229-36-02_x000D_ +7 (383) 229-48-02_x000D_ +7 (383) 229-50-27_x000D_ +7 (383) 334-02-43_x000D_ +7 (3842) 32-23-79_x000D_ +7 (3842) 32-39-50_x000D_ +7 (3852) 29-20-48_x000D_ +7 (3902) 29-45-66_x000D_ +7 (3912) 23-13-28_x000D_ +7 (3912) 48-04-35_x000D_ +7 (3912) 48-05-59_x000D_ +7 (3912) 59-52-98_x000D_ +7 (3952) 63-22-46_x000D_ +7 (3952) 63-42-66_x000D_ +7 (3952) 63-84-79_x000D_ +7 (3952) 64-42-46_x000D_ +7 (3952) 64-48-48_x000D_ +7 (3952) 64-51-55_x000D_ +7 (3953) 49-79-79_x000D_ +7 (4012) 58-61-01_x000D_ +7 (4012) 58-72-02_x000D_ +7 (41656) 7-20-00_x000D_ +7 (4212) 38-12-27_x000D_ +7 (4212) 38-37-18_x000D_ +7 (4212) 38-38-80_x000D_ +7 (4212) 38-41-36_x000D_ +7 (4212) 38-47-19_x000D_ +7 (4212) 38-48-43_x000D_ +7 (4212) 38-48-48_x000D_ +7 (4212) 38-53-57_x000D_ +7 (4212) 38-81-91_x000D_ +7 (4212) 38-88-34_x000D_ +7 (4712) 55-23-00_x000D_ +7 (4712) 55-57-54_x000D_ +7 (4722) 76-03-04_x000D_ +7 (4722) 76-05-25_x000D_ +7 (4732) 48-83-14_x000D_ +7 (4732) 65-08-10_x000D_ +7 (4732) 65-08-28_x000D_ +7 (4732) 65-22-64_x000D_ +7 (4732) 65-23-51_x000D_ +7 (4732) 65-28-32_x000D_ +7 (4732) 65-38-34_x000D_ +7 (4732) 65-44-50_x000D_ +7 (4732) 65-66-22_x000D_ +7 (4732) 65-72-81_x000D_ +7 (47391) 4-17-26_x000D_ +7 (47391) 7-59-64_x000D_ +7 (47545) 3-21-40_x000D_ +7 (47545) 3-22-76_x000D_ +7 (4812) 39-52-25_x000D_ +7 (4842) 78-52-95_x000D_ +7 (4852) 49-50-02_x000D_ +7 (4852) 52-40-86_x000D_ +7 (4852) 52-52-43_x000D_ +7 (4852) 79-22-41_x000D_ +7 (4852) 79-35-60_x000D_ +7 (4852) 79-43-14_x000D_ +7 (4852) 79-44-00_x000D_ +7 (4872) 20-20-80_x000D_ +7 (4872) 20-20-93 | B4: =IF(COUNTIF(Дела!$A:$A,ROW()-1)>0,VLOOKUP(ROW()-1,Дела!$A:$F,6,0),"") -> А40-34838/2024 | C4: =IF(COUNTIF(Дела!$A:$A,ROW()-1)>0,VLOOKUP(ROW()-1,Дела!$A:$G,7,0),"") -> АО "Нефтетранссервис" | D4: =IF(COUNTIF(Дела!$A:$A,ROW()-1)>0,VLOOKUP(ROW()-1,Дела!$A:$I,9,0),"") -> ОАО "РЖД" | E4: =IF(H4="","",MID(H4,SEARCH(" ",H4)+1,1000)) -> Олег Валентинович | F4: =IF(COUNTIF(Дела!$A:$A,ROW()-1)>0,VLOOKUP(ROW()-1,Дела!$A:$M,13,0),"") -> 1118159 | G4: =IF(COUNTIF(Дела!$A:$A,ROW()-1)>0,VLOOKUP(ROW()-1,Дела!$A:$N,14,0),"") -> 45342 | H4: =IF(COUNTIF(Дела!$A:$A,ROW()-1)>0,VLOOKUP(ROW()-1,Дела!$A:$K,11,0),"") -> Белозёров Олег Валентинович
A5: =IF(COUNTIF(Дела!$A:$A,ROW()-1)>0,VLOOKUP(ROW()-1,Дела!$A:$C,3,0),"") -> +7 (916) 428-25-05 | B5: =IF(COUNTIF(Дела!$A:$A,ROW()-1)>0,VLOOKUP(ROW()-1,Дела!$A:$F,6,0),"") -> А40-34726/2024 | C5: =IF(COUNTIF(Дела!$A:$A,ROW()-1)>0,VLOOKUP(ROW()-1,Дела!$A:$G,7,0),"") -> ООО "Акрополь Инжиниринг" | D5: =IF(COUNTIF(Дела!$A:$A,ROW()-1)>0,VLOOKUP(ROW()-1,Дела!$A:$I,9,0),"") -> ООО "НЖС" | E5: =IF(H5="","",MID(H5,SEARCH(" ",H5)+1,1000)) -> Константин Юрьевич | F5: =IF(COUNTIF(Дела!$A:$A,ROW()-1)>0,VLOOKUP(ROW()-1,Дела!$A:$M,13,0),"") -> 4306490.7 | G5: =IF(COUNTIF(Дела!$A:$A,ROW()-1)>0,VLOOKUP(ROW()-1,Дела!$A:$N,14,0),"") -> 45342 | H5: =IF(COUNTIF(Дела!$A:$A,ROW()-1)>0,VLOOKUP(ROW()-1,Дела!$A:$K,11,0),"") -> Шевацуков Константин Юрьевич
A6: =IF(COUNTIF(Дела!$A:$A,ROW()-1)>0,VLOOKUP(ROW()-1,Дела!$A:$C,3,0),"") -> 0 | B6: =IF(COUNTIF(Дела!$A:$A,ROW()-1)>0,VLOOKUP(ROW()-1,Дела!$A:$F,6,0),"") -> А40-34801/2024 | C6: =IF(COUNTIF(Дела!$A:$A,ROW()-1)>0,VLOOKUP(ROW()-1,Дела!$A:$G,7,0),"") -> ООО "Екс-Групп" | D6: =IF(COUNTIF(Дела!$A:$A,ROW()-1)>0,VLOOKUP(ROW()-1,Дела!$A:$I,9,0),"") -> ИП Гасангусейнов Вазир Султанович | E6: =IF(H6="","",MID(H6,SEARCH(" ",H6)+1,1000)) -> Вазир Султанович | F6: =IF(COUNTIF(Дела!$A:$A,ROW()-1)>0,VLOOKUP(ROW()-1,Дела!$A:$M,13,0),"") -> 611481 | G6: =IF(COUNTIF(Дела!$A:$A,ROW()-1)>0,VLOOKUP(ROW()-1,Дела!$A:$N,14,0),"") -> 45342 | H6: =IF(COUNTIF(Дела!$A:$A,ROW()-1)>0,VLOOKUP(ROW()-1,Дела!$A:$K,11,0),"") -> Гасангусейнов Вазир Султанович
A7: =IF(COUNTIF(Дела!$A:$A,ROW()-1)>0,VLOOKUP(ROW()-1,Дела!$A:$C,3,0),"") -> +7 (495) 120-28-80 | B7: =IF(COUNTIF(Дела!$A:$A,ROW()-1)>0,VLOOKUP(ROW()-1,Дела!$A:$F,6,0),"") -> А40-34707/2024 | C7: =IF(COUNTIF(Дела!$A:$A,ROW()-1)>0,VLOOKUP(ROW()-1,Дела!$A:$G,7,0),"") -> Департамент городского Имущества Города Москвы | D7: =IF(COUNTIF(Дела!$A:$A,ROW()-1)>0,VLOOKUP(ROW()-1,Дела!$A:$I,9,0),"") -> ООО "Горячий Ключ" | E7: =IF(H7="","",MID(H7,SEARCH(" ",H7)+1,1000)) -> Алигулу Ильгар Оглы | F7: =IF(COUNTIF(Дела!$A:$A,ROW()-1)>0,VLOOKUP(ROW()-1,Дела!$A:$M,13,0),"") -> 663120.56 | G7: =IF(COUNTIF(Дела!$A:$A,ROW()-1)>0,VLOOKUP(ROW()-1,Дела!$A:$N,14,0),"") -> 45342 | H7: =IF(COUNTIF(Дела!$A:$A,ROW()-1)>0,VLOOKUP(ROW()-1,Дела!$A:$K,11,0),"") -> Асгарли Алигулу Ильгар Оглы
A8: =IF(COUNTIF(Дела!$A:$A,ROW()-1)>0,VLOOKUP(ROW()-1,Дела!$A:$C,3,0),"") -> +7 (499) 260-40-00_x000D_ +7 (4832) 60-55-48_x000D_ +7 (4832) 63-02-26_x000D_ +7 (4832) 60-22-22_x000D_ +7 (3955) 75-57-30_x000D_ +7 (3955) 75-57-33_x000D_ +7 (3955) 76-14-06_x000D_ +7 (499) 262-28-46_x000D_ +7 (950) 089-92-94_x000D_ +7 (3012) 28-21-71_x000D_ +7 (499) 260-40-50_x000D_ +7 (812) 436-61-53_x000D_ +7 (81837) 6-26-43_x000D_ +7 (84663) 2-19-75_x000D_ +7 (863) 259-08-48_x000D_ +7 (914) 176-98-95_x000D_ +7 (3955) 75-57-36_x000D_ +7 (950) 075-17-94_x000D_ +7 (812) 436-61-44_x000D_ +7 (383) 337-94-01_x000D_ +7 (3519) 44-72-22_x000D_ +7 (499) 260-71-22_x000D_ +7 (3012) 28-22-22_x000D_ +7 (3012) 28-22-58_x000D_ +7 (34256) 9-22-22_x000D_ +7 (343) 310-90-69_x000D_ +7 (343) 310-91-65_x000D_ +7 (34551) 5-22-22_x000D_ +7 (34551) 5-26-87_x000D_ +7 (3812) 44-20-61_x000D_ +7 (3812) 44-21-65_x000D_ +7 (3812) 44-99-33_x000D_ +7 (383) 229-92-87_x000D_ +7 (38448) 2-24-39_x000D_ +7 (38456) 7-37-64_x000D_ +7 (39563) 5-32-20_x000D_ +7 (39563) 5-38-40_x000D_ +7 (4212) 38-82-58_x000D_ +7 (4234) 25-30-35_x000D_ +7 (4234) 38-15-35_x000D_ +7 (42355) 4-24-21_x000D_ +7 (4725) 41-17-52_x000D_ +7 (47376) 2-27-34_x000D_ +7 (491) 375-16-26_x000D_ +7 (49644) 2-47-55_x000D_ +7 (49644) 2-55-55_x000D_ +7 (499) 623-51-40_x000D_ +7 (499) 623-51-62_x000D_ +7 (8112) 70-71-11_x000D_ +7 (8112) 70-79-08_x000D_ +7 (81361) 2-01-06_x000D_ +7 (81361) 2-80-04_x000D_ +7 (8142) 79-36-04_x000D_ +7 (8142) 79-36-75_x000D_ +7 (81533) 3-36-04_x000D_ +7 (81533) 4-33-02_x000D_ +7 (8172) 79-69-61_x000D_ +7 (81837) 6-22-22_x000D_ +7 (831) 248-52-22_x000D_ +7 (833) 260-52-22_x000D_ +7 (833) 260-61-00_x000D_ +7 (8412) 58-72-22_x000D_ +7 (8412) 58-72-64_x000D_ +7 (8452) 41-38-69_x000D_ +7 (8452) 41-75-09_x000D_ +7 (846) 303-95-00_x000D_ +7 (846) 303-95-39_x000D_ +7 (8464) 33-32-80, доб 6_x000D_ +7 (8464) 33-38-40, доб 6_x000D_ +7 (84663) 2-19-74_x000D_ +7 (8512) 32-52-55_x000D_ +7 (8612) 14-79-14_x000D_ +7 (863) 259-08-50_x000D_ +7 (863) 259-48-91_x000D_ +7 (86354) 4-54-37_x000D_ +7 (911) 957-27-96_x000D_ +7 (915) 607-33-06_x000D_ +7 (918) 508-91-11_x000D_ +7 (960) 993-79-10_x000D_ +7 (984) 277-02-89_x000D_ +7 (499) 260-00-00_x000D_ +7 (3955) 77-26-10_x000D_ +7 (4832) 60-32-33, доб 7070_x000D_ +7 (4832) 60-39-49_x000D_ +7 (4832) 60-22-56_x000D_ +7 (499) 260-49-09_x000D_ +7 (499) 260-49-66_x000D_ +7 (86354) 4-23-61_x000D_ +7 (499) 262-66-66_x000D_ +7 (846) 303-95-02, доб 303_x000D_ +7 (950) 630-39-53, доб 9_x000D_ +7 (495) 260-40-00_x000D_ +7 (499) 262-00-58_x000D_ +7 (4212) 31-58-56_x000D_ +7 (39173) 9-31-97_x000D_ +7 (846) 303-95-02_x000D_ +7 (812) 457-53-88_x000D_ +7 (812) 436-20-36_x000D_ +7 (911) 848-78-23_x000D_ +7 (499) 260-40-68 | B8: =IF(COUNTIF(Дела!$A:$A,ROW()-1)>0,VLOOKUP(ROW()-1,Дела!$A:$F,6,0),"") -> А40-34588/2024 | C8: =IF(COUNTIF(Дела!$A:$A,ROW()-1)>0,VLOOKUP(ROW()-1,Дела!$A:$G,7,0),"") -> АО "Уголь-Транс" | D8: =IF(COUNTIF(Дела!$A:$A,ROW()-1)>0,VLOOKUP(ROW()-1,Дела!$A:$I,9,0),"") -> АО "ВРК-1" | E8: =IF(H8="","",MID(H8,SEARCH(" ",H8)+1,1000)) -> Владимир Николаевич | F8: =IF(COUNTIF(Дела!$A:$A,ROW()-1)>0,VLOOKUP(ROW()-1,Дела!$A:$M,13,0),"") -> 744855.11 | G8: =IF(COUNTIF(Дела!$A:$A,ROW()-1)>0,VLOOKUP(ROW()-1,Дела!$A:$N,14,0),"") -> 45342 | H8: =IF(COUNTIF(Дела!$A:$A,ROW()-1)>0,VLOOKUP(ROW()-1,Дела!$A:$K,11,0),"") -> Белюгин Владимир Николаевич
A9: =IF(COUNTIF(Дела!$A:$A,ROW()-1)>0,VLOOKUP(ROW()-1,Дела!$A:$C,3,0),"") -> 0 | B9: =IF(COUNTIF(Дела!$A:$A,ROW()-1)>0,VLOOKUP(ROW()-1,Дела!$A:$F,6,0),"") -> А40-34679/2024 | C9: =IF(COUNTIF(Дела!$A:$A,ROW()-1)>0,VLOOKUP(ROW()-1,Дела!$A:$G,7,0),"") -> Ассоциация СРО "Центррегион" | D9: =IF(COUNTIF(Дела!$A:$A,ROW()-1)>0,VLOOKUP(ROW()-1,Дела!$A:$I,9,0),"") -> ООО "Бизнес-Капитал" | E9: =IF(H9="","",MID(H9,SEARCH(" ",H9)+1,1000)) -> Дмитрий Александрович | F9: =IF(COUNTIF(Дела!$A:$A,ROW()-1)>0,VLOOKUP(ROW()-1,Дела!$A:$M,13,0),"") -> 506700 | G9: =IF(COUNTIF(Дела!$A:$A,ROW()-1)>0,VLOOKUP(ROW()-1,Дела!$A:$N,14,0),"") -> 45342 | H9: =IF(COUNTIF(Дела!$A:$A,ROW()-1)>0,VLOOKUP(ROW()-1,Дела!$A:$K,11,0),"") -> Холоднюк Дмитрий Александрович
A10: =IF(COUNTIF(Дела!$A:$A,ROW()-1)>0,VLOOKUP(ROW()-1,Дела!$A:$C,3,0),"") -> +7 (495) 699-72-50_x000D_ +7 (495) 959-18-02_x000D_ +7 (495) 331-02-22_x000D_ +7 (495) 587-70-87_x000D_ +7 (495) 625-45-13_x000D_ +7 (495) 634-01-27_x000D_ +7 (495) 675-46-24_x000D_ +7 (495) 953-21-56_x000D_ +7 (495) 957-75-00_x000D_ +7 (495) 959-09-75_x000D_ +7 (495) 959-19-03_x000D_ +7 (495) 959-19-13_x000D_ +7 (495) 959-19-59_x000D_ +7 (495) 959-53-39_x000D_ +7 (499) 268-56-70_x000D_ +7 (499) 380-80-84_x000D_ +7 (495) 625-45-15_x000D_ +7 (495) 777-77-77_x000D_ +7 (495) 699-20-48_x000D_ +7 (495) 362-14-63_x000D_ +7 (495) 959-19-82_x000D_ +7 (495) 957-98-53_x000D_ +7 (499) 648-05-64_x000D_ +7 (495) 959-18-88_x000D_ +7 (499) 233-97-39_x000D_ +7 (495) 959-19-55_x000D_ +7 (495) 955-53-08_x000D_ +7 (495) 122-19-27, доб 1302_x000D_ +7 (495) 955-53-79_x000D_ +7 (495) 955-51-96_x000D_ +7 (495) 955-53-68_x000D_ +7 (495) 142-12-32_x000D_ +7 (499) 649-39-23_x000D_ +7 (499) 959-18-02_x000D_ +7 (495) 959-18-22_x000D_ +7 (495) 777-77-77, доб 7_x000D_ +7 (499) 000-00-00_x000D_ +7 (495) 957-99-77 | B10: =IF(COUNTIF(Дела!$A:$A,ROW()-1)>0,VLOOKUP(ROW()-1,Дела!$A:$F,6,0),"") -> А40-34515/2024 | C10: =IF(COUNTIF(Дела!$A:$A,ROW()-1)>0,VLOOKUP(ROW()-1,Дела!$A:$G,7,0),"") -> АО "Специализированный Застройщик ТПУ "Рассказовка" | D10: =IF(COUNTIF(Дела!$A:$A,ROW()-1)>0,VLOOKUP(ROW()-1,Дела!$A:$I,9,0),"") -> Департамент городского Имущества Города Москвы | E10: =IF(H10="","",MID(H10,SEARCH(" ",H10)+1,1000)) -> Максим Федорович | F10: =IF(COUNTIF(Дела!$A:$A,ROW()-1)>0,VLOOKUP(ROW()-1,Дела!$A:$M,13,0),"") -> 330346000 | G10: =IF(COUNTIF(Дела!$A:$A,ROW()-1)>0,VLOOKUP(ROW()-1,Дела!$A:$N,14,0),"") -> 45342 | H10: =IF(COUNTIF(Дела!$A:$A,ROW()-1)>0,VLOOKUP(ROW()-1,Дела!$A:$K,11,0),"") -> Гаман Максим Федорович
A11: =IF(COUNTIF(Дела!$A:$A,ROW()-1)>0,VLOOKUP(ROW()-1,Дела!$A:$C,3,0),"") -> +7 (499) 262-99-01_x000D_ +7 (499) 262-10-02_x000D_ 8 (800) 775-00-00_x000D_ +7 (4852) 52-18-30_x000D_ +7 (3012) 28-25-04_x000D_ +7 (3022) 22-33-05_x000D_ +7 (3022) 22-46-03_x000D_ +7 (3022) 22-46-72_x000D_ +7 (3022) 22-75-05_x000D_ +7 (3022) 24-18-00_x000D_ +7 (3022) 24-22-25_x000D_ +7 (3022) 24-45-58_x000D_ +7 (30241) 2-40-54_x000D_ +7 (342) 230-22-25_x000D_ +7 (343) 358-22-25_x000D_ +7 (343) 358-22-60_x000D_ +7 (343) 358-29-32_x000D_ +7 (343) 358-40-88_x000D_ +7 (343) 358-44-00_x000D_ +7 (343) 358-48-10_x000D_ +7 (343) 358-48-48_x000D_ +7 (343) 358-48-89_x000D_ +7 (343) 358-57-27_x000D_ +7 (343) 380-14-74_x000D_ +7 (343) 380-17-54_x000D_ +7 (3435) 49-42-39_x000D_ +7 (3452) 52-31-40_x000D_ +7 (3452) 52-38-48_x000D_ +7 (3462) 39-35-33_x000D_ +7 (347) 229-63-15_x000D_ +7 (347) 253-14-52_x000D_ +7 (351) 259-29-04_x000D_ +7 (351) 263-84-82_x000D_ +7 (351) 268-21-40_x000D_ +7 (351) 268-39-12_x000D_ +7 (351) 268-65-09_x000D_ +7 (3513) 69-21-40_x000D_ +7 (3812) 44-30-79_x000D_ +7 (383) 229-20-20_x000D_ +7 (383) 229-36-02_x000D_ +7 (383) 229-48-02_x000D_ +7 (383) 229-50-27_x000D_ +7 (383) 334-02-43_x000D_ +7 (3842) 32-23-79_x000D_ +7 (3842) 32-39-50_x000D_ +7 (3852) 29-20-48_x000D_ +7 (3902) 29-45-66_x000D_ +7 (3912) 23-13-28_x000D_ +7 (3912) 48-04-35_x000D_ +7 (3912) 48-05-59_x000D_ +7 (3912) 59-52-98_x000D_ +7 (3952) 63-22-46_x000D_ +7 (3952) 63-42-66_x000D_ +7 (3952) 63-84-79_x000D_ +7 (3952) 64-42-46_x000D_ +7 (3952) 64-48-48_x000D_ +7 (3952) 64-51-55_x000D_ +7 (3953) 49-79-79_x000D_ +7 (4012) 58-61-01_x000D_ +7 (4012) 58-72-02_x000D_ +7 (41656) 7-20-00_x000D_ +7 (4212) 38-12-27_x000D_ +7 (4212) 38-37-18_x000D_ +7 (4212) 38-38-80_x000D_ +7 (4212) 38-41-36_x000D_ +7 (4212) 38-47-19_x000D_ +7 (4212) 38-48-43_x000D_ +7 (4212) 38-48-48_x000D_ +7 (4212) 38-53-57_x000D_ +7 (4212) 38-81-91_x000D_ +7 (4212) 38-88-34_x000D_ +7 (4712) 55-23-00_x000D_ +7 (4712) 55-57-54_x000D_ +7 (4722) 76-03-04_x000D_ +7 (4722) 76-05-25_x000D_ +7 (4732) 48-83-14_x000D_ +7 (4732) 65-08-10_x000D_ +7 (4732) 65-08-28_x000D_ +7 (4732) 65-22-64_x000D_ +7 (4732) 65-23-51_x000D_ +7 (4732) 65-28-32_x000D_ +7 (4732) 65-38-34_x000D_ +7 (4732) 65-44-50_x000D_ +7 (4732) 65-66-22_x000D_ +7 (4732) 65-72-81_x000D_ +7 (47391) 4-17-26_x000D_ +7 (47391) 7-59-64_x000D_ +7 (47545) 3-21-40_x000D_ +7 (47545) 3-22-76_x000D_ +7 (4812) 39-52-25_x000D_ +7 (4842) 78-52-95_x000D_ +7 (4852) 49-50-02_x000D_ +7 (4852) 52-40-86_x000D_ +7 (4852) 52-52-43_x000D_ +7 (4852) 79-22-41_x000D_ +7 (4852) 79-35-60_x000D_ +7 (4852) 79-43-14_x000D_ +7 (4852) 79-44-00_x000D_ +7 (4872) 20-20-80_x000D_ +7 (4872) 20-20-93 | B11: =IF(COUNTIF(Дела!$A:$A,ROW()-1)>0,VLOOKUP(ROW()-1,Дела!$A:$F,6,0),"") -> А40-34376/2024 | C11: =IF(COUNTIF(Дела!$A:$A,ROW()-1)>0,VLOOKUP(ROW()-1,Дела!$A:$G,7,0),"") -> ООО "Сапфир-Агро" | D11: =IF(COUNTIF(Дела!$A:$A,ROW()-1)>0,VLOOKUP(ROW()-1,Дела!$A:$I,9,0),"") -> ОАО "РЖД" | E11: =IF(H11="","",MID(H11,SEARCH(" ",H11)+1,1000)) -> Олег Валентинович | F11: =IF(COUNTIF(Дела!$A:$A,ROW()-1)>0,VLOOKUP(ROW()-1,Дела!$A:$M,13,0),"") -> 731393 | G11: =IF(COUNTIF(Дела!$A:$A,ROW()-1)>0,VLOOKUP(ROW()-1,Дела!$A:$N,14,0),"") -> 45342 | H11: =IF(COUNTIF(Дела!$A:$A,ROW()-1)>0,VLOOKUP(ROW()-1,Дела!$A:$K,11,0),"") -> Белозёров Олег Валентинович
A12: =IF(COUNTIF(Дела!$A:$A,ROW()-1)>0,VLOOKUP(ROW()-1,Дела!$A:$C,3,0),"") -> 0 | B12: =IF(COUNTIF(Дела!$A:$A,ROW()-1)>0,VLOOKUP(ROW()-1,Дела!$A:$F,6,0),"") -> А40-34438/2024 | C12: =IF(COUNTIF(Дела!$A:$A,ROW()-1)>0,VLOOKUP(ROW()-1,Дела!$A:$G,7,0),"") -> АО "Трест КХМ" | D12: =IF(COUNTIF(Дела!$A:$A,ROW()-1)>0,VLOOKUP(ROW()-1,Дела!$A:$I,9,0),"") -> ООО "Аэрогаз" | E12: =IF(H12="","",MID(H12,SEARCH(" ",H12)+1,1000)) -> Салават Зайнетдинович | F12: =IF(COUNTIF(Дела!$A:$A,ROW()-1)>0,VLOOKUP(ROW()-1,Дела!$A:$M,13,0),"") -> 3706461.5 | G12: =IF(COUNTIF(Дела!$A:$A,ROW()-1)>0,VLOOKUP(ROW()-1,Дела!$A:$N,14,0),"") -> 45342 | H12: =IF(COUNTIF(Дела!$A:$A,ROW()-1)>0,VLOOKUP(ROW()-1,Дела!$A:$K,11,0),"") -> Имаев Салават Зайнетдинович
A13: =IF(COUNTIF(Дела!$A:$A,ROW()-1)>0,VLOOKUP(ROW()-1,Дела!$A:$C,3,0),"") -> +7 (49679) 6-13-80_x000D_ +7 (49679) 6-13-79 | B13: =IF(COUNTIF(Дела!$A:$A,ROW()-1)>0,VLOOKUP(ROW()-1,Дела!$A:$F,6,0),"") -> А40-34333/2024 | C13: =IF(COUNTIF(Дела!$A:$A,ROW()-1)>0,VLOOKUP(ROW()-1,Дела!$A:$G,7,0),"") -> АО "Мосэнергосбыт" | D13: =IF(COUNTIF(Дела!$A:$A,ROW()-1)>0,VLOOKUP(ROW()-1,Дела!$A:$I,9,0),"") -> ОАО "Заря-Жилсервис" | E13: =IF(H13="","",MID(H13,SEARCH(" ",H13)+1,1000)) -> Александр Борисович | F13: =IF(COUNTIF(Дела!$A:$A,ROW()-1)>0,VLOOKUP(ROW()-1,Дела!$A:$M,13,0),"") -> 1360795.4 | G13: =IF(COUNTIF(Дела!$A:$A,ROW()-1)>0,VLOOKUP(ROW()-1,Дела!$A:$N,14,0),"") -> 45342 | H13: =IF(COUNTIF(Дела!$A:$A,ROW()-1)>0,VLOOKUP(ROW()-1,Дела!$A:$K,11,0),"") -> Руднев Александр Борисович
... A600: =IF(COUNTIF(Дела!$A:$A,ROW()-1)>0,VLOOKUP(ROW()-1,Дела!$A:$C,3,0),"") | B600: =IF(COUNTIF(Дела!$A:$A,ROW()-1)>0,VLOOKUP(ROW()-1,Дела!$A:$F,6,0),"") | C600: =IF(COUNTIF(Дела!$A:$A,ROW()-1)>0,VLOOKUP(ROW()-1,Дела!$A:$G,7,0),"") | D600: =IF(COUNTIF(Дела!$A:$A,ROW()-1)>0,VLOOKUP(ROW()-1,Дела!$A:$I,9,0),"") | E600: =IF(H600="","",MID(H600,SEARCH(" ",H600)+1,1000)) | F600: =IF(COUNTIF(Дела!$A:$A,ROW()-1)>0,VLOOKUP(ROW()-1,Дела!$A:$M,13,0),"") | G600: =IF(COUNTIF(Дела!$A:$A,ROW()-1)>0,VLOOKUP(ROW()-1,Дела!$A:$N,14,0),"") | H600: =IF(COUNTIF(Дела!$A:$A,ROW()-1)>0,VLOOKUP(ROW()-1,Дела!$A:$K,11,0),"")
